Workbook
Name budget: 'Budget dashboard'!$L1
Name budget_range: 'Budget dashboard'!$Q1
Name budget_rank: 'Budget dashboard'!$R1
Name cc_budget: Calculations!$K1
Name cc_delta: Calculations!$L1
Name cc_in_focus: Calculations!$G1
Name cc_month_number: Calculations!$F1
Name cc_show_rem_budget: Calculations!$I1
Name cc_show_type: Calculations!$H1
Name cc_tracked: Calculations!$J1
Name cc_type: Calculations!$E1
Name comb_rank: 'Budget dashboard'!$S1
Name comb_rank_norm: 'Budget dashboard'!$U1
Name comb_rank_norm_run_range: 'Budget dashboard'!$V1
Name comb_rank_range: 'Budget dashboard'!$T1
Name comb_rank_unique: 'Budget dashboard'!$W1
Name current_date: TODAY()
Name expenses_header_row: ROW(Expenses[[#Headers],[Expenses]])
Name expenses_max_row: MAX(ROW(Expenses[]))
Name expenses_min_row: MIN(ROW(Expenses[]))
Name expenses_total_row: ROW('Budget Planning'!$C$30)
Name header_row_id: 'Budget dashboard'!$D1
Name income_header_row: ROW(Income[[#Headers],[Income]])
Name income_max_row: MAX(ROW(Income[]))
Name income_min_row: MIN(ROW(Income[]))
Name income_total_row: ROW('Budget Planning'!$C$20)
Name is_cat: 'Budget dashboard'!$F1
Name is_empty: 'Budget dashboard'!$H1
Name is_header: 'Budget dashboard'!$E1
Name is_total: 'Budget dashboard'!$G1
Name item: 'Budget dashboard'!$J1
Name left_money_loan: #REF!
Name loan_amount: #REF!
Name out_budget: 'Budget dashboard'!$AA1
Name out_percentage_completed: 'Budget dashboard'!$AB1
Name out_tracked: 'Budget dashboard'!$Z1
Name row_id: 'Budget dashboard'!$C1
Name savings_header_row: ROW(Savings[[#Headers],[Savings]])
Name savings_max_row: MAX(ROW(Savings[]))
Name savings_min_row: MIN(ROW(Savings[]))
Name savings_rate_calculation_type: Settings!$E$22
Name savings_total_row: ROW('Budget Planning'!$C$43)
Name selected_period: Calculations!$E$20
Name selected_period_display: Calculations!$E$21
Name selected_year: Calculations!$E$19
Name Shift_late_income_status: Settings!$E$16
Name Shift_late_starting_day: Settings!$E$18
Name sort_max_row: 'Budget dashboard'!$N1
Name sort_min_row: 'Budget dashboard'!$M1
Name starting_year: Settings!$E$8
Name tracked: 'Budget dashboard'!$K1
Name tracked_range: 'Budget dashboard'!$O1
Name tracked_rank: 'Budget dashboard'!$P1
Name type: 'Budget dashboard'!$I1

Sheet Settings
B1: Settings
C6: General
D8: Starting Year: | E8: 2025
C12: Budget Tracking & Dashboard
D14: Late Monthly Income
D16: Shift late Income: | E16: Active
D18: Starting on day x in month: | E18: 20
D20: KPI Calculation in Dashboard
D22: Savings Rate as % of Income: | E22: % not allocated to Expenses

Sheet Budget Planning
B1: Budget Planning
E5: =starting_year -> 2025 | S5: =E5+1 -> 2026 | AG5: =S5+1 -> 2027
E6: =IF(E7=0,"sty ✓", "sty") -> sty ✓ | F6: =IF(F7=0,"lut ✓", "lut") -> lut | G6: =IF(G7=0,"mar ✓", "mar") -> mar | H6: =IF(H7=0,"kwi ✓", "kwi") -> kwi | I6: =IF(I7=0,"maj ✓", "maj") -> maj | J6: =IF(J7=0,"cze ✓", "cze") -> cze | K6: =IF(K7=0,"lip ✓", "lip") -> lip | L6: =IF(L7=0,"sie ✓", "sie") -> sie | M6: =IF(M7=0,"wrz ✓", "wrz") -> wrz | N6: =IF(N7=0,"paż ✓", "paż") -> paż | O6: =IF(O7=0,"lis ✓", "lis") -> lis | P6: =IF(P7=0,"gru ✓", "gru") -> gru | Q6: =IF(Q7=0,"Total ✓", "Total") -> Total | S6: =IF(S7=0,"sty ✓", "sty") -> sty ✓ | T6: =IF(T7=0,"lut ✓", "lut") -> lut | U6: =IF(U7=0,"mar ✓", "mar") -> mar | V6: =IF(V7=0,"kwi ✓", "kwi") -> kwi | W6: =IF(W7=0,"maj ✓", "maj") -> maj | X6: =IF(X7=0,"cze ✓", "cze") -> cze | Y6: =IF(Y7=0,"lip ✓", "lip") -> lip | Z6: =IF(Z7=0,"sie ✓", "sie") -> sie | AA6: =IF(AA7=0,"wrz ✓", "wrz") -> wrz | AB6: =IF(AB7=0,"paż ✓", "paż") -> paż | AC6: =IF(AC7=0,"lis ✓", "lis") -> lis | AD6: =IF(AD7=0,"gru ✓", "gru") -> gru | AE6: =IF(AE7=0,"Total ✓", "Total") -> Total | AG6: =IF(AG7=0,"sty ✓", "sty") -> sty ✓ | AH6: =IF(AH7=0,"lut ✓", "lut") -> lut ✓ | AI6: =IF(AI7=0,"mar ✓", "mar") -> mar ✓ | AJ6: =IF(AJ7=0,"kwi ✓", "kwi") -> kwi ✓ | AK6: =IF(AK7=0,"maj ✓", "maj") -> maj ✓ | AL6: =IF(AL7=0,"cze ✓", "cze") -> cze ✓ | AM6: =IF(AM7=0,"lip ✓", "lip") -> lip ✓ | AN6: =IF(AN7=0,"sie ✓", "sie") -> sie ✓ | AO6: =IF(AO7=0,"wrz ✓", "wrz") -> wrz ✓ | AP6: =IF(AP7=0,"paż ✓", "paż") -> paż ✓ | AQ6: =IF(AQ7=0,"lis ✓", "lis") -> lis ✓ | AR6: =IF(AR7=0,"gru ✓", "gru") -> gru ✓ | AS6: =IF(AS7=0,"Total ✓", "Total") -> Total ✓
C7: To be allocated: | E7: =E20-(E30+E43) -> 0 | F7: =F20-(F30+F43) -> 600 | G7: =G20-(G30+G43) -> 350 | H7: =H20-(H30+H43) -> 650 | I7: =I20-(I30+I43) -> 650 | J7: =J20-(J30+J43) -> 2350 | K7: =K20-(K30+K43) -> 1750 | L7: =L20-(L30+L43) -> 1100 | ... Q7: =Q20-(Q30+Q43) -> 11750 | S7: =S20-(S30+S43) -> 0 | T7: =T20-(T30+T43) -> 600 | U7: =U20-(U30+U43) -> 350 | V7: =V20-(V30+V43) -> 650 | W7: =W20-(W30+W43) -> 650 | X7: =X20-(X30+X43) -> 2350 | Y7: =Y20-(Y30+Y43) -> 1750 | Z7: =Z20-(Z30+Z43) -> 1100 | ... AE7: =AE20-(AE30+AE43) -> 11750 | AG7: =AG20-(AG30+AG43) -> 0 | AH7: =AH20-(AH30+AH43) -> 0 | AI7: =AI20-(AI30+AI43) -> 0 | AJ7: =AJ20-(AJ30+AJ43) -> 0 | AK7: =AK20-(AK30+AK43) -> 0 | AL7: =AL20-(AL30+AL43) -> 0 | AM7: =AM20-(AM30+AM43) -> 0 | AN7: =AN20-(AN30+AN43) -> 0 | ... AS7: =AS20-(AS30+AS43) -> 0
C9: Income | E9: =DATE(E$5,1,1) -> 45658 | F9: =DATE(E$5,2,1) -> 45689 | G9: =DATE(E$5,3,1) -> 45717 | H9: =DATE(E$5,4,1) -> 45748 | I9: =DATE(E$5,5,1) -> 45778 | J9: =DATE(E$5,6,1) -> 45809 | K9: =DATE(E$5,7,1) -> 45839 | L9: =DATE(E$5,8,1) -> 45870 | M9: =DATE(E$5,9,1) -> 45901 | N9: =DATE(E$5,10,1) -> 45931 | O9: =DATE(E$5,11,1) -> 45962 | P9: =DATE(E$5,12,1) -> 45992 | Q9: =E5 -> 2025 | S9: =DATE(S$5,1,1) -> 46023 | T9: =DATE(S$5,2,1) -> 46054 | U9: =DATE(S$5,3,1) -> 46082 | V9: =DATE(S$5,4,1) -> 46113 | W9: =DATE(S$5,5,1) -> 46143 | X9: =DATE(S$5,6,1) -> 46174 | Y9: =DATE(S$5,7,1) -> 46204 | Z9: =DATE(S$5,8,1) -> 46235 | AA9: =DATE(S$5,9,1) -> 46266 | AB9: =DATE(S$5,10,1) -> 46296 | AC9: =DATE(S$5,11,1) -> 46327 | AD9: =DATE(S$5,12,1) -> 46357 | AE9: =S5 -> 2026 | AG9: =DATE(AG$5,1,1) -> 46388 | AH9: =DATE(AG$5,2,1) -> 46419 | AI9: =DATE(AG$5,3,1) -> 46447 | AJ9: =DATE(AG$5,4,1) -> 46478 | AK9: =DATE(AG$5,5,1) -> 46508 | AL9: =DATE(AG$5,6,1) -> 46539 | AM9: =DATE(AG$5,7,1) -> 46569 | AN9: =DATE(AG$5,8,1) -> 46600 | AO9: =DATE(AG$5,9,1) -> 46631 | AP9: =DATE(AG$5,10,1) -> 46661 | AQ9: =DATE(AG$5,11,1) -> 46692 | AR9: =DATE(AG$5,12,1) -> 46722 | AS9: =AG5 -> 2027
C10: Empoyment(Net) | E10: 8500 | F10: 8500 | G10: 8800 | H10: 8800 | I10: 8800 | J10: 8800 | K10: 8800 | L10: 9200 | M10: 9200 | N10: 9200 | O10: 8500 | P10: 9000 | Q10: =SUM(E10:P10) -> 106100 | S10: 8500 | T10: 8500 | U10: 8800 | V10: 8800 | W10: 8800 | X10: 8800 | Y10: 8800 | Z10: 9200 | AA10: 9200 | AB10: 9200 | AC10: 8500 | AD10: 9000 | AE10: =SUM(S10:AD10) -> 106100 | AS10: =SUM(AG10:AR10) -> 0
C11: Side Hustle(Net) | E11: 1200 | F11: 1800 | G11: 2100 | H11: 1500 | I11: 2400 | J11: 3100 | K11: 2800 | L11: 2200 | M11: 2900 | N11: 1800 | O11: 2550 | P11: 2400 | Q11: =SUM(E11:P11) -> 26750 | S11: 1200 | T11: 1800 | U11: 2100 | V11: 1500 | W11: 2400 | X11: 3100 | Y11: 2800 | Z11: 2200 | AA11: 2900 | AB11: 1800 | AC11: 2550 | AD11: 2400 | AE11: =SUM(S11:AD11) -> 26750 | AS11: =SUM(AG11:AR11) -> 0
C12: Dividents | E12: 50 | F12: 0 | G12: 450 | H12: 0 | I12: 0 | J12: 500 | K12: 0 | L12: 0 | M12: 350 | N12: 1000 | O12: 0 | P12: 1500 | Q12: =SUM(E12:P12) -> 3850 | S12: 50 | T12: 0 | U12: 450 | V12: 0 | W12: 0 | X12: 500 | Y12: 0 | Z12: 0 | AA12: 350 | AB12: 1000 | AC12: 0 | AD12: 1500 | AE12: =SUM(S12:AD12) -> 3850 | AS12: =SUM(AG12:AR12) -> 0
C13: Other | E13: 150 | F13: 300 | G13: 1000 | H13: 400 | I13: 200 | J13: 150 | K13: 600 | L13: 100 | M13: 250 | N13: 350 | O13: 0 | P13: 500 | Q13: =SUM(E13:P13) -> 4000 | S13: 150 | T13: 300 | U13: 1000 | V13: 400 | W13: 200 | X13: 150 | Y13: 600 | Z13: 100 | AA13: 250 | AB13: 350 | AC13: 0 | AD13: 500 | AE13: =SUM(S13:AD13) -> 4000 | AS13: =SUM(AG13:AR13) -> 0
C14: Enter Income Category… | Q14: =SUM(E14:P14) -> 0 | AE14: =SUM(S14:AD14) -> 0 | AS14: =SUM(AG14:AR14) -> 0
C15: Enter Income Category… | Q15: =SUM(E15:P15) -> 0 | AE15: =SUM(S15:AD15) -> 0 | AS15: =SUM(AG15:AR15) -> 0
C16: Enter Income Category… | Q16: =SUM(E16:P16) -> 0 | AE16: =SUM(S16:AD16) -> 0 | AS16: =SUM(AG16:AR16) -> 0
C17: Enter Income Category… | Q17: =SUM(E17:P17) -> 0 | AE17: =SUM(S17:AD17) -> 0 | AS17: =SUM(AG17:AR17) -> 0
C18: Enter Income Category… | Q18: =SUM(E18:P18) -> 0 | AE18: =SUM(S18:AD18) -> 0 | AS18: =SUM(AG18:AR18) -> 0
C19: Enter Income Category… | Q19: =SUM(E19:P19) -> 0 | AE19: =SUM(S19:AD19) -> 0 | AS19: =SUM(AG19:AR19) -> 0
C20: Total | E20: {=SUM(INDIRECT(ADDRESS(income_min_row,COLUMN()) & ":" & ADDRESS(income_max_row,COLUMN())))} -> 9900 | F20: {=SUM(INDIRECT(ADDRESS(income_min_row,COLUMN()) & ":" & ADDRESS(income_max_row,COLUMN())))} -> 10600 | G20: {=SUM(INDIRECT(ADDRESS(income_min_row,COLUMN()) & ":" & ADDRESS(income_max_row,COLUMN())))} -> 12350 | H20: {=SUM(INDIRECT(ADDRESS(income_min_row,COLUMN()) & ":" & ADDRESS(income_max_row,COLUMN())))} -> 10700 | I20: {=SUM(INDIRECT(ADDRESS(income_min_row,COLUMN()) & ":" & ADDRESS(income_max_row,COLUMN())))} -> 11400 | J20: {=SUM(INDIRECT(ADDRESS(income_min_row,COLUMN()) & ":" & ADDRESS(income_max_row,COLUMN())))} -> 12550 | K20: {=SUM(INDIRECT(ADDRESS(income_min_row,COLUMN()) & ":" & ADDRESS(income_max_row,COLUMN())))} -> 12200 | L20: {=SUM(INDIRECT(ADDRESS(income_min_row,COLUMN()) & ":" & ADDRESS(income_max_row,COLUMN())))} -> 11500 | ... Q20: {=SUM(INDIRECT(ADDRESS(income_min_row,COLUMN()) & ":" & ADDRESS(income_max_row,COLUMN())))} -> 140700 | S20: {=SUM(INDIRECT(ADDRESS(income_min_row,COLUMN()) & ":" & ADDRESS(income_max_row,COLUMN())))} -> 9900 | T20: {=SUM(INDIRECT(ADDRESS(income_min_row,COLUMN()) & ":" & ADDRESS(income_max_row,COLUMN())))} -> 10600 | U20: {=SUM(INDIRECT(ADDRESS(income_min_row,COLUMN()) & ":" & ADDRESS(income_max_row,COLUMN())))} -> 12350 | V20: {=SUM(INDIRECT(ADDRESS(income_min_row,COLUMN()) & ":" & ADDRESS(income_max_row,COLUMN())))} -> 10700 | W20: {=SUM(INDIRECT(ADDRESS(income_min_row,COLUMN()) & ":" & ADDRESS(income_max_row,COLUMN())))} -> 11400 | X20: {=SUM(INDIRECT(ADDRESS(income_min_row,COLUMN()) & ":" & ADDRESS(income_max_row,COLUMN())))} -> 12550 | Y20: {=SUM(INDIRECT(ADDRESS(income_min_row,COLUMN()) & ":" & ADDRESS(income_max_row,COLUMN())))} -> 12200 | Z20: {=SUM(INDIRECT(ADDRESS(income_min_row,COLUMN()) & ":" & ADDRESS(income_max_row,COLUMN())))} -> 11500 | ... AE20: {=SUM(INDIRECT(ADDRESS(income_min_row,COLUMN()) & ":" & ADDRESS(income_max_row,COLUMN())))} -> 140700 | AG20: {=SUM(INDIRECT(ADDRESS(income_min_row,COLUMN()) & ":" & ADDRESS(income_max_row,COLUMN())))} -> 0 | AH20: {=SUM(INDIRECT(ADDRESS(income_min_row,COLUMN()) & ":" & ADDRESS(income_max_row,COLUMN())))} -> 0 | AI20: {=SUM(INDIRECT(ADDRESS(income_min_row,COLUMN()) & ":" & ADDRESS(income_max_row,COLUMN())))} -> 0 | AJ20: {=SUM(INDIRECT(ADDRESS(income_min_row,COLUMN()) & ":" & ADDRESS(income_max_row,COLUMN())))} -> 0 | AK20: {=SUM(INDIRECT(ADDRESS(income_min_row,COLUMN()) & ":" & ADDRESS(income_max_row,COLUMN())))} -> 0 | AL20: {=SUM(INDIRECT(ADDRESS(income_min_row,COLUMN()) & ":" & ADDRESS(income_max_row,COLUMN())))} -> 0 | AM20: {=SUM(INDIRECT(ADDRESS(income_min_row,COLUMN()) & ":" & ADDRESS(income_max_row,COLUMN())))} -> 0 | AN20: {=SUM(INDIRECT(ADDRESS(income_min_row,COLUMN()) & ":" & ADDRESS(income_max_row,COLUMN())))} -> 0 | ... AS20: {=SUM(INDIRECT(ADDRESS(income_min_row,COLUMN()) & ":" & ADDRESS(income_max_row,COLUMN())))} -> 0
C22: Expenses | E22: =DATE(E$5,1,1) -> 45658 | F22: =DATE(E$5,2,1) -> 45689 | G22: =DATE(E$5,3,1) -> 45717 | H22: =DATE(E$5,4,1) -> 45748 | I22: =DATE(E$5,5,1) -> 45778 | J22: =DATE(E$5,6,1) -> 45809 | K22: =DATE(E$5,7,1) -> 45839 | L22: =DATE(E$5,8,1) -> 45870 | M22: =DATE(E$5,9,1) -> 45901 | N22: =DATE(E$5,10,1) -> 45931 | O22: =DATE(E$5,11,1) -> 45962 | P22: =DATE(E$5,12,1) -> 45992 | Q22: =E5 -> 2025 | S22: =DATE(S$5,1,1) -> 46023 | T22: =DATE(S$5,2,1) -> 46054 | U22: =DATE(S$5,3,1) -> 46082 | V22: =DATE(S$5,4,1) -> 46113 | W22: =DATE(S$5,5,1) -> 46143 | X22: =DATE(S$5,6,1) -> 46174 | Y22: =DATE(S$5,7,1) -> 46204 | Z22: =DATE(S$5,8,1) -> 46235 | AA22: =DATE(S$5,9,1) -> 46266 | AB22: =DATE(S$5,10,1) -> 46296 | AC22: =DATE(S$5,11,1) -> 46327 | AD22: =DATE(S$5,12,1) -> 46357 | AE22: =S5 -> 2026 | AG22: =DATE(AG$5,1,1) -> 46388 | AH22: =DATE(AG$5,2,1) -> 46419 | AI22: =DATE(AG$5,3,1) -> 46447 | AJ22: =DATE(AG$5,4,1) -> 46478 | AK22: =DATE(AG$5,5,1) -> 46508 | AL22: =DATE(AG$5,6,1) -> 46539 | AM22: =DATE(AG$5,7,1) -> 46569 | AN22: =DATE(AG$5,8,1) -> 46600 | AO22: =DATE(AG$5,9,1) -> 46631 | AP22: =DATE(AG$5,10,1) -> 46661 | AQ22: =DATE(AG$5,11,1) -> 46692 | AR22: =DATE(AG$5,12,1) -> 46722 | AS22: =AG5 -> 2027
C23: Housing | E23: 4200 | F23: 4200 | G23: 4200 | H23: 4200 | I23: 4200 | J23: 4200 | K23: 4200 | L23: 4200 | M23: 4200 | N23: 4200 | O23: 4200 | P23: 4200 | Q23: =SUM(E23:P23) -> 50400 | S23: 4200 | T23: 4200 | U23: 4200 | V23: 4200 | W23: 4200 | X23: 4200 | Y23: 4200 | Z23: 4200 | AA23: 4200 | AB23: 4200 | AC23: 4200 | AD23: 4200 | AE23: =SUM(S23:AD23) -> 50400 | AS23: =SUM(AG23:AR23) -> 0
C24: Groceries | E24: 1500 | F24: 1450 | G24: 1600 | H24: 1550 | I24: 1500 | J24: 1400 | K24: 1450 | L24: 1500 | M24: 1650 | N24: 1550 | O24: 1600 | P24: 1800 | Q24: =SUM(E24:P24) -> 18550 | S24: 1500 | T24: 1450 | U24: 1600 | V24: 1550 | W24: 1500 | X24: 1400 | Y24: 1450 | Z24: 1500 | AA24: 1650 | AB24: 1550 | AC24: 1600 | AD24: 1800 | AE24: =SUM(S24:AD24) -> 18550 | AS24: =SUM(AG24:AR24) -> 0
C25: Other | E25: 400 | F25: 350 | G25: 600 | H25: 450 | I25: 500 | J25: 300 | K25: 800 | L25: 450 | M25: 300 | N25: 550 | O25: 400 | P25: 900 | Q25: =SUM(E25:P25) -> 6000 | S25: 400 | T25: 350 | U25: 600 | V25: 450 | W25: 500 | X25: 300 | Y25: 800 | Z25: 450 | AA25: 300 | AB25: 550 | AC25: 400 | AD25: 900 | AE25: =SUM(S25:AD25) -> 6000 | AS25: =SUM(AG25:AR25) -> 0
C26: Transport | E26: 150 | F26: 150 | G26: 200 | H26: 150 | I26: 300 | J26: 250 | K26: 150 | L26: 150 | M26: 250 | N26: 150 | O26: 150 | P26: 300 | Q26: =SUM(E26:P26) -> 2350 | S26: 150 | T26: 150 | U26: 200 | V26: 150 | W26: 300 | X26: 250 | Y26: 150 | Z26: 150 | AA26: 250 | AB26: 150 | AC26: 150 | AD26: 300 | AE26: =SUM(S26:AD26) -> 2350 | AS26: =SUM(AG26:AR26) -> 0
C27: Studies | E27: 0 | F27: 0 | G27: 1500 | H27: 0 | I27: 0 | J27: 0 | K27: 0 | L27: 0 | M27: 0 | N27: 1500 | O27: 0 | P27: 500 | Q27: =SUM(E27:P27) -> 3500 | S27: 0 | T27: 0 | U27: 1500 | V27: 0 | W27: 0 | X27: 0 | Y27: 0 | Z27: 0 | AA27: 0 | AB27: 1500 | AC27: 0 | AD27: 500 | AE27: =SUM(S27:AD27) -> 3500 | AS27: =SUM(AG27:AR27) -> 0
C28: Technologies | E28: 150 | F28: 150 | G28: 150 | H28: 150 | I28: 450 | J28: 150 | K28: 150 | L28: 150 | M28: 150 | N28: 150 | O28: 150 | P28: 600 | Q28: =SUM(E28:P28) -> 2550 | S28: 150 | T28: 150 | U28: 150 | V28: 150 | W28: 450 | X28: 150 | Y28: 150 | Z28: 150 | AA28: 150 | AB28: 150 | AC28: 150 | AD28: 600 | AE28: =SUM(S28:AD28) -> 2550 | AS28: =SUM(AG28:AR28) -> 0
C29: Enter Expenses Category… | Q29: =SUM(E29:P29) -> 0 | AE29: =SUM(S29:AD29) -> 0 | AS29: =SUM(AG29:AR29) -> 0
C30: Total | E30: {=SUM(INDIRECT(ADDRESS(expenses_min_row,COLUMN()) & ":" & ADDRESS(expenses_max_row,COLUMN())))} -> 6400 | F30: {=SUM(INDIRECT(ADDRESS(expenses_min_row,COLUMN()) & ":" & ADDRESS(expenses_max_row,COLUMN())))} -> 6300 | G30: {=SUM(INDIRECT(ADDRESS(expenses_min_row,COLUMN()) & ":" & ADDRESS(expenses_max_row,COLUMN())))} -> 8250 | H30: {=SUM(INDIRECT(ADDRESS(expenses_min_row,COLUMN()) & ":" & ADDRESS(expenses_max_row,COLUMN())))} -> 6500 | I30: {=SUM(INDIRECT(ADDRESS(expenses_min_row,COLUMN()) & ":" & ADDRESS(expenses_max_row,COLUMN())))} -> 6950 | J30: {=SUM(INDIRECT(ADDRESS(expenses_min_row,COLUMN()) & ":" & ADDRESS(expenses_max_row,COLUMN())))} -> 6300 | K30: {=SUM(INDIRECT(ADDRESS(expenses_min_row,COLUMN()) & ":" & ADDRESS(expenses_max_row,COLUMN())))} -> 6750 | L30: {=SUM(INDIRECT(ADDRESS(expenses_min_row,COLUMN()) & ":" & ADDRESS(expenses_max_row,COLUMN())))} -> 6450 | ... Q30: {=SUM(INDIRECT(ADDRESS(expenses_min_row,COLUMN()) & ":" & ADDRESS(expenses_max_row,COLUMN())))} -> 83350 | S30: {=SUM(INDIRECT(ADDRESS(expenses_min_row,COLUMN()) & ":" & ADDRESS(expenses_max_row,COLUMN())))} -> 6400 | T30: {=SUM(INDIRECT(ADDRESS(expenses_min_row,COLUMN()) & ":" & ADDRESS(expenses_max_row,COLUMN())))} -> 6300 | U30: {=SUM(INDIRECT(ADDRESS(expenses_min_row,COLUMN()) & ":" & ADDRESS(expenses_max_row,COLUMN())))} -> 8250 | V30: {=SUM(INDIRECT(ADDRESS(expenses_min_row,COLUMN()) & ":" & ADDRESS(expenses_max_row,COLUMN())))} -> 6500 | W30: {=SUM(INDIRECT(ADDRESS(expenses_min_row,COLUMN()) & ":" & ADDRESS(expenses_max_row,COLUMN())))} -> 6950 | X30: {=SUM(INDIRECT(ADDRESS(expenses_min_row,COLUMN()) & ":" & ADDRESS(expenses_max_row,COLUMN())))} -> 6300 | Y30: {=SUM(INDIRECT(ADDRESS(expenses_min_row,COLUMN()) & ":" & ADDRESS(expenses_max_row,COLUMN())))} -> 6750 | Z30: {=SUM(INDIRECT(ADDRESS(expenses_min_row,COLUMN()) & ":" & ADDRESS(expenses_max_row,COLUMN())))} -> 6450 | ... AE30: {=SUM(INDIRECT(ADDRESS(expenses_min_row,COLUMN()) & ":" & ADDRESS(expenses_max_row,COLUMN())))} -> 83350 | AG30: {=SUM(INDIRECT(ADDRESS(expenses_min_row,COLUMN()) & ":" & ADDRESS(expenses_max_row,COLUMN())))} -> 0 | AH30: {=SUM(INDIRECT(ADDRESS(expenses_min_row,COLUMN()) & ":" & ADDRESS(expenses_max_row,COLUMN())))} -> 0 | AI30: {=SUM(INDIRECT(ADDRESS(expenses_min_row,COLUMN()) & ":" & ADDRESS(expenses_max_row,COLUMN())))} -> 0 | AJ30: {=SUM(INDIRECT(ADDRESS(expenses_min_row,COLUMN()) & ":" & ADDRESS(expenses_max_row,COLUMN())))} -> 0 | AK30: {=SUM(INDIRECT(ADDRESS(expenses_min_row,COLUMN()) & ":" & ADDRESS(expenses_max_row,COLUMN())))} -> 0 | AL30: {=SUM(INDIRECT(ADDRESS(expenses_min_row,COLUMN()) & ":" & ADDRESS(expenses_max_row,COLUMN())))} -> 0 | AM30: {=SUM(INDIRECT(ADDRESS(expenses_min_row,COLUMN()) & ":" & ADDRESS(expenses_max_row,COLUMN())))} -> 0 | AN30: {=SUM(INDIRECT(ADDRESS(expenses_min_row,COLUMN()) & ":" & ADDRESS(expenses_max_row,COLUMN())))} -> 0 | ... AS30: {=SUM(INDIRECT(ADDRESS(expenses_min_row,COLUMN()) & ":" & ADDRESS(expenses_max_row,COLUMN())))} -> 0
C32: Savings | E32: =DATE(E$5,1,1) -> 45658 | F32: =DATE(E$5,2,1) -> 45689 | G32: =DATE(E$5,3,1) -> 45717 | H32: =DATE(E$5,4,1) -> 45748 | I32: =DATE(E$5,5,1) -> 45778 | J32: =DATE(E$5,6,1) -> 45809 | K32: =DATE(E$5,7,1) -> 45839 | L32: =DATE(E$5,8,1) -> 45870 | M32: =DATE(E$5,9,1) -> 45901 | N32: =DATE(E$5,10,1) -> 45931 | O32: =DATE(E$5,11,1) -> 45962 | P32: =DATE(E$5,12,1) -> 45992 | Q32: =E5 -> 2025 | S32: =DATE(S$5,1,1) -> 46023 | T32: =DATE(S$5,2,1) -> 46054 | U32: =DATE(S$5,3,1) -> 46082 | V32: =DATE(S$5,4,1) -> 46113 | W32: =DATE(S$5,5,1) -> 46143 | X32: =DATE(S$5,6,1) -> 46174 | Y32: =DATE(S$5,7,1) -> 46204 | Z32: =DATE(S$5,8,1) -> 46235 | AA32: =DATE(S$5,9,1) -> 46266 | AB32: =DATE(S$5,10,1) -> 46296 | AC32: =DATE(S$5,11,1) -> 46327 | AD32: =DATE(S$5,12,1) -> 46357 | AE32: =S5 -> 2026 | AG32: =DATE(AG$5,1,1) -> 46388 | AH32: =DATE(AG$5,2,1) -> 46419 | AI32: =DATE(AG$5,3,1) -> 46447 | AJ32: =DATE(AG$5,4,1) -> 46478 | AK32: =DATE(AG$5,5,1) -> 46508 | AL32: =DATE(AG$5,6,1) -> 46539 | AM32: =DATE(AG$5,7,1) -> 46569 | AN32: =DATE(AG$5,8,1) -> 46600 | AO32: =DATE(AG$5,9,1) -> 46631 | AP32: =DATE(AG$5,10,1) -> 46661 | AQ32: =DATE(AG$5,11,1) -> 46692 | AR32: =DATE(AG$5,12,1) -> 46722 | AS32: =AG5 -> 2027
C33: Emergency Fund | E33: 1200 | F33: 1200 | G33: 1200 | H33: 1200 | I33: 1200 | J33: 1200 | K33: 1200 | L33: 1200 | M33: 1200 | N33: 1200 | O33: 1200 | P33: 1200 | Q33: =SUM(E33:P33) -> 14400 | S33: 1200 | T33: 1200 | U33: 1200 | V33: 1200 | W33: 1200 | X33: 1200 | Y33: 1200 | Z33: 1200 | AA33: 1200 | AB33: 1200 | AC33: 1200 | AD33: 1200 | AE33: =SUM(S33:AD33) -> 14400 | AS33: =SUM(AG33:AR33) -> 0
C34: Retirement Account | E34: 1400 | F34: 1400 | G34: 1400 | H34: 1400 | I34: 1400 | J34: 1400 | K34: 1400 | L34: 1400 | M34: 1400 | N34: 1400 | O34: 1400 | P34: 1400 | Q34: =SUM(E34:P34) -> 16800 | S34: 1400 | T34: 1400 | U34: 1400 | V34: 1400 | W34: 1400 | X34: 1400 | Y34: 1400 | Z34: 1400 | AA34: 1400 | AB34: 1400 | AC34: 1400 | AD34: 1400 | AE34: =SUM(S34:AD34) -> 16800 | AS34: =SUM(AG34:AR34) -> 0
C35: Stock Portfolio | E35: 800 | F35: 900 | G35: 1000 | H35: 700 | I35: 1100 | J35: 1000 | K35: 900 | L35: 1200 | M35: 800 | N35: 1000 | O35: 900 | P35: 1800 | Q35: =SUM(E35:P35) -> 12100 | S35: 800 | T35: 900 | U35: 1000 | V35: 700 | W35: 1100 | X35: 1000 | Y35: 900 | Z35: 1200 | AA35: 800 | AB35: 1000 | AC35: 900 | AD35: 1800 | AE35: =SUM(S35:AD35) -> 12100 | AS35: =SUM(AG35:AR35) -> 0
C36: Other | E36: 100 | F36: 200 | G36: 150 | H36: 250 | I36: 100 | J36: 300 | K36: 200 | L36: 150 | M36: 250 | N36: 200 | O36: 100 | P36: 300 | Q36: =SUM(E36:P36) -> 2300 | S36: 100 | T36: 200 | U36: 150 | V36: 250 | W36: 100 | X36: 300 | Y36: 200 | Z36: 150 | AA36: 250 | AB36: 200 | AC36: 100 | AD36: 300 | AE36: =SUM(S36:AD36) -> 2300 | AS36: =SUM(AG36:AR36) -> 0
C37: Enter Savings Category… | Q37: =SUM(E37:P37) -> 0 | AE37: =SUM(S37:AD37) -> 0 | AS37: =SUM(AG37:AR37) -> 0
C38: Enter Savings Category… | Q38: =SUM(E38:P38) -> 0 | AE38: =SUM(S38:AD38) -> 0 | AS38: =SUM(AG38:AR38) -> 0
C39: Enter Savings Category… | Q39: =SUM(E39:P39) -> 0 | AE39: =SUM(S39:AD39) -> 0 | AS39: =SUM(AG39:AR39) -> 0
C40: Enter Savings Category… | Q40: =SUM(E40:P40) -> 0 | AE40: =SUM(S40:AD40) -> 0 | AS40: =SUM(AG40:AR40) -> 0
C41: Enter Savings Category… | Q41: =SUM(E41:P41) -> 0 | AE41: =SUM(S41:AD41) -> 0 | AS41: =SUM(AG41:AR41) -> 0
C42: Enter Savings Category… | Q42: =SUM(E42:P42) -> 0 | AE42: =SUM(S42:AD42) -> 0 | AS42: =SUM(AG42:AR42) -> 0
C43: Total | E43: {=SUM(INDIRECT(ADDRESS(savings_min_row,COLUMN()) & ":" & ADDRESS(savings_max_row,COLUMN())))} -> 3500 | F43: {=SUM(INDIRECT(ADDRESS(savings_min_row,COLUMN()) & ":" & ADDRESS(savings_max_row,COLUMN())))} -> 3700 | G43: {=SUM(INDIRECT(ADDRESS(savings_min_row,COLUMN()) & ":" & ADDRESS(savings_max_row,COLUMN())))} -> 3750 | H43: {=SUM(INDIRECT(ADDRESS(savings_min_row,COLUMN()) & ":" & ADDRESS(savings_max_row,COLUMN())))} -> 3550 | I43: {=SUM(INDIRECT(ADDRESS(savings_min_row,COLUMN()) & ":" & ADDRESS(savings_max_row,COLUMN())))} -> 3800 | J43: {=SUM(INDIRECT(ADDRESS(savings_min_row,COLUMN()) & ":" & ADDRESS(savings_max_row,COLUMN())))} -> 3900 | K43: {=SUM(INDIRECT(ADDRESS(savings_min_row,COLUMN()) & ":" & ADDRESS(savings_max_row,COLUMN())))} -> 3700 | L43: {=SUM(INDIRECT(ADDRESS(savings_min_row,COLUMN()) & ":" & ADDRESS(savings_max_row,COLUMN())))} -> 3950 | ... Q43: {=SUM(INDIRECT(ADDRESS(savings_min_row,COLUMN()) & ":" & ADDRESS(savings_max_row,COLUMN())))} -> 45600 | S43: {=SUM(INDIRECT(ADDRESS(savings_min_row,COLUMN()) & ":" & ADDRESS(savings_max_row,COLUMN())))} -> 3500 | T43: {=SUM(INDIRECT(ADDRESS(savings_min_row,COLUMN()) & ":" & ADDRESS(savings_max_row,COLUMN())))} -> 3700 | U43: {=SUM(INDIRECT(ADDRESS(savings_min_row,COLUMN()) & ":" & ADDRESS(savings_max_row,COLUMN())))} -> 3750 | V43: {=SUM(INDIRECT(ADDRESS(savings_min_row,COLUMN()) & ":" & ADDRESS(savings_max_row,COLUMN())))} -> 3550 | W43: {=SUM(INDIRECT(ADDRESS(savings_min_row,COLUMN()) & ":" & ADDRESS(savings_max_row,COLUMN())))} -> 3800 | X43: {=SUM(INDIRECT(ADDRESS(savings_min_row,COLUMN()) & ":" & ADDRESS(savings_max_row,COLUMN())))} -> 3900 | Y43: {=SUM(INDIRECT(ADDRESS(savings_min_row,COLUMN()) & ":" & ADDRESS(savings_max_row,COLUMN())))} -> 3700 | Z43: {=SUM(INDIRECT(ADDRESS(savings_min_row,COLUMN()) & ":" & ADDRESS(savings_max_row,COLUMN())))} -> 3950 | ... AE43: {=SUM(INDIRECT(ADDRESS(savings_min_row,COLUMN()) & ":" & ADDRESS(savings_max_row,COLUMN())))} -> 45600 | AG43: {=SUM(INDIRECT(ADDRESS(savings_min_row,COLUMN()) & ":" & ADDRESS(savings_max_row,COLUMN())))} -> 0 | AH43: {=SUM(INDIRECT(ADDRESS(savings_min_row,COLUMN()) & ":" & ADDRESS(savings_max_row,COLUMN())))} -> 0 | AI43: {=SUM(INDIRECT(ADDRESS(savings_min_row,COLUMN()) & ":" & ADDRESS(savings_max_row,COLUMN())))} -> 0 | AJ43: {=SUM(INDIRECT(ADDRESS(savings_min_row,COLUMN()) & ":" & ADDRESS(savings_max_row,COLUMN())))} -> 0 | AK43: {=SUM(INDIRECT(ADDRESS(savings_min_row,COLUMN()) & ":" & ADDRESS(savings_max_row,COLUMN())))} -> 0 | AL43: {=SUM(INDIRECT(ADDRESS(savings_min_row,COLUMN()) & ":" & ADDRESS(savings_max_row,COLUMN())))} -> 0 | AM43: {=SUM(INDIRECT(ADDRESS(savings_min_row,COLUMN()) & ":" & ADDRESS(savings_max_row,COLUMN())))} -> 0 | AN43: {=SUM(INDIRECT(ADDRESS(savings_min_row,COLUMN()) & ":" & ADDRESS(savings_max_row,COLUMN())))} -> 0 | ... AS43: {=SUM(INDIRECT(ADDRESS(savings_min_row,COLUMN()) & ":" & ADDRESS(savings_max_row,COLUMN())))} -> 0

Sheet Budget Tracking
B1: Budget Tracking
C11: Date | D11: Type | E11: Category | F11: Amount | G11: Details | H11: Balance | I11: Effective Date
C12: 45658 | D12: Income | E12: Other | F12: 10 | G12: … | H12: {=SUMPRODUCT(Tracking[Amount], --(Tracking[Date]<=Tracking[[#This Row],[Date]]), (Tracking[Type]<>"Income")*(-1)+(Tracking[Type]="Income"))} -> -823.59 | I12: =IF(AND(Tracking[[#This Row],[Type]]="Income", Shift_late_income_status="Active",DAY(Tracking[[#This Row],[Date]])>=Shift_late_starting_day),DATE(YEAR(Tracking[[#This Row],[Date]]),MONTH(Tracking[[#This Row],[Date]])+1,1),Tracking[[#This Row],[Date]]) -> 45658
C13: 45666 | D13: Income | E13: Empoyment(Net) | F13: 1906.88 | G13: … | H13: {=SUMPRODUCT(Tracking[Amount], --(Tracking[Date]<=Tracking[[#This Row],[Date]]), (Tracking[Type]<>"Income")*(-1)+(Tracking[Type]="Income"))} -> 3776.25 | I13: =IF(AND(Tracking[[#This Row],[Type]]="Income", Shift_late_income_status="Active",DAY(Tracking[[#This Row],[Date]])>=Shift_late_starting_day),DATE(YEAR(Tracking[[#This Row],[Date]]),MONTH(Tracking[[#This Row],[Date]])+1,1),Tracking[[#This Row],[Date]]) -> 45666
C14: 45658 | D14: Expenses | E14: Groceries | F14: 833.59 | G14: ... | H14: {=SUMPRODUCT(Tracking[Amount], --(Tracking[Date]<=Tracking[[#This Row],[Date]]), (Tracking[Type]<>"Income")*(-1)+(Tracking[Type]="Income"))} -> -823.59 | I14: =IF(AND(Tracking[[#This Row],[Type]]="Income", Shift_late_income_status="Active",DAY(Tracking[[#This Row],[Date]])>=Shift_late_starting_day),DATE(YEAR(Tracking[[#This Row],[Date]]),MONTH(Tracking[[#This Row],[Date]])+1,1),Tracking[[#This Row],[Date]]) -> 45658
C15: 45659 | D15: Income | E15: Dividents | F15: 37.94 | G15: ... | H15: {=SUMPRODUCT(Tracking[Amount], --(Tracking[Date]<=Tracking[[#This Row],[Date]]), (Tracking[Type]<>"Income")*(-1)+(Tracking[Type]="Income"))} -> -1171.14 | I15: =IF(AND(Tracking[[#This Row],[Type]]="Income", Shift_late_income_status="Active",DAY(Tracking[[#This Row],[Date]])>=Shift_late_starting_day),DATE(YEAR(Tracking[[#This Row],[Date]]),MONTH(Tracking[[#This Row],[Date]])+1,1),Tracking[[#This Row],[Date]]) -> 45659
C16: 45659 | D16: Income | E16: Other | F16: 57.38 | G16: ... | H16: {=SUMPRODUCT(Tracking[Amount], --(Tracking[Date]<=Tracking[[#This Row],[Date]]), (Tracking[Type]<>"Income")*(-1)+(Tracking[Type]="Income"))} -> -1171.14 | I16: =IF(AND(Tracking[[#This Row],[Type]]="Income", Shift_late_income_status="Active",DAY(Tracking[[#This Row],[Date]])>=Shift_late_starting_day),DATE(YEAR(Tracking[[#This Row],[Date]]),MONTH(Tracking[[#This Row],[Date]])+1,1),Tracking[[#This Row],[Date]]) -> 45659
C17: 45659 | D17: Savings | E17: Retirement Account | F17: 442.87 | G17: ... | H17: {=SUMPRODUCT(Tracking[Amount], --(Tracking[Date]<=Tracking[[#This Row],[Date]]), (Tracking[Type]<>"Income")*(-1)+(Tracking[Type]="Income"))} -> -1171.14 | I17: =IF(AND(Tracking[[#This Row],[Type]]="Income", Shift_late_income_status="Active",DAY(Tracking[[#This Row],[Date]])>=Shift_late_starting_day),DATE(YEAR(Tracking[[#This Row],[Date]]),MONTH(Tracking[[#This Row],[Date]])+1,1),Tracking[[#This Row],[Date]]) -> 45659
C18: 45660 | D18: Expenses | E18: Transport | F18: 212.72 | G18: ... | H18: {=SUMPRODUCT(Tracking[Amount], --(Tracking[Date]<=Tracking[[#This Row],[Date]]), (Tracking[Type]<>"Income")*(-1)+(Tracking[Type]="Income"))} -> -1383.86 | I18: =IF(AND(Tracking[[#This Row],[Type]]="Income", Shift_late_income_status="Active",DAY(Tracking[[#This Row],[Date]])>=Shift_late_starting_day),DATE(YEAR(Tracking[[#This Row],[Date]]),MONTH(Tracking[[#This Row],[Date]])+1,1),Tracking[[#This Row],[Date]]) -> 45660
C19: 45662 | D19: Expenses | E19: Other | F19: 93.89 | G19: ... | H19: {=SUMPRODUCT(Tracking[Amount], --(Tracking[Date]<=Tracking[[#This Row],[Date]]), (Tracking[Type]<>"Income")*(-1)+(Tracking[Type]="Income"))} -> -5724.24 | I19: =IF(AND(Tracking[[#This Row],[Type]]="Income", Shift_late_income_status="Active",DAY(Tracking[[#This Row],[Date]])>=Shift_late_starting_day),DATE(YEAR(Tracking[[#This Row],[Date]]),MONTH(Tracking[[#This Row],[Date]])+1,1),Tracking[[#This Row],[Date]]) -> 45662
C20: 45662 | D20: Expenses | E20: Other | F20: 46.49 | G20: ... | H20: {=SUMPRODUCT(Tracking[Amount], --(Tracking[Date]<=Tracking[[#This Row],[Date]]), (Tracking[Type]<>"Income")*(-1)+(Tracking[Type]="Income"))} -> -5724.24 | I20: =IF(AND(Tracking[[#This Row],[Type]]="Income", Shift_late_income_status="Active",DAY(Tracking[[#This Row],[Date]])>=Shift_late_starting_day),DATE(YEAR(Tracking[[#This Row],[Date]]),MONTH(Tracking[[#This Row],[Date]])+1,1),Tracking[[#This Row],[Date]]) -> 45662
C21: 45662 | D21: Expenses | E21: Housing | F21: 4200 | G21: ... | H21: {=SUMPRODUCT(Tracking[Amount], --(Tracking[Date]<=Tracking[[#This Row],[Date]]), (Tracking[Type]<>"Income")*(-1)+(Tracking[Type]="Income"))} -> -5724.24 | I21: =IF(AND(Tracking[[#This Row],[Type]]="Income", Shift_late_income_status="Active",DAY(Tracking[[#This Row],[Date]])>=Shift_late_starting_day),DATE(YEAR(Tracking[[#This Row],[Date]]),MONTH(Tracking[[#This Row],[Date]])+1,1),Tracking[[#This Row],[Date]]) -> 45662
C22: 45663 | D22: Expenses | E22: Groceries | F22: 666.41 | G22: ... | H22: {=SUMPRODUCT(Tracking[Amount], --(Tracking[Date]<=Tracking[[#This Row],[Date]]), (Tracking[Type]<>"Income")*(-1)+(Tracking[Type]="Income"))} -> -6390.65 | I22: =IF(AND(Tracking[[#This Row],[Type]]="Income", Shift_late_income_status="Active",DAY(Tracking[[#This Row],[Date]])>=Shift_late_starting_day),DATE(YEAR(Tracking[[#This Row],[Date]]),MONTH(Tracking[[#This Row],[Date]])+1,1),Tracking[[#This Row],[Date]]) -> 45663
C23: 45664 | D23: Savings | E23: Stock Portfolio | F23: 239.98 | G23: ... | H23: {=SUMPRODUCT(Tracking[Amount], --(Tracking[Date]<=Tracking[[#This Row],[Date]]), (Tracking[Type]<>"Income")*(-1)+(Tracking[Type]="Income"))} -> -6630.63 | I23: =IF(AND(Tracking[[#This Row],[Type]]="Income", Shift_late_income_status="Active",DAY(Tracking[[#This Row],[Date]])>=Shift_late_starting_day),DATE(YEAR(Tracking[[#This Row],[Date]]),MONTH(Tracking[[#This Row],[Date]])+1,1),Tracking[[#This Row],[Date]]) -> 45664
... C357: 46170 | D357: Savings | E357: Other | F357: 250 | G357: ... | H357: {=SUMPRODUCT(Tracking[Amount], --(Tracking[Date]<=Tracking[[#This Row],[Date]]), (Tracking[Type]<>"Income")*(-1)+(Tracking[Type]="Income"))} -> 22766.97 | I357: =IF(AND(Tracking[[#This Row],[Type]]="Income", Shift_late_income_status="Active",DAY(Tracking[[#This Row],[Date]])>=Shift_late_starting_day),DATE(YEAR(Tracking[[#This Row],[Date]]),MONTH(Tracking[[#This Row],[Date]])+1,1),Tracking[[#This Row],[Date]]) -> 46170

Sheet Budget dashboard
AQ5: Year
AN6: Select the year of view: | AQ6: 2026
AQ8: Period
AN9: Select the period of view: | AQ9: Total Year
Y11: ="Breakdown - "&IF(selected_period="Total Year",selected_year&" (Total Year)",selected_period_display&" "&selected_year) -> Breakdown - 2026 (Total Year) | AF11: ="Summary - "&IF(selected_period="Total Year",selected_year&" (Total Year)",selected_period_display&" "&selected_year) -> Summary - 2026 (Total Year)
C12: row_id | D12: header_row_id | E12: is_header | F12: is_cat | G12: is_total | H12: is_empty | I12: type | J12: item | K12: tracked | L12: budget | M12: sort_min_row | N12: sort_max_row | O12: tracked_range | P12: tracked_rank | Q12: budget_range | R12: budget_rank | S12: comb_rank | T12: comb_rank_range | U12: comb_rank_norm | V12: comb_rank_norm_run_range | W12: comb_rank_unique | X12: sorted_row_id [Lookup]
C13: {=income_header_row} -> 9 | D13: =IF(is_header,row_id, IF(NOT(is_empty),D12,-1)) -> 9 | E13: {=1*OR(row_id=income_header_row,row_id=expenses_header_row,row_id=savings_header_row)} -> 1 | F13: =1*NOT(OR(is_header,is_total,is_empty)) -> 0 | G13: {=1*OR(row_id=expenses_total_row,row_id=savings_total_row,row_id=income_total_row)} -> 0 | H13: =1*OR(row_id="/1", row_id="/2", row_id=-1) -> 0 | I13: {=IFERROR(INDEX('Budget Planning'!$C:$C, header_row_id), "")} -> Income | J13: {=IFERROR(INDEX('Budget Planning'!$C:$C, row_id), "")} -> Income | K13: {=IF(OR(is_header, is_empty), "", IF(is_total, IF(selected_period="Total Year", SUM(Tracking[Amount] * (Tracking[Type]=type) * (YEAR(Tracking[Effective Date])=selected_year)), SUM(Tracking[Amount] * (Tracking[Type]=type) * (YEAR(Tracking[Effective Date])=selected_year) * (MONTH(Tracking[Effective Date])=selected_period))), IF(selected_period="Total Year", SUM(Tracking[Amount] * (Tracking[Type]=type) * (Tracking[Category]=item) * (YEAR(Tracking[Effective Date])=selected_year)), SUM(Tracking[Amount] * (Tracking[Type]=type) * (Tracking[Category]=item) * (YEAR(Tracking[Effective Date])=selected_year) * (MONTH(Tracking[Effective Date])=selected_period))) ) )} | L13: {=IF(OR(is_empty,is_header), "", INDEX('Budget Planning'!$E:$AS, row_id, MATCH(IF(selected_period="Total Year", selected_year, DATE(selected_year, selected_period, 1)),'Budget Planning'!$E$9:$AS$9,0) ))} | M13: {=IF(is_cat, IF(header_row_id=income_header_row, MATCH(income_min_row,$C:$C,0), IF(header_row_id=expenses_header_row, MATCH(expenses_min_row,$C:$C,0), IF(header_row_id=savings_header_row, MATCH(savings_min_row,$C:$C,0), ""))), "")} | N13: {=IF(is_cat, IF(header_row_id=income_header_row, MATCH(income_max_row,$C:$C,0), IF(header_row_id=expenses_header_row, MATCH(expenses_max_row,$C:$C,0), IF(header_row_id=savings_header_row, MATCH(savings_max_row,$C:$C,0), ""))), "")} | O13: =IF(is_cat, ADDRESS(sort_min_row, COLUMN(tracked)) & ":" & ADDRESS(sort_max_row,COLUMN(tracked)), "") | P13: =IF(is_cat, RANK(tracked, INDIRECT(tracked_range), 0),"") | Q13: =IF(is_cat, ADDRESS(sort_min_row, COLUMN(budget)) & ":" & ADDRESS(sort_max_row,COLUMN(budget)), "") | R13: =IF(is_cat, RANK(budget, INDIRECT(budget_range), 0),"") | S13: =IF(is_cat, _xlfn.NUMBERVALUE(tracked_rank & budget_rank), "") | T13: =IF(is_cat, ADDRESS(sort_min_row, COLUMN(comb_rank)) & ":" & ADDRESS(sort_max_row,COLUMN(comb_rank)), "") | U13: =IF(is_cat, RANK(comb_rank, INDIRECT(comb_rank_range),1), "") | V13: =IF(is_cat, ADDRESS(sort_min_row, COLUMN(comb_rank_norm)) & ":" & ADDRESS(ROW(),COLUMN(comb_rank_norm)), "") | W13: =IF(is_cat,comb_rank_norm + COUNTIF(INDIRECT(comb_rank_norm_run_range),comb_rank_norm)-1, "") | X13: =IF(is_cat, header_row_id + comb_rank_unique, row_id) -> 9 | Y13: =IF(is_empty, "", INDEX($J:$J,MATCH(row_id, $X:$X, 0))) -> Income | Z13: =IF(is_empty, "", IF(is_header, "Tracked", INDEX($K:$K, MATCH(row_id, $X:$X,0)))) -> Tracked | AA13: =IF(is_empty, "", IF(is_header, "Budget", INDEX($L:$L, MATCH(row_id, $X:$X,0)))) -> Budget | AB13: =IF(is_empty, "", IF(is_header, "% Compl.", IFERROR(out_tracked / out_budget, "-"))) -> % Compl. | AC13: =IF(is_empty, "", IF(is_header, "Remaining", IF(out_budget - out_tracked > 0, out_budget - out_tracked, 0))) -> Remaining | AD13: =IF(is_empty, "", IF(is_header, "Excess", IF(out_budget - out_tracked < 0, out_tracked - out_budget, 0))) -> Excess
C14: {=IF(C13=-1,-1, IF(C13<income_max_row,C13+1, IF(C13=income_max_row,income_total_row, IF(C13=income_total_row,"/1", IF(C13="/1",expenses_header_row, IF(C13<expenses_max_row,C13+1, IF(C13=expenses_max_row,expenses_total_row, IF(C13=expenses_total_row,"/2", IF(C13="/2",savings_header_row, IF(C13<savings_max_row,C13+1, IF(C13=savings_max_row,savings_total_row,-1)))))))))))} -> 10 | D14: =IF(is_header,row_id, IF(NOT(is_empty),D13,-1)) -> 9 | E14: {=1*OR(row_id=income_header_row,row_id=expenses_header_row,row_id=savings_header_row)} -> 0 | F14: =1*NOT(OR(is_header,is_total,is_empty)) -> 1 | G14: {=1*OR(row_id=expenses_total_row,row_id=savings_total_row,row_id=income_total_row)} -> 0 | H14: =1*OR(row_id="/1", row_id="/2", row_id=-1) -> 0 | I14: {=IFERROR(INDEX('Budget Planning'!$C:$C, header_row_id), "")} -> Income | J14: {=IFERROR(INDEX('Budget Planning'!$C:$C, row_id), "")} -> Empoyment(Net) | K14: {=IF(OR(is_header, is_empty), "", IF(is_total, IF(selected_period="Total Year", SUM(Tracking[Amount] * (Tracking[Type]=type) * (YEAR(Tracking[Effective Date])=selected_year)), SUM(Tracking[Amount] * (Tracking[Type]=type) * (YEAR(Tracking[Effective Date])=selected_year) * (MONTH(Tracking[Effective Date])=selected_period))), IF(selected_period="Total Year", SUM(Tracking[Amount] * (Tracking[Type]=type) * (Tracking[Category]=item) * (YEAR(Tracking[Effective Date])=selected_year)), SUM(Tracking[Amount] * (Tracking[Type]=type) * (Tracking[Category]=item) * (YEAR(Tracking[Effective Date])=selected_year) * (MONTH(Tracking[Effective Date])=selected_period))) ) )} -> 47100 | L14: {=IF(OR(is_empty,is_header), "", INDEX('Budget Planning'!$E:$AS, row_id, MATCH(IF(selected_period="Total Year", selected_year, DATE(selected_year, selected_period, 1)),'Budget Planning'!$E$9:$AS$9,0) ))} -> 106100 | M14: {=IF(is_cat, IF(header_row_id=income_header_row, MATCH(income_min_row,$C:$C,0), IF(header_row_id=expenses_header_row, MATCH(expenses_min_row,$C:$C,0), IF(header_row_id=savings_header_row, MATCH(savings_min_row,$C:$C,0), ""))), "")} -> 14 | N14: {=IF(is_cat, IF(header_row_id=income_header_row, MATCH(income_max_row,$C:$C,0), IF(header_row_id=expenses_header_row, MATCH(expenses_max_row,$C:$C,0), IF(header_row_id=savings_header_row, MATCH(savings_max_row,$C:$C,0), ""))), "")} -> 17 | O14: =IF(is_cat, ADDRESS(sort_min_row, COLUMN(tracked)) & ":" & ADDRESS(sort_max_row,COLUMN(tracked)), "") -> $K$14:$K$17 | P14: =IF(is_cat, RANK(tracked, INDIRECT(tracked_range), 0),"") -> 1 | Q14: =IF(is_cat, ADDRESS(sort_min_row, COLUMN(budget)) & ":" & ADDRESS(sort_max_row,COLUMN(budget)), "") -> $L$14:$L$17 | R14: =IF(is_cat, RANK(budget, INDIRECT(budget_range), 0),"") -> 1 | S14: =IF(is_cat, _xlfn.NUMBERVALUE(tracked_rank & budget_rank), "") -> 11 | T14: =IF(is_cat, ADDRESS(sort_min_row, COLUMN(comb_rank)) & ":" & ADDRESS(sort_max_row,COLUMN(comb_rank)), "") -> $S$14:$S$17 | U14: =IF(is_cat, RANK(comb_rank, INDIRECT(comb_rank_range),1), "") -> 1 | V14: =IF(is_cat, ADDRESS(sort_min_row, COLUMN(comb_rank_norm)) & ":" & ADDRESS(ROW(),COLUMN(comb_rank_norm)), "") -> $U$14:$U$14 | W14: =IF(is_cat,comb_rank_norm + COUNTIF(INDIRECT(comb_rank_norm_run_range),comb_rank_norm)-1, "") -> 1 | X14: =IF(is_cat, header_row_id + comb_rank_unique, row_id) -> 10 | Y14: =IF(is_empty, "", INDEX($J:$J,MATCH(row_id, $X:$X, 0))) -> Empoyment(Net) | Z14: =IF(is_empty, "", IF(is_header, "Tracked", INDEX($K:$K, MATCH(row_id, $X:$X,0)))) -> 47100 | AA14: =IF(is_empty, "", IF(is_header, "Budget", INDEX($L:$L, MATCH(row_id, $X:$X,0)))) -> 106100 | AB14: =IF(is_empty, "", IF(is_header, "% Compl.", IFERROR(out_tracked / out_budget, "-"))) -> 0.44392083 | AC14: =IF(is_empty, "", IF(is_header, "Remaining", IF(out_budget - out_tracked > 0, out_budget - out_tracked, 0))) -> 59000 | AD14: =IF(is_empty, "", IF(is_header, "Excess", IF(out_budget - out_tracked < 0, out_tracked - out_budget, 0))) -> 0
C15: {=IF(C14=-1,-1, IF(C14<income_max_row,C14+1, IF(C14=income_max_row,income_total_row, IF(C14=income_total_row,"/1", IF(C14="/1",expenses_header_row, IF(C14<expenses_max_row,C14+1, IF(C14=expenses_max_row,expenses_total_row, IF(C14=expenses_total_row,"/2", IF(C14="/2",savings_header_row, IF(C14<savings_max_row,C14+1, IF(C14=savings_max_row,savings_total_row,-1)))))))))))} -> 11 | D15: =IF(is_header,row_id, IF(NOT(is_empty),D14,-1)) -> 9 | E15: {=1*OR(row_id=income_header_row,row_id=expenses_header_row,row_id=savings_header_row)} -> 0 | F15: =1*NOT(OR(is_header,is_total,is_empty)) -> 1 | G15: {=1*OR(row_id=expenses_total_row,row_id=savings_total_row,row_id=income_total_row)} -> 0 | H15: =1*OR(row_id="/1", row_id="/2", row_id=-1) -> 0 | I15: {=IFERROR(INDEX('Budget Planning'!$C:$C, header_row_id), "")} -> Income | J15: {=IFERROR(INDEX('Budget Planning'!$C:$C, row_id), "")} -> Side Hustle(Net) | K15: {=IF(OR(is_header, is_empty), "", IF(is_total, IF(selected_period="Total Year", SUM(Tracking[Amount] * (Tracking[Type]=type) * (YEAR(Tracking[Effective Date])=selected_year)), SUM(Tracking[Amount] * (Tracking[Type]=type) * (YEAR(Tracking[Effective Date])=selected_year) * (MONTH(Tracking[Effective Date])=selected_period))), IF(selected_period="Total Year", SUM(Tracking[Amount] * (Tracking[Type]=type) * (Tracking[Category]=item) * (YEAR(Tracking[Effective Date])=selected_year)), SUM(Tracking[Amount] * (Tracking[Type]=type) * (Tracking[Category]=item) * (YEAR(Tracking[Effective Date])=selected_year) * (MONTH(Tracking[Effective Date])=selected_period))) ) )} -> 10931.15 | L15: {=IF(OR(is_empty,is_header), "", INDEX('Budget Planning'!$E:$AS, row_id, MATCH(IF(selected_period="Total Year", selected_year, DATE(selected_year, selected_period, 1)),'Budget Planning'!$E$9:$AS$9,0) ))} -> 26750 | M15: {=IF(is_cat, IF(header_row_id=income_header_row, MATCH(income_min_row,$C:$C,0), IF(header_row_id=expenses_header_row, MATCH(expenses_min_row,$C:$C,0), IF(header_row_id=savings_header_row, MATCH(savings_min_row,$C:$C,0), ""))), "")} -> 14 | N15: {=IF(is_cat, IF(header_row_id=income_header_row, MATCH(income_max_row,$C:$C,0), IF(header_row_id=expenses_header_row, MATCH(expenses_max_row,$C:$C,0), IF(header_row_id=savings_header_row, MATCH(savings_max_row,$C:$C,0), ""))), "")} -> 17 | O15: =IF(is_cat, ADDRESS(sort_min_row, COLUMN(tracked)) & ":" & ADDRESS(sort_max_row,COLUMN(tracked)), "") -> $K$14:$K$17 | P15: =IF(is_cat, RANK(tracked, INDIRECT(tracked_range), 0),"") -> 2 | Q15: =IF(is_cat, ADDRESS(sort_min_row, COLUMN(budget)) & ":" & ADDRESS(sort_max_row,COLUMN(budget)), "") -> $L$14:$L$17 | R15: =IF(is_cat, RANK(budget, INDIRECT(budget_range), 0),"") -> 2 | S15: =IF(is_cat, _xlfn.NUMBERVALUE(tracked_rank & budget_rank), "") -> 22 | T15: =IF(is_cat, ADDRESS(sort_min_row, COLUMN(comb_rank)) & ":" & ADDRESS(sort_max_row,COLUMN(comb_rank)), "") -> $S$14:$S$17 | U15: =IF(is_cat, RANK(comb_rank, INDIRECT(comb_rank_range),1), "") -> 2 | V15: =IF(is_cat, ADDRESS(sort_min_row, COLUMN(comb_rank_norm)) & ":" & ADDRESS(ROW(),COLUMN(comb_rank_norm)), "") -> $U$14:$U$15 | W15: =IF(is_cat,comb_rank_norm + COUNTIF(INDIRECT(comb_rank_norm_run_range),comb_rank_norm)-1, "") -> 2 | X15: =IF(is_cat, header_row_id + comb_rank_unique, row_id) -> 11 | Y15: =IF(is_empty, "", INDEX($J:$J,MATCH(row_id, $X:$X, 0))) -> Side Hustle(Net) | Z15: =IF(is_empty, "", IF(is_header, "Tracked", INDEX($K:$K, MATCH(row_id, $X:$X,0)))) -> 10931.15 | AA15: =IF(is_empty, "", IF(is_header, "Budget", INDEX($L:$L, MATCH(row_id, $X:$X,0)))) -> 26750 | AB15: =IF(is_empty, "", IF(is_header, "% Compl.", IFERROR(out_tracked / out_budget, "-"))) -> 0.40864112 | AC15: =IF(is_empty, "", IF(is_header, "Remaining", IF(out_budget - out_tracked > 0, out_budget - out_tracked, 0))) -> 15818.85 | AD15: =IF(is_empty, "", IF(is_header, "Excess", IF(out_budget - out_tracked < 0, out_tracked - out_budget, 0))) -> 0
C16: {=IF(C15=-1,-1, IF(C15<income_max_row,C15+1, IF(C15=income_max_row,income_total_row, IF(C15=income_total_row,"/1", IF(C15="/1",expenses_header_row, IF(C15<expenses_max_row,C15+1, IF(C15=expenses_max_row,expenses_total_row, IF(C15=expenses_total_row,"/2", IF(C15="/2",savings_header_row, IF(C15<savings_max_row,C15+1, IF(C15=savings_max_row,savings_total_row,-1)))))))))))} -> 12 | D16: =IF(is_header,row_id, IF(NOT(is_empty),D15,-1)) -> 9 | E16: {=1*OR(row_id=income_header_row,row_id=expenses_header_row,row_id=savings_header_row)} -> 0 | F16: =1*NOT(OR(is_header,is_total,is_empty)) -> 1 | G16: {=1*OR(row_id=expenses_total_row,row_id=savings_total_row,row_id=income_total_row)} -> 0 | H16: =1*OR(row_id="/1", row_id="/2", row_id=-1) -> 0 | I16: {=IFERROR(INDEX('Budget Planning'!$C:$C, header_row_id), "")} -> Income | J16: {=IFERROR(INDEX('Budget Planning'!$C:$C, row_id), "")} -> Dividents | K16: {=IF(OR(is_header, is_empty), "", IF(is_total, IF(selected_period="Total Year", SUM(Tracking[Amount] * (Tracking[Type]=type) * (YEAR(Tracking[Effective Date])=selected_year)), SUM(Tracking[Amount] * (Tracking[Type]=type) * (YEAR(Tracking[Effective Date])=selected_year) * (MONTH(Tracking[Effective Date])=selected_period))), IF(selected_period="Total Year", SUM(Tracking[Amount] * (Tracking[Type]=type) * (Tracking[Category]=item) * (YEAR(Tracking[Effective Date])=selected_year)), SUM(Tracking[Amount] * (Tracking[Type]=type) * (Tracking[Category]=item) * (YEAR(Tracking[Effective Date])=selected_year) * (MONTH(Tracking[Effective Date])=selected_period))) ) )} -> 2050 | L16: {=IF(OR(is_empty,is_header), "", INDEX('Budget Planning'!$E:$AS, row_id, MATCH(IF(selected_period="Total Year", selected_year, DATE(selected_year, selected_period, 1)),'Budget Planning'!$E$9:$AS$9,0) ))} -> 3850 | M16: {=IF(is_cat, IF(header_row_id=income_header_row, MATCH(income_min_row,$C:$C,0), IF(header_row_id=expenses_header_row, MATCH(expenses_min_row,$C:$C,0), IF(header_row_id=savings_header_row, MATCH(savings_min_row,$C:$C,0), ""))), "")} -> 14 | N16: {=IF(is_cat, IF(header_row_id=income_header_row, MATCH(income_max_row,$C:$C,0), IF(header_row_id=expenses_header_row, MATCH(expenses_max_row,$C:$C,0), IF(header_row_id=savings_header_row, MATCH(savings_max_row,$C:$C,0), ""))), "")} -> 17 | O16: =IF(is_cat, ADDRESS(sort_min_row, COLUMN(tracked)) & ":" & ADDRESS(sort_max_row,COLUMN(tracked)), "") -> $K$14:$K$17 | P16: =IF(is_cat, RANK(tracked, INDIRECT(tracked_range), 0),"") -> 3 | Q16: =IF(is_cat, ADDRESS(sort_min_row, COLUMN(budget)) & ":" & ADDRESS(sort_max_row,COLUMN(budget)), "") -> $L$14:$L$17 | R16: =IF(is_cat, RANK(budget, INDIRECT(budget_range), 0),"") -> 4 | S16: =IF(is_cat, _xlfn.NUMBERVALUE(tracked_rank & budget_rank), "") -> 34 | T16: =IF(is_cat, ADDRESS(sort_min_row, COLUMN(comb_rank)) & ":" & ADDRESS(sort_max_row,COLUMN(comb_rank)), "") -> $S$14:$S$17 | U16: =IF(is_cat, RANK(comb_rank, INDIRECT(comb_rank_range),1), "") -> 3 | V16: =IF(is_cat, ADDRESS(sort_min_row, COLUMN(comb_rank_norm)) & ":" & ADDRESS(ROW(),COLUMN(comb_rank_norm)), "") -> $U$14:$U$16 | W16: =IF(is_cat,comb_rank_norm + COUNTIF(INDIRECT(comb_rank_norm_run_range),comb_rank_norm)-1, "") -> 3 | X16: =IF(is_cat, header_row_id + comb_rank_unique, row_id) -> 12 | Y16: =IF(is_empty, "", INDEX($J:$J,MATCH(row_id, $X:$X, 0))) -> Dividents | Z16: =IF(is_empty, "", IF(is_header, "Tracked", INDEX($K:$K, MATCH(row_id, $X:$X,0)))) -> 2050 | AA16: =IF(is_empty, "", IF(is_header, "Budget", INDEX($L:$L, MATCH(row_id, $X:$X,0)))) -> 3850 | AB16: =IF(is_empty, "", IF(is_header, "% Compl.", IFERROR(out_tracked / out_budget, "-"))) -> 0.53246753 | AC16: =IF(is_empty, "", IF(is_header, "Remaining", IF(out_budget - out_tracked > 0, out_budget - out_tracked, 0))) -> 1800 | AD16: =IF(is_empty, "", IF(is_header, "Excess", IF(out_budget - out_tracked < 0, out_tracked - out_budget, 0))) -> 0 | AI16: =Calculations!E35 -> Empoyment(Net) | AJ16: =Calculations!F35 -> 47100
C17: {=IF(C16=-1,-1, IF(C16<income_max_row,C16+1, IF(C16=income_max_row,income_total_row, IF(C16=income_total_row,"/1", IF(C16="/1",expenses_header_row, IF(C16<expenses_max_row,C16+1, IF(C16=expenses_max_row,expenses_total_row, IF(C16=expenses_total_row,"/2", IF(C16="/2",savings_header_row, IF(C16<savings_max_row,C16+1, IF(C16=savings_max_row,savings_total_row,-1)))))))))))} -> 13 | D17: =IF(is_header,row_id, IF(NOT(is_empty),D16,-1)) -> 9 | E17: {=1*OR(row_id=income_header_row,row_id=expenses_header_row,row_id=savings_header_row)} -> 0 | F17: =1*NOT(OR(is_header,is_total,is_empty)) -> 1 | G17: {=1*OR(row_id=expenses_total_row,row_id=savings_total_row,row_id=income_total_row)} -> 0 | H17: =1*OR(row_id="/1", row_id="/2", row_id=-1) -> 0 | I17: {=IFERROR(INDEX('Budget Planning'!$C:$C, header_row_id), "")} -> Income | J17: {=IFERROR(INDEX('Budget Planning'!$C:$C, row_id), "")} -> Other | K17: {=IF(OR(is_header, is_empty), "", IF(is_total, IF(selected_period="Total Year", SUM(Tracking[Amount] * (Tracking[Type]=type) * (YEAR(Tracking[Effective Date])=selected_year)), SUM(Tracking[Amount] * (Tracking[Type]=type) * (YEAR(Tracking[Effective Date])=selected_year) * (MONTH(Tracking[Effective Date])=selected_period))), IF(selected_period="Total Year", SUM(Tracking[Amount] * (Tracking[Type]=type) * (Tracking[Category]=item) * (YEAR(Tracking[Effective Date])=selected_year)), SUM(Tracking[Amount] * (Tracking[Type]=type) * (Tracking[Category]=item) * (YEAR(Tracking[Effective Date])=selected_year) * (MONTH(Tracking[Effective Date])=selected_period))) ) )} -> 1000 | L17: {=IF(OR(is_empty,is_header), "", INDEX('Budget Planning'!$E:$AS, row_id, MATCH(IF(selected_period="Total Year", selected_year, DATE(selected_year, selected_period, 1)),'Budget Planning'!$E$9:$AS$9,0) ))} -> 4000 | M17: {=IF(is_cat, IF(header_row_id=income_header_row, MATCH(income_min_row,$C:$C,0), IF(header_row_id=expenses_header_row, MATCH(expenses_min_row,$C:$C,0), IF(header_row_id=savings_header_row, MATCH(savings_min_row,$C:$C,0), ""))), "")} -> 14 | N17: {=IF(is_cat, IF(header_row_id=income_header_row, MATCH(income_max_row,$C:$C,0), IF(header_row_id=expenses_header_row, MATCH(expenses_max_row,$C:$C,0), IF(header_row_id=savings_header_row, MATCH(savings_max_row,$C:$C,0), ""))), "")} -> 17 | O17: =IF(is_cat, ADDRESS(sort_min_row, COLUMN(tracked)) & ":" & ADDRESS(sort_max_row,COLUMN(tracked)), "") -> $K$14:$K$17 | P17: =IF(is_cat, RANK(tracked, INDIRECT(tracked_range), 0),"") -> 4 | Q17: =IF(is_cat, ADDRESS(sort_min_row, COLUMN(budget)) & ":" & ADDRESS(sort_max_row,COLUMN(budget)), "") -> $L$14:$L$17 | R17: =IF(is_cat, RANK(budget, INDIRECT(budget_range), 0),"") -> 3 | S17: =IF(is_cat, _xlfn.NUMBERVALUE(tracked_rank & budget_rank), "") -> 43 | T17: =IF(is_cat, ADDRESS(sort_min_row, COLUMN(comb_rank)) & ":" & ADDRESS(sort_max_row,COLUMN(comb_rank)), "") -> $S$14:$S$17 | U17: =IF(is_cat, RANK(comb_rank, INDIRECT(comb_rank_range),1), "") -> 4 | V17: =IF(is_cat, ADDRESS(sort_min_row, COLUMN(comb_rank_norm)) & ":" & ADDRESS(ROW(),COLUMN(comb_rank_norm)), "") -> $U$14:$U$17 | W17: =IF(is_cat,comb_rank_norm + COUNTIF(INDIRECT(comb_rank_norm_run_range),comb_rank_norm)-1, "") -> 4 | X17: =IF(is_cat, header_row_id + comb_rank_unique, row_id) -> 13 | Y17: =IF(is_empty, "", INDEX($J:$J,MATCH(row_id, $X:$X, 0))) -> Other | Z17: =IF(is_empty, "", IF(is_header, "Tracked", INDEX($K:$K, MATCH(row_id, $X:$X,0)))) -> 1000 | AA17: =IF(is_empty, "", IF(is_header, "Budget", INDEX($L:$L, MATCH(row_id, $X:$X,0)))) -> 4000 | AB17: =IF(is_empty, "", IF(is_header, "% Compl.", IFERROR(out_tracked / out_budget, "-"))) -> 0.25 | AC17: =IF(is_empty, "", IF(is_header, "Remaining", IF(out_budget - out_tracked > 0, out_budget - out_tracked, 0))) -> 3000 | AD17: =IF(is_empty, "", IF(is_header, "Excess", IF(out_budget - out_tracked < 0, out_tracked - out_budget, 0))) -> 0 | AI17: =Calculations!E36 -> Side Hustle(Net) | AJ17: =Calculations!F36 -> 10931.15
C18: {=IF(C17=-1,-1, IF(C17<income_max_row,C17+1, IF(C17=income_max_row,income_total_row, IF(C17=income_total_row,"/1", IF(C17="/1",expenses_header_row, IF(C17<expenses_max_row,C17+1, IF(C17=expenses_max_row,expenses_total_row, IF(C17=expenses_total_row,"/2", IF(C17="/2",savings_header_row, IF(C17<savings_max_row,C17+1, IF(C17=savings_max_row,savings_total_row,-1)))))))))))} -> 20 | D18: =IF(is_header,row_id, IF(NOT(is_empty),D17,-1)) -> 9 | E18: {=1*OR(row_id=income_header_row,row_id=expenses_header_row,row_id=savings_header_row)} -> 0 | F18: =1*NOT(OR(is_header,is_total,is_empty)) -> 0 | G18: {=1*OR(row_id=expenses_total_row,row_id=savings_total_row,row_id=income_total_row)} -> 1 | H18: =1*OR(row_id="/1", row_id="/2", row_id=-1) -> 0 | I18: {=IFERROR(INDEX('Budget Planning'!$C:$C, header_row_id), "")} -> Income | J18: {=IFERROR(INDEX('Budget Planning'!$C:$C, row_id), "")} -> Total | K18: {=IF(OR(is_header, is_empty), "", IF(is_total, IF(selected_period="Total Year", SUM(Tracking[Amount] * (Tracking[Type]=type) * (YEAR(Tracking[Effective Date])=selected_year)), SUM(Tracking[Amount] * (Tracking[Type]=type) * (YEAR(Tracking[Effective Date])=selected_year) * (MONTH(Tracking[Effective Date])=selected_period))), IF(selected_period="Total Year", SUM(Tracking[Amount] * (Tracking[Type]=type) * (Tracking[Category]=item) * (YEAR(Tracking[Effective Date])=selected_year)), SUM(Tracking[Amount] * (Tracking[Type]=type) * (Tracking[Category]=item) * (YEAR(Tracking[Effective Date])=selected_year) * (MONTH(Tracking[Effective Date])=selected_period))) ) )} -> 61081.15 | L18: {=IF(OR(is_empty,is_header), "", INDEX('Budget Planning'!$E:$AS, row_id, MATCH(IF(selected_period="Total Year", selected_year, DATE(selected_year, selected_period, 1)),'Budget Planning'!$E$9:$AS$9,0) ))} -> 140700 | M18: {=IF(is_cat, IF(header_row_id=income_header_row, MATCH(income_min_row,$C:$C,0), IF(header_row_id=expenses_header_row, MATCH(expenses_min_row,$C:$C,0), IF(header_row_id=savings_header_row, MATCH(savings_min_row,$C:$C,0), ""))), "")} | N18: {=IF(is_cat, IF(header_row_id=income_header_row, MATCH(income_max_row,$C:$C,0), IF(header_row_id=expenses_header_row, MATCH(expenses_max_row,$C:$C,0), IF(header_row_id=savings_header_row, MATCH(savings_max_row,$C:$C,0), ""))), "")} | O18: =IF(is_cat, ADDRESS(sort_min_row, COLUMN(tracked)) & ":" & ADDRESS(sort_max_row,COLUMN(tracked)), "") | P18: =IF(is_cat, RANK(tracked, INDIRECT(tracked_range), 0),"") | Q18: =IF(is_cat, ADDRESS(sort_min_row, COLUMN(budget)) & ":" & ADDRESS(sort_max_row,COLUMN(budget)), "") | R18: =IF(is_cat, RANK(budget, INDIRECT(budget_range), 0),"") | S18: =IF(is_cat, _xlfn.NUMBERVALUE(tracked_rank & budget_rank), "") | T18: =IF(is_cat, ADDRESS(sort_min_row, COLUMN(comb_rank)) & ":" & ADDRESS(sort_max_row,COLUMN(comb_rank)), "") | U18: =IF(is_cat, RANK(comb_rank, INDIRECT(comb_rank_range),1), "") | V18: =IF(is_cat, ADDRESS(sort_min_row, COLUMN(comb_rank_norm)) & ":" & ADDRESS(ROW(),COLUMN(comb_rank_norm)), "") | W18: =IF(is_cat,comb_rank_norm + COUNTIF(INDIRECT(comb_rank_norm_run_range),comb_rank_norm)-1, "") | X18: =IF(is_cat, header_row_id + comb_rank_unique, row_id) -> 20 | Y18: =IF(is_empty, "", INDEX($J:$J,MATCH(row_id, $X:$X, 0))) -> Total | Z18: =IF(is_empty, "", IF(is_header, "Tracked", INDEX($K:$K, MATCH(row_id, $X:$X,0)))) -> 61081.15 | AA18: =IF(is_empty, "", IF(is_header, "Budget", INDEX($L:$L, MATCH(row_id, $X:$X,0)))) -> 140700 | AB18: =IF(is_empty, "", IF(is_header, "% Compl.", IFERROR(out_tracked / out_budget, "-"))) -> 0.43412331 | AC18: =IF(is_empty, "", IF(is_header, "Remaining", IF(out_budget - out_tracked > 0, out_budget - out_tracked, 0))) -> 79618.85 | AD18: =IF(is_empty, "", IF(is_header, "Excess", IF(out_budget - out_tracked < 0, out_tracked - out_budget, 0))) -> 0 | AI18: =Calculations!E37 -> Dividents | AJ18: =Calculations!F37 -> 2050
C19: {=IF(C18=-1,-1, IF(C18<income_max_row,C18+1, IF(C18=income_max_row,income_total_row, IF(C18=income_total_row,"/1", IF(C18="/1",expenses_header_row, IF(C18<expenses_max_row,C18+1, IF(C18=expenses_max_row,expenses_total_row, IF(C18=expenses_total_row,"/2", IF(C18="/2",savings_header_row, IF(C18<savings_max_row,C18+1, IF(C18=savings_max_row,savings_total_row,-1)))))))))))} -> /1 | D19: =IF(is_header,row_id, IF(NOT(is_empty),D18,-1)) -> -1 | E19: {=1*OR(row_id=income_header_row,row_id=expenses_header_row,row_id=savings_header_row)} -> 0 | F19: =1*NOT(OR(is_header,is_total,is_empty)) -> 0 | G19: {=1*OR(row_id=expenses_total_row,row_id=savings_total_row,row_id=income_total_row)} -> 0 | H19: =1*OR(row_id="/1", row_id="/2", row_id=-1) -> 1 | I19: {=IFERROR(INDEX('Budget Planning'!$C:$C, header_row_id), "")} | J19: {=IFERROR(INDEX('Budget Planning'!$C:$C, row_id), "")} | K19: {=IF(OR(is_header, is_empty), "", IF(is_total, IF(selected_period="Total Year", SUM(Tracking[Amount] * (Tracking[Type]=type) * (YEAR(Tracking[Effective Date])=selected_year)), SUM(Tracking[Amount] * (Tracking[Type]=type) * (YEAR(Tracking[Effective Date])=selected_year) * (MONTH(Tracking[Effective Date])=selected_period))), IF(selected_period="Total Year", SUM(Tracking[Amount] * (Tracking[Type]=type) * (Tracking[Category]=item) * (YEAR(Tracking[Effective Date])=selected_year)), SUM(Tracking[Amount] * (Tracking[Type]=type) * (Tracking[Category]=item) * (YEAR(Tracking[Effective Date])=selected_year) * (MONTH(Tracking[Effective Date])=selected_period))) ) )} | L19: {=IF(OR(is_empty,is_header), "", INDEX('Budget Planning'!$E:$AS, row_id, MATCH(IF(selected_period="Total Year", selected_year, DATE(selected_year, selected_period, 1)),'Budget Planning'!$E$9:$AS$9,0) ))} | M19: {=IF(is_cat, IF(header_row_id=income_header_row, MATCH(income_min_row,$C:$C,0), IF(header_row_id=expenses_header_row, MATCH(expenses_min_row,$C:$C,0), IF(header_row_id=savings_header_row, MATCH(savings_min_row,$C:$C,0), ""))), "")} | N19: {=IF(is_cat, IF(header_row_id=income_header_row, MATCH(income_max_row,$C:$C,0), IF(header_row_id=expenses_header_row, MATCH(expenses_max_row,$C:$C,0), IF(header_row_id=savings_header_row, MATCH(savings_max_row,$C:$C,0), ""))), "")} | O19: =IF(is_cat, ADDRESS(sort_min_row, COLUMN(tracked)) & ":" & ADDRESS(sort_max_row,COLUMN(tracked)), "") | P19: =IF(is_cat, RANK(tracked, INDIRECT(tracked_range), 0),"") | Q19: =IF(is_cat, ADDRESS(sort_min_row, COLUMN(budget)) & ":" & ADDRESS(sort_max_row,COLUMN(budget)), "") | R19: =IF(is_cat, RANK(budget, INDIRECT(budget_range), 0),"") | S19: =IF(is_cat, _xlfn.NUMBERVALUE(tracked_rank & budget_rank), "") | T19: =IF(is_cat, ADDRESS(sort_min_row, COLUMN(comb_rank)) & ":" & ADDRESS(sort_max_row,COLUMN(comb_rank)), "") | U19: =IF(is_cat, RANK(comb_rank, INDIRECT(comb_rank_range),1), "") | V19: =IF(is_cat, ADDRESS(sort_min_row, COLUMN(comb_rank_norm)) & ":" & ADDRESS(ROW(),COLUMN(comb_rank_norm)), "") | W19: =IF(is_cat,comb_rank_norm + COUNTIF(INDIRECT(comb_rank_norm_run_range),comb_rank_norm)-1, "") | X19: =IF(is_cat, header_row_id + comb_rank_unique, row_id) -> /1 | Y19: =IF(is_empty, "", INDEX($J:$J,MATCH(row_id, $X:$X, 0))) | Z19: =IF(is_empty, "", IF(is_header, "Tracked", INDEX($K:$K, MATCH(row_id, $X:$X,0)))) | AA19: =IF(is_empty, "", IF(is_header, "Budget", INDEX($L:$L, MATCH(row_id, $X:$X,0)))) | AB19: =IF(is_empty, "", IF(is_header, "% Compl.", IFERROR(out_tracked / out_budget, "-"))) | AC19: =IF(is_empty, "", IF(is_header, "Remaining", IF(out_budget - out_tracked > 0, out_budget - out_tracked, 0))) | AD19: =IF(is_empty, "", IF(is_header, "Excess", IF(out_budget - out_tracked < 0, out_tracked - out_budget, 0))) | AI19: =Calculations!E38 -> Other | AJ19: =Calculations!F38 -> 1000
C20: {=IF(C19=-1,-1, IF(C19<income_max_row,C19+1, IF(C19=income_max_row,income_total_row, IF(C19=income_total_row,"/1", IF(C19="/1",expenses_header_row, IF(C19<expenses_max_row,C19+1, IF(C19=expenses_max_row,expenses_total_row, IF(C19=expenses_total_row,"/2", IF(C19="/2",savings_header_row, IF(C19<savings_max_row,C19+1, IF(C19=savings_max_row,savings_total_row,-1)))))))))))} -> 22 | D20: =IF(is_header,row_id, IF(NOT(is_empty),D19,-1)) -> 22 | E20: {=1*OR(row_id=income_header_row,row_id=expenses_header_row,row_id=savings_header_row)} -> 1 | F20: =1*NOT(OR(is_header,is_total,is_empty)) -> 0 | G20: {=1*OR(row_id=expenses_total_row,row_id=savings_total_row,row_id=income_total_row)} -> 0 | H20: =1*OR(row_id="/1", row_id="/2", row_id=-1) -> 0 | I20: {=IFERROR(INDEX('Budget Planning'!$C:$C, header_row_id), "")} -> Expenses | J20: {=IFERROR(INDEX('Budget Planning'!$C:$C, row_id), "")} -> Expenses | K20: {=IF(OR(is_header, is_empty), "", IF(is_total, IF(selected_period="Total Year", SUM(Tracking[Amount] * (Tracking[Type]=type) * (YEAR(Tracking[Effective Date])=selected_year)), SUM(Tracking[Amount] * (Tracking[Type]=type) * (YEAR(Tracking[Effective Date])=selected_year) * (MONTH(Tracking[Effective Date])=selected_period))), IF(selected_period="Total Year", SUM(Tracking[Amount] * (Tracking[Type]=type) * (Tracking[Category]=item) * (YEAR(Tracking[Effective Date])=selected_year)), SUM(Tracking[Amount] * (Tracking[Type]=type) * (Tracking[Category]=item) * (YEAR(Tracking[Effective Date])=selected_year) * (MONTH(Tracking[Effective Date])=selected_period))) ) )} | L20: {=IF(OR(is_empty,is_header), "", INDEX('Budget Planning'!$E:$AS, row_id, MATCH(IF(selected_period="Total Year", selected_year, DATE(selected_year, selected_period, 1)),'Budget Planning'!$E$9:$AS$9,0) ))} | M20: {=IF(is_cat, IF(header_row_id=income_header_row, MATCH(income_min_row,$C:$C,0), IF(header_row_id=expenses_header_row, MATCH(expenses_min_row,$C:$C,0), IF(header_row_id=savings_header_row, MATCH(savings_min_row,$C:$C,0), ""))), "")} | N20: {=IF(is_cat, IF(header_row_id=income_header_row, MATCH(income_max_row,$C:$C,0), IF(header_row_id=expenses_header_row, MATCH(expenses_max_row,$C:$C,0), IF(header_row_id=savings_header_row, MATCH(savings_max_row,$C:$C,0), ""))), "")} | O20: =IF(is_cat, ADDRESS(sort_min_row, COLUMN(tracked)) & ":" & ADDRESS(sort_max_row,COLUMN(tracked)), "") | P20: =IF(is_cat, RANK(tracked, INDIRECT(tracked_range), 0),"") | Q20: =IF(is_cat, ADDRESS(sort_min_row, COLUMN(budget)) & ":" & ADDRESS(sort_max_row,COLUMN(budget)), "") | R20: =IF(is_cat, RANK(budget, INDIRECT(budget_range), 0),"") | S20: =IF(is_cat, _xlfn.NUMBERVALUE(tracked_rank & budget_rank), "") | T20: =IF(is_cat, ADDRESS(sort_min_row, COLUMN(comb_rank)) & ":" & ADDRESS(sort_max_row,COLUMN(comb_rank)), "") | U20: =IF(is_cat, RANK(comb_rank, INDIRECT(comb_rank_range),1), "") | V20: =IF(is_cat, ADDRESS(sort_min_row, COLUMN(comb_rank_norm)) & ":" & ADDRESS(ROW(),COLUMN(comb_rank_norm)), "") | W20: =IF(is_cat,comb_rank_norm + COUNTIF(INDIRECT(comb_rank_norm_run_range),comb_rank_norm)-1, "") | X20: =IF(is_cat, header_row_id + comb_rank_unique, row_id) -> 22 | Y20: =IF(is_empty, "", INDEX($J:$J,MATCH(row_id, $X:$X, 0))) -> Expenses | Z20: =IF(is_empty, "", IF(is_header, "Tracked", INDEX($K:$K, MATCH(row_id, $X:$X,0)))) -> Tracked | AA20: =IF(is_empty, "", IF(is_header, "Budget", INDEX($L:$L, MATCH(row_id, $X:$X,0)))) -> Budget | AB20: =IF(is_empty, "", IF(is_header, "% Compl.", IFERROR(out_tracked / out_budget, "-"))) -> % Compl. | AC20: =IF(is_empty, "", IF(is_header, "Remaining", IF(out_budget - out_tracked > 0, out_budget - out_tracked, 0))) -> Remaining | AD20: =IF(is_empty, "", IF(is_header, "Excess", IF(out_budget - out_tracked < 0, out_tracked - out_budget, 0))) -> Excess | AI20: =Calculations!E39 | AJ20: =Calculations!F39
C21: {=IF(C20=-1,-1, IF(C20<income_max_row,C20+1, IF(C20=income_max_row,income_total_row, IF(C20=income_total_row,"/1", IF(C20="/1",expenses_header_row, IF(C20<expenses_max_row,C20+1, IF(C20=expenses_max_row,expenses_total_row, IF(C20=expenses_total_row,"/2", IF(C20="/2",savings_header_row, IF(C20<savings_max_row,C20+1, IF(C20=savings_max_row,savings_total_row,-1)))))))))))} -> 23 | D21: =IF(is_header,row_id, IF(NOT(is_empty),D20,-1)) -> 22 | E21: {=1*OR(row_id=income_header_row,row_id=expenses_header_row,row_id=savings_header_row)} -> 0 | F21: =1*NOT(OR(is_header,is_total,is_empty)) -> 1 | G21: {=1*OR(row_id=expenses_total_row,row_id=savings_total_row,row_id=income_total_row)} -> 0 | H21: =1*OR(row_id="/1", row_id="/2", row_id=-1) -> 0 | I21: {=IFERROR(INDEX('Budget Planning'!$C:$C, header_row_id), "")} -> Expenses | J21: {=IFERROR(INDEX('Budget Planning'!$C:$C, row_id), "")} -> Housing | K21: {=IF(OR(is_header, is_empty), "", IF(is_total, IF(selected_period="Total Year", SUM(Tracking[Amount] * (Tracking[Type]=type) * (YEAR(Tracking[Effective Date])=selected_year)), SUM(Tracking[Amount] * (Tracking[Type]=type) * (YEAR(Tracking[Effective Date])=selected_year) * (MONTH(Tracking[Effective Date])=selected_period))), IF(selected_period="Total Year", SUM(Tracking[Amount] * (Tracking[Type]=type) * (Tracking[Category]=item) * (YEAR(Tracking[Effective Date])=selected_year)), SUM(Tracking[Amount] * (Tracking[Type]=type) * (Tracking[Category]=item) * (YEAR(Tracking[Effective Date])=selected_year) * (MONTH(Tracking[Effective Date])=selected_period))) ) )} -> 17400 | L21: {=IF(OR(is_empty,is_header), "", INDEX('Budget Planning'!$E:$AS, row_id, MATCH(IF(selected_period="Total Year", selected_year, DATE(selected_year, selected_period, 1)),'Budget Planning'!$E$9:$AS$9,0) ))} -> 50400 | M21: {=IF(is_cat, IF(header_row_id=income_header_row, MATCH(income_min_row,$C:$C,0), IF(header_row_id=expenses_header_row, MATCH(expenses_min_row,$C:$C,0), IF(header_row_id=savings_header_row, MATCH(savings_min_row,$C:$C,0), ""))), "")} -> 21 | N21: {=IF(is_cat, IF(header_row_id=income_header_row, MATCH(income_max_row,$C:$C,0), IF(header_row_id=expenses_header_row, MATCH(expenses_max_row,$C:$C,0), IF(header_row_id=savings_header_row, MATCH(savings_max_row,$C:$C,0), ""))), "")} -> 26 | O21: =IF(is_cat, ADDRESS(sort_min_row, COLUMN(tracked)) & ":" & ADDRESS(sort_max_row,COLUMN(tracked)), "") -> $K$21:$K$26 | P21: =IF(is_cat, RANK(tracked, INDIRECT(tracked_range), 0),"") -> 1 | Q21: =IF(is_cat, ADDRESS(sort_min_row, COLUMN(budget)) & ":" & ADDRESS(sort_max_row,COLUMN(budget)), "") -> $L$21:$L$26 | R21: =IF(is_cat, RANK(budget, INDIRECT(budget_range), 0),"") -> 1 | S21: =IF(is_cat, _xlfn.NUMBERVALUE(tracked_rank & budget_rank), "") -> 11 | T21: =IF(is_cat, ADDRESS(sort_min_row, COLUMN(comb_rank)) & ":" & ADDRESS(sort_max_row,COLUMN(comb_rank)), "") -> $S$21:$S$26 | U21: =IF(is_cat, RANK(comb_rank, INDIRECT(comb_rank_range),1), "") -> 1 | V21: =IF(is_cat, ADDRESS(sort_min_row, COLUMN(comb_rank_norm)) & ":" & ADDRESS(ROW(),COLUMN(comb_rank_norm)), "") -> $U$21:$U$21 | W21: =IF(is_cat,comb_rank_norm + COUNTIF(INDIRECT(comb_rank_norm_run_range),comb_rank_norm)-1, "") -> 1 | X21: =IF(is_cat, header_row_id + comb_rank_unique, row_id) -> 23 | Y21: =IF(is_empty, "", INDEX($J:$J,MATCH(row_id, $X:$X, 0))) -> Housing | Z21: =IF(is_empty, "", IF(is_header, "Tracked", INDEX($K:$K, MATCH(row_id, $X:$X,0)))) -> 17400 | AA21: =IF(is_empty, "", IF(is_header, "Budget", INDEX($L:$L, MATCH(row_id, $X:$X,0)))) -> 50400 | AB21: =IF(is_empty, "", IF(is_header, "% Compl.", IFERROR(out_tracked / out_budget, "-"))) -> 0.3452381 | AC21: =IF(is_empty, "", IF(is_header, "Remaining", IF(out_budget - out_tracked > 0, out_budget - out_tracked, 0))) -> 33000 | AD21: =IF(is_empty, "", IF(is_header, "Excess", IF(out_budget - out_tracked < 0, out_tracked - out_budget, 0))) -> 0 | AI21: =Calculations!E40 -> Other | AJ21: =Calculations!F40 -> -7.2759576e-12
C22: {=IF(C21=-1,-1, IF(C21<income_max_row,C21+1, IF(C21=income_max_row,income_total_row, IF(C21=income_total_row,"/1", IF(C21="/1",expenses_header_row, IF(C21<expenses_max_row,C21+1, IF(C21=expenses_max_row,expenses_total_row, IF(C21=expenses_total_row,"/2", IF(C21="/2",savings_header_row, IF(C21<savings_max_row,C21+1, IF(C21=savings_max_row,savings_total_row,-1)))))))))))} -> 24 | D22: =IF(is_header,row_id, IF(NOT(is_empty),D21,-1)) -> 22 | E22: {=1*OR(row_id=income_header_row,row_id=expenses_header_row,row_id=savings_header_row)} -> 0 | F22: =1*NOT(OR(is_header,is_total,is_empty)) -> 1 | G22: {=1*OR(row_id=expenses_total_row,row_id=savings_total_row,row_id=income_total_row)} -> 0 | H22: =1*OR(row_id="/1", row_id="/2", row_id=-1) -> 0 | I22: {=IFERROR(INDEX('Budget Planning'!$C:$C, header_row_id), "")} -> Expenses | J22: {=IFERROR(INDEX('Budget Planning'!$C:$C, row_id), "")} -> Groceries | K22: {=IF(OR(is_header, is_empty), "", IF(is_total, IF(selected_period="Total Year", SUM(Tracking[Amount] * (Tracking[Type]=type) * (YEAR(Tracking[Effective Date])=selected_year)), SUM(Tracking[Amount] * (Tracking[Type]=type) * (YEAR(Tracking[Effective Date])=selected_year) * (MONTH(Tracking[Effective Date])=selected_period))), IF(selected_period="Total Year", SUM(Tracking[Amount] * (Tracking[Type]=type) * (Tracking[Category]=item) * (YEAR(Tracking[Effective Date])=selected_year)), SUM(Tracking[Amount] * (Tracking[Type]=type) * (Tracking[Category]=item) * (YEAR(Tracking[Effective Date])=selected_year) * (MONTH(Tracking[Effective Date])=selected_period))) ) )} -> 7300 | L22: {=IF(OR(is_empty,is_header), "", INDEX('Budget Planning'!$E:$AS, row_id, MATCH(IF(selected_period="Total Year", selected_year, DATE(selected_year, selected_period, 1)),'Budget Planning'!$E$9:$AS$9,0) ))} -> 18550 | M22: {=IF(is_cat, IF(header_row_id=income_header_row, MATCH(income_min_row,$C:$C,0), IF(header_row_id=expenses_header_row, MATCH(expenses_min_row,$C:$C,0), IF(header_row_id=savings_header_row, MATCH(savings_min_row,$C:$C,0), ""))), "")} -> 21 | N22: {=IF(is_cat, IF(header_row_id=income_header_row, MATCH(income_max_row,$C:$C,0), IF(header_row_id=expenses_header_row, MATCH(expenses_max_row,$C:$C,0), IF(header_row_id=savings_header_row, MATCH(savings_max_row,$C:$C,0), ""))), "")} -> 26 | O22: =IF(is_cat, ADDRESS(sort_min_row, COLUMN(tracked)) & ":" & ADDRESS(sort_max_row,COLUMN(tracked)), "") -> $K$21:$K$26 | P22: =IF(is_cat, RANK(tracked, INDIRECT(tracked_range), 0),"") -> 2 | Q22: =IF(is_cat, ADDRESS(sort_min_row, COLUMN(budget)) & ":" & ADDRESS(sort_max_row,COLUMN(budget)), "") -> $L$21:$L$26 | R22: =IF(is_cat, RANK(budget, INDIRECT(budget_range), 0),"") -> 2 | S22: =IF(is_cat, _xlfn.NUMBERVALUE(tracked_rank & budget_rank), "") -> 22 | T22: =IF(is_cat, ADDRESS(sort_min_row, COLUMN(comb_rank)) & ":" & ADDRESS(sort_max_row,COLUMN(comb_rank)), "") -> $S$21:$S$26 | U22: =IF(is_cat, RANK(comb_rank, INDIRECT(comb_rank_range),1), "") -> 2 | V22: =IF(is_cat, ADDRESS(sort_min_row, COLUMN(comb_rank_norm)) & ":" & ADDRESS(ROW(),COLUMN(comb_rank_norm)), "") -> $U$21:$U$22 | W22: =IF(is_cat,comb_rank_norm + COUNTIF(INDIRECT(comb_rank_norm_run_range),comb_rank_norm)-1, "") -> 2 | X22: =IF(is_cat, header_row_id + comb_rank_unique, row_id) -> 24 | Y22: =IF(is_empty, "", INDEX($J:$J,MATCH(row_id, $X:$X, 0))) -> Groceries | Z22: =IF(is_empty, "", IF(is_header, "Tracked", INDEX($K:$K, MATCH(row_id, $X:$X,0)))) -> 7300 | AA22: =IF(is_empty, "", IF(is_header, "Budget", INDEX($L:$L, MATCH(row_id, $X:$X,0)))) -> 18550 | AB22: =IF(is_empty, "", IF(is_header, "% Compl.", IFERROR(out_tracked / out_budget, "-"))) -> 0.393531 | AC22: =IF(is_empty, "", IF(is_header, "Remaining", IF(out_budget - out_tracked > 0, out_budget - out_tracked, 0))) -> 11250 | AD22: =IF(is_empty, "", IF(is_header, "Excess", IF(out_budget - out_tracked < 0, out_tracked - out_budget, 0))) -> 0 | AI22: =Calculations!E41 -> Total | AJ22: =Calculations!F41 -> 61081.15
C23: {=IF(C22=-1,-1, IF(C22<income_max_row,C22+1, IF(C22=income_max_row,income_total_row, IF(C22=income_total_row,"/1", IF(C22="/1",expenses_header_row, IF(C22<expenses_max_row,C22+1, IF(C22=expenses_max_row,expenses_total_row, IF(C22=expenses_total_row,"/2", IF(C22="/2",savings_header_row, IF(C22<savings_max_row,C22+1, IF(C22=savings_max_row,savings_total_row,-1)))))))))))} -> 25 | D23: =IF(is_header,row_id, IF(NOT(is_empty),D22,-1)) -> 22 | E23: {=1*OR(row_id=income_header_row,row_id=expenses_header_row,row_id=savings_header_row)} -> 0 | F23: =1*NOT(OR(is_header,is_total,is_empty)) -> 1 | G23: {=1*OR(row_id=expenses_total_row,row_id=savings_total_row,row_id=income_total_row)} -> 0 | H23: =1*OR(row_id="/1", row_id="/2", row_id=-1) -> 0 | I23: {=IFERROR(INDEX('Budget Planning'!$C:$C, header_row_id), "")} -> Expenses | J23: {=IFERROR(INDEX('Budget Planning'!$C:$C, row_id), "")} -> Other | K23: {=IF(OR(is_header, is_empty), "", IF(is_total, IF(selected_period="Total Year", SUM(Tracking[Amount] * (Tracking[Type]=type) * (YEAR(Tracking[Effective Date])=selected_year)), SUM(Tracking[Amount] * (Tracking[Type]=type) * (YEAR(Tracking[Effective Date])=selected_year) * (MONTH(Tracking[Effective Date])=selected_period))), IF(selected_period="Total Year", SUM(Tracking[Amount] * (Tracking[Type]=type) * (Tracking[Category]=item) * (YEAR(Tracking[Effective Date])=selected_year)), SUM(Tracking[Amount] * (Tracking[Type]=type) * (Tracking[Category]=item) * (YEAR(Tracking[Effective Date])=selected_year) * (MONTH(Tracking[Effective Date])=selected_period))) ) )} -> 1100 | L23: {=IF(OR(is_empty,is_header), "", INDEX('Budget Planning'!$E:$AS, row_id, MATCH(IF(selected_period="Total Year", selected_year, DATE(selected_year, selected_period, 1)),'Budget Planning'!$E$9:$AS$9,0) ))} -> 6000 | M23: {=IF(is_cat, IF(header_row_id=income_header_row, MATCH(income_min_row,$C:$C,0), IF(header_row_id=expenses_header_row, MATCH(expenses_min_row,$C:$C,0), IF(header_row_id=savings_header_row, MATCH(savings_min_row,$C:$C,0), ""))), "")} -> 21 | N23: {=IF(is_cat, IF(header_row_id=income_header_row, MATCH(income_max_row,$C:$C,0), IF(header_row_id=expenses_header_row, MATCH(expenses_max_row,$C:$C,0), IF(header_row_id=savings_header_row, MATCH(savings_max_row,$C:$C,0), ""))), "")} -> 26 | O23: =IF(is_cat, ADDRESS(sort_min_row, COLUMN(tracked)) & ":" & ADDRESS(sort_max_row,COLUMN(tracked)), "") -> $K$21:$K$26 | P23: =IF(is_cat, RANK(tracked, INDIRECT(tracked_range), 0),"") -> 5 | Q23: =IF(is_cat, ADDRESS(sort_min_row, COLUMN(budget)) & ":" & ADDRESS(sort_max_row,COLUMN(budget)), "") -> $L$21:$L$26 | R23: =IF(is_cat, RANK(budget, INDIRECT(budget_range), 0),"") -> 3 | S23: =IF(is_cat, _xlfn.NUMBERVALUE(tracked_rank & budget_rank), "") -> 53 | T23: =IF(is_cat, ADDRESS(sort_min_row, COLUMN(comb_rank)) & ":" & ADDRESS(sort_max_row,COLUMN(comb_rank)), "") -> $S$21:$S$26 | U23: =IF(is_cat, RANK(comb_rank, INDIRECT(comb_rank_range),1), "") -> 5 | V23: =IF(is_cat, ADDRESS(sort_min_row, COLUMN(comb_rank_norm)) & ":" & ADDRESS(ROW(),COLUMN(comb_rank_norm)), "") -> $U$21:$U$23 | W23: =IF(is_cat,comb_rank_norm + COUNTIF(INDIRECT(comb_rank_norm_run_range),comb_rank_norm)-1, "") -> 5 | X23: =IF(is_cat, header_row_id + comb_rank_unique, row_id) -> 27 | Y23: =IF(is_empty, "", INDEX($J:$J,MATCH(row_id, $X:$X, 0))) -> Technologies | Z23: =IF(is_empty, "", IF(is_header, "Tracked", INDEX($K:$K, MATCH(row_id, $X:$X,0)))) -> 2800 | AA23: =IF(is_empty, "", IF(is_header, "Budget", INDEX($L:$L, MATCH(row_id, $X:$X,0)))) -> 2550 | AB23: =IF(is_empty, "", IF(is_header, "% Compl.", IFERROR(out_tracked / out_budget, "-"))) -> 1.0980392 | AC23: =IF(is_empty, "", IF(is_header, "Remaining", IF(out_budget - out_tracked > 0, out_budget - out_tracked, 0))) -> 0 | AD23: =IF(is_empty, "", IF(is_header, "Excess", IF(out_budget - out_tracked < 0, out_tracked - out_budget, 0))) -> 250
C24: {=IF(C23=-1,-1, IF(C23<income_max_row,C23+1, IF(C23=income_max_row,income_total_row, IF(C23=income_total_row,"/1", IF(C23="/1",expenses_header_row, IF(C23<expenses_max_row,C23+1, IF(C23=expenses_max_row,expenses_total_row, IF(C23=expenses_total_row,"/2", IF(C23="/2",savings_header_row, IF(C23<savings_max_row,C23+1, IF(C23=savings_max_row,savings_total_row,-1)))))))))))} -> 26 | D24: =IF(is_header,row_id, IF(NOT(is_empty),D23,-1)) -> 22 | E24: {=1*OR(row_id=income_header_row,row_id=expenses_header_row,row_id=savings_header_row)} -> 0 | F24: =1*NOT(OR(is_header,is_total,is_empty)) -> 1 | G24: {=1*OR(row_id=expenses_total_row,row_id=savings_total_row,row_id=income_total_row)} -> 0 | H24: =1*OR(row_id="/1", row_id="/2", row_id=-1) -> 0 | I24: {=IFERROR(INDEX('Budget Planning'!$C:$C, header_row_id), "")} -> Expenses | J24: {=IFERROR(INDEX('Budget Planning'!$C:$C, row_id), "")} -> Transport | K24: {=IF(OR(is_header, is_empty), "", IF(is_total, IF(selected_period="Total Year", SUM(Tracking[Amount] * (Tracking[Type]=type) * (YEAR(Tracking[Effective Date])=selected_year)), SUM(Tracking[Amount] * (Tracking[Type]=type) * (YEAR(Tracking[Effective Date])=selected_year) * (MONTH(Tracking[Effective Date])=selected_period))), IF(selected_period="Total Year", SUM(Tracking[Amount] * (Tracking[Type]=type) * (Tracking[Category]=item) * (YEAR(Tracking[Effective Date])=selected_year)), SUM(Tracking[Amount] * (Tracking[Type]=type) * (Tracking[Category]=item) * (YEAR(Tracking[Effective Date])=selected_year) * (MONTH(Tracking[Effective Date])=selected_period))) ) )} -> 2800 | L24: {=IF(OR(is_empty,is_header), "", INDEX('Budget Planning'!$E:$AS, row_id, MATCH(IF(selected_period="Total Year", selected_year, DATE(selected_year, selected_period, 1)),'Budget Planning'!$E$9:$AS$9,0) ))} -> 2350 | M24: {=IF(is_cat, IF(header_row_id=income_header_row, MATCH(income_min_row,$C:$C,0), IF(header_row_id=expenses_header_row, MATCH(expenses_min_row,$C:$C,0), IF(header_row_id=savings_header_row, MATCH(savings_min_row,$C:$C,0), ""))), "")} -> 21 | N24: {=IF(is_cat, IF(header_row_id=income_header_row, MATCH(income_max_row,$C:$C,0), IF(header_row_id=expenses_header_row, MATCH(expenses_max_row,$C:$C,0), IF(header_row_id=savings_header_row, MATCH(savings_max_row,$C:$C,0), ""))), "")} -> 26 | O24: =IF(is_cat, ADDRESS(sort_min_row, COLUMN(tracked)) & ":" & ADDRESS(sort_max_row,COLUMN(tracked)), "") -> $K$21:$K$26 | P24: =IF(is_cat, RANK(tracked, INDIRECT(tracked_range), 0),"") -> 3 | Q24: =IF(is_cat, ADDRESS(sort_min_row, COLUMN(budget)) & ":" & ADDRESS(sort_max_row,COLUMN(budget)), "") -> $L$21:$L$26 | R24: =IF(is_cat, RANK(budget, INDIRECT(budget_range), 0),"") -> 6 | S24: =IF(is_cat, _xlfn.NUMBERVALUE(tracked_rank & budget_rank), "") -> 36 | T24: =IF(is_cat, ADDRESS(sort_min_row, COLUMN(comb_rank)) & ":" & ADDRESS(sort_max_row,COLUMN(comb_rank)), "") -> $S$21:$S$26 | U24: =IF(is_cat, RANK(comb_rank, INDIRECT(comb_rank_range),1), "") -> 4 | V24: =IF(is_cat, ADDRESS(sort_min_row, COLUMN(comb_rank_norm)) & ":" & ADDRESS(ROW(),COLUMN(comb_rank_norm)), "") -> $U$21:$U$24 | W24: =IF(is_cat,comb_rank_norm + COUNTIF(INDIRECT(comb_rank_norm_run_range),comb_rank_norm)-1, "") -> 4 | X24: =IF(is_cat, header_row_id + comb_rank_unique, row_id) -> 26 | Y24: =IF(is_empty, "", INDEX($J:$J,MATCH(row_id, $X:$X, 0))) -> Transport | Z24: =IF(is_empty, "", IF(is_header, "Tracked", INDEX($K:$K, MATCH(row_id, $X:$X,0)))) -> 2800 | AA24: =IF(is_empty, "", IF(is_header, "Budget", INDEX($L:$L, MATCH(row_id, $X:$X,0)))) -> 2350 | AB24: =IF(is_empty, "", IF(is_header, "% Compl.", IFERROR(out_tracked / out_budget, "-"))) -> 1.1914894 | AC24: =IF(is_empty, "", IF(is_header, "Remaining", IF(out_budget - out_tracked > 0, out_budget - out_tracked, 0))) -> 0 | AD24: =IF(is_empty, "", IF(is_header, "Excess", IF(out_budget - out_tracked < 0, out_tracked - out_budget, 0))) -> 450
C25: {=IF(C24=-1,-1, IF(C24<income_max_row,C24+1, IF(C24=income_max_row,income_total_row, IF(C24=income_total_row,"/1", IF(C24="/1",expenses_header_row, IF(C24<expenses_max_row,C24+1, IF(C24=expenses_max_row,expenses_total_row, IF(C24=expenses_total_row,"/2", IF(C24="/2",savings_header_row, IF(C24<savings_max_row,C24+1, IF(C24=savings_max_row,savings_total_row,-1)))))))))))} -> 27 | D25: =IF(is_header,row_id, IF(NOT(is_empty),D24,-1)) -> 22 | E25: {=1*OR(row_id=income_header_row,row_id=expenses_header_row,row_id=savings_header_row)} -> 0 | F25: =1*NOT(OR(is_header,is_total,is_empty)) -> 1 | G25: {=1*OR(row_id=expenses_total_row,row_id=savings_total_row,row_id=income_total_row)} -> 0 | H25: =1*OR(row_id="/1", row_id="/2", row_id=-1) -> 0 | I25: {=IFERROR(INDEX('Budget Planning'!$C:$C, header_row_id), "")} -> Expenses | J25: {=IFERROR(INDEX('Budget Planning'!$C:$C, row_id), "")} -> Studies | K25: {=IF(OR(is_header, is_empty), "", IF(is_total, IF(selected_period="Total Year", SUM(Tracking[Amount] * (Tracking[Type]=type) * (YEAR(Tracking[Effective Date])=selected_year)), SUM(Tracking[Amount] * (Tracking[Type]=type) * (YEAR(Tracking[Effective Date])=selected_year) * (MONTH(Tracking[Effective Date])=selected_period))), IF(selected_period="Total Year", SUM(Tracking[Amount] * (Tracking[Type]=type) * (Tracking[Category]=item) * (YEAR(Tracking[Effective Date])=selected_year)), SUM(Tracking[Amount] * (Tracking[Type]=type) * (Tracking[Category]=item) * (YEAR(Tracking[Effective Date])=selected_year) * (MONTH(Tracking[Effective Date])=selected_period))) ) )} -> 950 | L25: {=IF(OR(is_empty,is_header), "", INDEX('Budget Planning'!$E:$AS, row_id, MATCH(IF(selected_period="Total Year", selected_year, DATE(selected_year, selected_period, 1)),'Budget Planning'!$E$9:$AS$9,0) ))} -> 3500 | M25: {=IF(is_cat, IF(header_row_id=income_header_row, MATCH(income_min_row,$C:$C,0), IF(header_row_id=expenses_header_row, MATCH(expenses_min_row,$C:$C,0), IF(header_row_id=savings_header_row, MATCH(savings_min_row,$C:$C,0), ""))), "")} -> 21 | N25: {=IF(is_cat, IF(header_row_id=income_header_row, MATCH(income_max_row,$C:$C,0), IF(header_row_id=expenses_header_row, MATCH(expenses_max_row,$C:$C,0), IF(header_row_id=savings_header_row, MATCH(savings_max_row,$C:$C,0), ""))), "")} -> 26 | O25: =IF(is_cat, ADDRESS(sort_min_row, COLUMN(tracked)) & ":" & ADDRESS(sort_max_row,COLUMN(tracked)), "") -> $K$21:$K$26 | P25: =IF(is_cat, RANK(tracked, INDIRECT(tracked_range), 0),"") -> 6 | Q25: =IF(is_cat, ADDRESS(sort_min_row, COLUMN(budget)) & ":" & ADDRESS(sort_max_row,COLUMN(budget)), "") -> $L$21:$L$26 | R25: =IF(is_cat, RANK(budget, INDIRECT(budget_range), 0),"") -> 4 | S25: =IF(is_cat, _xlfn.NUMBERVALUE(tracked_rank & budget_rank), "") -> 64 | T25: =IF(is_cat, ADDRESS(sort_min_row, COLUMN(comb_rank)) & ":" & ADDRESS(sort_max_row,COLUMN(comb_rank)), "") -> $S$21:$S$26 | U25: =IF(is_cat, RANK(comb_rank, INDIRECT(comb_rank_range),1), "") -> 6 | V25: =IF(is_cat, ADDRESS(sort_min_row, COLUMN(comb_rank_norm)) & ":" & ADDRESS(ROW(),COLUMN(comb_rank_norm)), "") -> $U$21:$U$25 | W25: =IF(is_cat,comb_rank_norm + COUNTIF(INDIRECT(comb_rank_norm_run_range),comb_rank_norm)-1, "") -> 6 | X25: =IF(is_cat, header_row_id + comb_rank_unique, row_id) -> 28 | Y25: =IF(is_empty, "", INDEX($J:$J,MATCH(row_id, $X:$X, 0))) -> Other | Z25: =IF(is_empty, "", IF(is_header, "Tracked", INDEX($K:$K, MATCH(row_id, $X:$X,0)))) -> 1100 | AA25: =IF(is_empty, "", IF(is_header, "Budget", INDEX($L:$L, MATCH(row_id, $X:$X,0)))) -> 6000 | AB25: =IF(is_empty, "", IF(is_header, "% Compl.", IFERROR(out_tracked / out_budget, "-"))) -> 0.18333333 | AC25: =IF(is_empty, "", IF(is_header, "Remaining", IF(out_budget - out_tracked > 0, out_budget - out_tracked, 0))) -> 4900 | AD25: =IF(is_empty, "", IF(is_header, "Excess", IF(out_budget - out_tracked < 0, out_tracked - out_budget, 0))) -> 0
C26: {=IF(C25=-1,-1, IF(C25<income_max_row,C25+1, IF(C25=income_max_row,income_total_row, IF(C25=income_total_row,"/1", IF(C25="/1",expenses_header_row, IF(C25<expenses_max_row,C25+1, IF(C25=expenses_max_row,expenses_total_row, IF(C25=expenses_total_row,"/2", IF(C25="/2",savings_header_row, IF(C25<savings_max_row,C25+1, IF(C25=savings_max_row,savings_total_row,-1)))))))))))} -> 28 | D26: =IF(is_header,row_id, IF(NOT(is_empty),D25,-1)) -> 22 | E26: {=1*OR(row_id=income_header_row,row_id=expenses_header_row,row_id=savings_header_row)} -> 0 | F26: =1*NOT(OR(is_header,is_total,is_empty)) -> 1 | G26: {=1*OR(row_id=expenses_total_row,row_id=savings_total_row,row_id=income_total_row)} -> 0 | H26: =1*OR(row_id="/1", row_id="/2", row_id=-1) -> 0 | I26: {=IFERROR(INDEX('Budget Planning'!$C:$C, header_row_id), "")} -> Expenses | J26: {=IFERROR(INDEX('Budget Planning'!$C:$C, row_id), "")} -> Technologies | K26: {=IF(OR(is_header, is_empty), "", IF(is_total, IF(selected_period="Total Year", SUM(Tracking[Amount] * (Tracking[Type]=type) * (YEAR(Tracking[Effective Date])=selected_year)), SUM(Tracking[Amount] * (Tracking[Type]=type) * (YEAR(Tracking[Effective Date])=selected_year) * (MONTH(Tracking[Effective Date])=selected_period))), IF(selected_period="Total Year", SUM(Tracking[Amount] * (Tracking[Type]=type) * (Tracking[Category]=item) * (YEAR(Tracking[Effective Date])=selected_year)), SUM(Tracking[Amount] * (Tracking[Type]=type) * (Tracking[Category]=item) * (YEAR(Tracking[Effective Date])=selected_year) * (MONTH(Tracking[Effective Date])=selected_period))) ) )} -> 2800 | L26: {=IF(OR(is_empty,is_header), "", INDEX('Budget Planning'!$E:$AS, row_id, MATCH(IF(selected_period="Total Year", selected_year, DATE(selected_year, selected_period, 1)),'Budget Planning'!$E$9:$AS$9,0) ))} -> 2550 | M26: {=IF(is_cat, IF(header_row_id=income_header_row, MATCH(income_min_row,$C:$C,0), IF(header_row_id=expenses_header_row, MATCH(expenses_min_row,$C:$C,0), IF(header_row_id=savings_header_row, MATCH(savings_min_row,$C:$C,0), ""))), "")} -> 21 | N26: {=IF(is_cat, IF(header_row_id=income_header_row, MATCH(income_max_row,$C:$C,0), IF(header_row_id=expenses_header_row, MATCH(expenses_max_row,$C:$C,0), IF(header_row_id=savings_header_row, MATCH(savings_max_row,$C:$C,0), ""))), "")} -> 26 | O26: =IF(is_cat, ADDRESS(sort_min_row, COLUMN(tracked)) & ":" & ADDRESS(sort_max_row,COLUMN(tracked)), "") -> $K$21:$K$26 | P26: =IF(is_cat, RANK(tracked, INDIRECT(tracked_range), 0),"") -> 3 | Q26: =IF(is_cat, ADDRESS(sort_min_row, COLUMN(budget)) & ":" & ADDRESS(sort_max_row,COLUMN(budget)), "") -> $L$21:$L$26 | R26: =IF(is_cat, RANK(budget, INDIRECT(budget_range), 0),"") -> 5 | S26: =IF(is_cat, _xlfn.NUMBERVALUE(tracked_rank & budget_rank), "") -> 35 | T26: =IF(is_cat, ADDRESS(sort_min_row, COLUMN(comb_rank)) & ":" & ADDRESS(sort_max_row,COLUMN(comb_rank)), "") -> $S$21:$S$26 | U26: =IF(is_cat, RANK(comb_rank, INDIRECT(comb_rank_range),1), "") -> 3 | V26: =IF(is_cat, ADDRESS(sort_min_row, COLUMN(comb_rank_norm)) & ":" & ADDRESS(ROW(),COLUMN(comb_rank_norm)), "") -> $U$21:$U$26 | W26: =IF(is_cat,comb_rank_norm + COUNTIF(INDIRECT(comb_rank_norm_run_range),comb_rank_norm)-1, "") -> 3 | X26: =IF(is_cat, header_row_id + comb_rank_unique, row_id) -> 25 | Y26: =IF(is_empty, "", INDEX($J:$J,MATCH(row_id, $X:$X, 0))) -> Studies | Z26: =IF(is_empty, "", IF(is_header, "Tracked", INDEX($K:$K, MATCH(row_id, $X:$X,0)))) -> 950 | AA26: =IF(is_empty, "", IF(is_header, "Budget", INDEX($L:$L, MATCH(row_id, $X:$X,0)))) -> 3500 | AB26: =IF(is_empty, "", IF(is_header, "% Compl.", IFERROR(out_tracked / out_budget, "-"))) -> 0.27142857 | AC26: =IF(is_empty, "", IF(is_header, "Remaining", IF(out_budget - out_tracked > 0, out_budget - out_tracked, 0))) -> 2550 | AD26: =IF(is_empty, "", IF(is_header, "Excess", IF(out_budget - out_tracked < 0, out_tracked - out_budget, 0))) -> 0
C27: {=IF(C26=-1,-1, IF(C26<income_max_row,C26+1, IF(C26=income_max_row,income_total_row, IF(C26=income_total_row,"/1", IF(C26="/1",expenses_header_row, IF(C26<expenses_max_row,C26+1, IF(C26=expenses_max_row,expenses_total_row, IF(C26=expenses_total_row,"/2", IF(C26="/2",savings_header_row, IF(C26<savings_max_row,C26+1, IF(C26=savings_max_row,savings_total_row,-1)))))))))))} -> 30 | D27: =IF(is_header,row_id, IF(NOT(is_empty),D26,-1)) -> 22 | E27: {=1*OR(row_id=income_header_row,row_id=expenses_header_row,row_id=savings_header_row)} -> 0 | F27: =1*NOT(OR(is_header,is_total,is_empty)) -> 0 | G27: {=1*OR(row_id=expenses_total_row,row_id=savings_total_row,row_id=income_total_row)} -> 1 | H27: =1*OR(row_id="/1", row_id="/2", row_id=-1) -> 0 | I27: {=IFERROR(INDEX('Budget Planning'!$C:$C, header_row_id), "")} -> Expenses | J27: {=IFERROR(INDEX('Budget Planning'!$C:$C, row_id), "")} -> Total | K27: {=IF(OR(is_header, is_empty), "", IF(is_total, IF(selected_period="Total Year", SUM(Tracking[Amount] * (Tracking[Type]=type) * (YEAR(Tracking[Effective Date])=selected_year)), SUM(Tracking[Amount] * (Tracking[Type]=type) * (YEAR(Tracking[Effective Date])=selected_year) * (MONTH(Tracking[Effective Date])=selected_period))), IF(selected_period="Total Year", SUM(Tracking[Amount] * (Tracking[Type]=type) * (Tracking[Category]=item) * (YEAR(Tracking[Effective Date])=selected_year)), SUM(Tracking[Amount] * (Tracking[Type]=type) * (Tracking[Category]=item) * (YEAR(Tracking[Effective Date])=selected_year) * (MONTH(Tracking[Effective Date])=selected_period))) ) )} -> 32350 | L27: {=IF(OR(is_empty,is_header), "", INDEX('Budget Planning'!$E:$AS, row_id, MATCH(IF(selected_period="Total Year", selected_year, DATE(selected_year, selected_period, 1)),'Budget Planning'!$E$9:$AS$9,0) ))} -> 83350 | M27: {=IF(is_cat, IF(header_row_id=income_header_row, MATCH(income_min_row,$C:$C,0), IF(header_row_id=expenses_header_row, MATCH(expenses_min_row,$C:$C,0), IF(header_row_id=savings_header_row, MATCH(savings_min_row,$C:$C,0), ""))), "")} | N27: {=IF(is_cat, IF(header_row_id=income_header_row, MATCH(income_max_row,$C:$C,0), IF(header_row_id=expenses_header_row, MATCH(expenses_max_row,$C:$C,0), IF(header_row_id=savings_header_row, MATCH(savings_max_row,$C:$C,0), ""))), "")} | O27: =IF(is_cat, ADDRESS(sort_min_row, COLUMN(tracked)) & ":" & ADDRESS(sort_max_row,COLUMN(tracked)), "") | P27: =IF(is_cat, RANK(tracked, INDIRECT(tracked_range), 0),"") | Q27: =IF(is_cat, ADDRESS(sort_min_row, COLUMN(budget)) & ":" & ADDRESS(sort_max_row,COLUMN(budget)), "") | R27: =IF(is_cat, RANK(budget, INDIRECT(budget_range), 0),"") | S27: =IF(is_cat, _xlfn.NUMBERVALUE(tracked_rank & budget_rank), "") | T27: =IF(is_cat, ADDRESS(sort_min_row, COLUMN(comb_rank)) & ":" & ADDRESS(sort_max_row,COLUMN(comb_rank)), "") | U27: =IF(is_cat, RANK(comb_rank, INDIRECT(comb_rank_range),1), "") | V27: =IF(is_cat, ADDRESS(sort_min_row, COLUMN(comb_rank_norm)) & ":" & ADDRESS(ROW(),COLUMN(comb_rank_norm)), "") | W27: =IF(is_cat,comb_rank_norm + COUNTIF(INDIRECT(comb_rank_norm_run_range),comb_rank_norm)-1, "") | X27: =IF(is_cat, header_row_id + comb_rank_unique, row_id) -> 30 | Y27: =IF(is_empty, "", INDEX($J:$J,MATCH(row_id, $X:$X, 0))) -> Total | Z27: =IF(is_empty, "", IF(is_header, "Tracked", INDEX($K:$K, MATCH(row_id, $X:$X,0)))) -> 32350 | AA27: =IF(is_empty, "", IF(is_header, "Budget", INDEX($L:$L, MATCH(row_id, $X:$X,0)))) -> 83350 | AB27: =IF(is_empty, "", IF(is_header, "% Compl.", IFERROR(out_tracked / out_budget, "-"))) -> 0.38812238 | AC27: =IF(is_empty, "", IF(is_header, "Remaining", IF(out_budget - out_tracked > 0, out_budget - out_tracked, 0))) -> 51000 | AD27: =IF(is_empty, "", IF(is_header, "Excess", IF(out_budget - out_tracked < 0, out_tracked - out_budget, 0))) -> 0
C28: {=IF(C27=-1,-1, IF(C27<income_max_row,C27+1, IF(C27=income_max_row,income_total_row, IF(C27=income_total_row,"/1", IF(C27="/1",expenses_header_row, IF(C27<expenses_max_row,C27+1, IF(C27=expenses_max_row,expenses_total_row, IF(C27=expenses_total_row,"/2", IF(C27="/2",savings_header_row, IF(C27<savings_max_row,C27+1, IF(C27=savings_max_row,savings_total_row,-1)))))))))))} -> /2 | D28: =IF(is_header,row_id, IF(NOT(is_empty),D27,-1)) -> -1 | E28: {=1*OR(row_id=income_header_row,row_id=expenses_header_row,row_id=savings_header_row)} -> 0 | F28: =1*NOT(OR(is_header,is_total,is_empty)) -> 0 | G28: {=1*OR(row_id=expenses_total_row,row_id=savings_total_row,row_id=income_total_row)} -> 0 | H28: =1*OR(row_id="/1", row_id="/2", row_id=-1) -> 1 | I28: {=IFERROR(INDEX('Budget Planning'!$C:$C, header_row_id), "")} | J28: {=IFERROR(INDEX('Budget Planning'!$C:$C, row_id), "")} | K28: {=IF(OR(is_header, is_empty), "", IF(is_total, IF(selected_period="Total Year", SUM(Tracking[Amount] * (Tracking[Type]=type) * (YEAR(Tracking[Effective Date])=selected_year)), SUM(Tracking[Amount] * (Tracking[Type]=type) * (YEAR(Tracking[Effective Date])=selected_year) * (MONTH(Tracking[Effective Date])=selected_period))), IF(selected_period="Total Year", SUM(Tracking[Amount] * (Tracking[Type]=type) * (Tracking[Category]=item) * (YEAR(Tracking[Effective Date])=selected_year)), SUM(Tracking[Amount] * (Tracking[Type]=type) * (Tracking[Category]=item) * (YEAR(Tracking[Effective Date])=selected_year) * (MONTH(Tracking[Effective Date])=selected_period))) ) )} | L28: {=IF(OR(is_empty,is_header), "", INDEX('Budget Planning'!$E:$AS, row_id, MATCH(IF(selected_period="Total Year", selected_year, DATE(selected_year, selected_period, 1)),'Budget Planning'!$E$9:$AS$9,0) ))} | M28: {=IF(is_cat, IF(header_row_id=income_header_row, MATCH(income_min_row,$C:$C,0), IF(header_row_id=expenses_header_row, MATCH(expenses_min_row,$C:$C,0), IF(header_row_id=savings_header_row, MATCH(savings_min_row,$C:$C,0), ""))), "")} | N28: {=IF(is_cat, IF(header_row_id=income_header_row, MATCH(income_max_row,$C:$C,0), IF(header_row_id=expenses_header_row, MATCH(expenses_max_row,$C:$C,0), IF(header_row_id=savings_header_row, MATCH(savings_max_row,$C:$C,0), ""))), "")} | O28: =IF(is_cat, ADDRESS(sort_min_row, COLUMN(tracked)) & ":" & ADDRESS(sort_max_row,COLUMN(tracked)), "") | P28: =IF(is_cat, RANK(tracked, INDIRECT(tracked_range), 0),"") | Q28: =IF(is_cat, ADDRESS(sort_min_row, COLUMN(budget)) & ":" & ADDRESS(sort_max_row,COLUMN(budget)), "") | R28: =IF(is_cat, RANK(budget, INDIRECT(budget_range), 0),"") | S28: =IF(is_cat, _xlfn.NUMBERVALUE(tracked_rank & budget_rank), "") | T28: =IF(is_cat, ADDRESS(sort_min_row, COLUMN(comb_rank)) & ":" & ADDRESS(sort_max_row,COLUMN(comb_rank)), "") | U28: =IF(is_cat, RANK(comb_rank, INDIRECT(comb_rank_range),1), "") | V28: =IF(is_cat, ADDRESS(sort_min_row, COLUMN(comb_rank_norm)) & ":" & ADDRESS(ROW(),COLUMN(comb_rank_norm)), "") | W28: =IF(is_cat,comb_rank_norm + COUNTIF(INDIRECT(comb_rank_norm_run_range),comb_rank_norm)-1, "") | X28: =IF(is_cat, header_row_id + comb_rank_unique, row_id) -> /2 | Y28: =IF(is_empty, "", INDEX($J:$J,MATCH(row_id, $X:$X, 0))) | Z28: =IF(is_empty, "", IF(is_header, "Tracked", INDEX($K:$K, MATCH(row_id, $X:$X,0)))) | AA28: =IF(is_empty, "", IF(is_header, "Budget", INDEX($L:$L, MATCH(row_id, $X:$X,0)))) | AB28: =IF(is_empty, "", IF(is_header, "% Compl.", IFERROR(out_tracked / out_budget, "-"))) | AC28: =IF(is_empty, "", IF(is_header, "Remaining", IF(out_budget - out_tracked > 0, out_budget - out_tracked, 0))) | AD28: =IF(is_empty, "", IF(is_header, "Excess", IF(out_budget - out_tracked < 0, out_tracked - out_budget, 0)))
C29: {=IF(C28=-1,-1, IF(C28<income_max_row,C28+1, IF(C28=income_max_row,income_total_row, IF(C28=income_total_row,"/1", IF(C28="/1",expenses_header_row, IF(C28<expenses_max_row,C28+1, IF(C28=expenses_max_row,expenses_total_row, IF(C28=expenses_total_row,"/2", IF(C28="/2",savings_header_row, IF(C28<savings_max_row,C28+1, IF(C28=savings_max_row,savings_total_row,-1)))))))))))} -> 32 | D29: =IF(is_header,row_id, IF(NOT(is_empty),D28,-1)) -> 32 | E29: {=1*OR(row_id=income_header_row,row_id=expenses_header_row,row_id=savings_header_row)} -> 1 | F29: =1*NOT(OR(is_header,is_total,is_empty)) -> 0 | G29: {=1*OR(row_id=expenses_total_row,row_id=savings_total_row,row_id=income_total_row)} -> 0 | H29: =1*OR(row_id="/1", row_id="/2", row_id=-1) -> 0 | I29: {=IFERROR(INDEX('Budget Planning'!$C:$C, header_row_id), "")} -> Savings | J29: {=IFERROR(INDEX('Budget Planning'!$C:$C, row_id), "")} -> Savings | K29: {=IF(OR(is_header, is_empty), "", IF(is_total, IF(selected_period="Total Year", SUM(Tracking[Amount] * (Tracking[Type]=type) * (YEAR(Tracking[Effective Date])=selected_year)), SUM(Tracking[Amount] * (Tracking[Type]=type) * (YEAR(Tracking[Effective Date])=selected_year) * (MONTH(Tracking[Effective Date])=selected_period))), IF(selected_period="Total Year", SUM(Tracking[Amount] * (Tracking[Type]=type) * (Tracking[Category]=item) * (YEAR(Tracking[Effective Date])=selected_year)), SUM(Tracking[Amount] * (Tracking[Type]=type) * (Tracking[Category]=item) * (YEAR(Tracking[Effective Date])=selected_year) * (MONTH(Tracking[Effective Date])=selected_period))) ) )} | L29: {=IF(OR(is_empty,is_header), "", INDEX('Budget Planning'!$E:$AS, row_id, MATCH(IF(selected_period="Total Year", selected_year, DATE(selected_year, selected_period, 1)),'Budget Planning'!$E$9:$AS$9,0) ))} | M29: {=IF(is_cat, IF(header_row_id=income_header_row, MATCH(income_min_row,$C:$C,0), IF(header_row_id=expenses_header_row, MATCH(expenses_min_row,$C:$C,0), IF(header_row_id=savings_header_row, MATCH(savings_min_row,$C:$C,0), ""))), "")} | N29: {=IF(is_cat, IF(header_row_id=income_header_row, MATCH(income_max_row,$C:$C,0), IF(header_row_id=expenses_header_row, MATCH(expenses_max_row,$C:$C,0), IF(header_row_id=savings_header_row, MATCH(savings_max_row,$C:$C,0), ""))), "")} | O29: =IF(is_cat, ADDRESS(sort_min_row, COLUMN(tracked)) & ":" & ADDRESS(sort_max_row,COLUMN(tracked)), "") | P29: =IF(is_cat, RANK(tracked, INDIRECT(tracked_range), 0),"") | Q29: =IF(is_cat, ADDRESS(sort_min_row, COLUMN(budget)) & ":" & ADDRESS(sort_max_row,COLUMN(budget)), "") | R29: =IF(is_cat, RANK(budget, INDIRECT(budget_range), 0),"") | S29: =IF(is_cat, _xlfn.NUMBERVALUE(tracked_rank & budget_rank), "") | T29: =IF(is_cat, ADDRESS(sort_min_row, COLUMN(comb_rank)) & ":" & ADDRESS(sort_max_row,COLUMN(comb_rank)), "") | U29: =IF(is_cat, RANK(comb_rank, INDIRECT(comb_rank_range),1), "") | V29: =IF(is_cat, ADDRESS(sort_min_row, COLUMN(comb_rank_norm)) & ":" & ADDRESS(ROW(),COLUMN(comb_rank_norm)), "") | W29: =IF(is_cat,comb_rank_norm + COUNTIF(INDIRECT(comb_rank_norm_run_range),comb_rank_norm)-1, "") | X29: =IF(is_cat, header_row_id + comb_rank_unique, row_id) -> 32 | Y29: =IF(is_empty, "", INDEX($J:$J,MATCH(row_id, $X:$X, 0))) -> Savings | Z29: =IF(is_empty, "", IF(is_header, "Tracked", INDEX($K:$K, MATCH(row_id, $X:$X,0)))) -> Tracked | AA29: =IF(is_empty, "", IF(is_header, "Budget", INDEX($L:$L, MATCH(row_id, $X:$X,0)))) -> Budget | AB29: =IF(is_empty, "", IF(is_header, "% Compl.", IFERROR(out_tracked / out_budget, "-"))) -> % Compl. | AC29: =IF(is_empty, "", IF(is_header, "Remaining", IF(out_budget - out_tracked > 0, out_budget - out_tracked, 0))) -> Remaining | AD29: =IF(is_empty, "", IF(is_header, "Excess", IF(out_budget - out_tracked < 0, out_tracked - out_budget, 0))) -> Excess | AI29: =Calculations!I35 -> Housing | AJ29: =Calculations!J35 -> 17400 | AP29: =Calculations!M35 -> Stock Portfolio | AQ29: =Calculations!N35 -> 6100
C30: {=IF(C29=-1,-1, IF(C29<income_max_row,C29+1, IF(C29=income_max_row,income_total_row, IF(C29=income_total_row,"/1", IF(C29="/1",expenses_header_row, IF(C29<expenses_max_row,C29+1, IF(C29=expenses_max_row,expenses_total_row, IF(C29=expenses_total_row,"/2", IF(C29="/2",savings_header_row, IF(C29<savings_max_row,C29+1, IF(C29=savings_max_row,savings_total_row,-1)))))))))))} -> 33 | D30: =IF(is_header,row_id, IF(NOT(is_empty),D29,-1)) -> 32 | E30: {=1*OR(row_id=income_header_row,row_id=expenses_header_row,row_id=savings_header_row)} -> 0 | F30: =1*NOT(OR(is_header,is_total,is_empty)) -> 1 | G30: {=1*OR(row_id=expenses_total_row,row_id=savings_total_row,row_id=income_total_row)} -> 0 | H30: =1*OR(row_id="/1", row_id="/2", row_id=-1) -> 0 | I30: {=IFERROR(INDEX('Budget Planning'!$C:$C, header_row_id), "")} -> Savings | J30: {=IFERROR(INDEX('Budget Planning'!$C:$C, row_id), "")} -> Emergency Fund | K30: {=IF(OR(is_header, is_empty), "", IF(is_total, IF(selected_period="Total Year", SUM(Tracking[Amount] * (Tracking[Type]=type) * (YEAR(Tracking[Effective Date])=selected_year)), SUM(Tracking[Amount] * (Tracking[Type]=type) * (YEAR(Tracking[Effective Date])=selected_year) * (MONTH(Tracking[Effective Date])=selected_period))), IF(selected_period="Total Year", SUM(Tracking[Amount] * (Tracking[Type]=type) * (Tracking[Category]=item) * (YEAR(Tracking[Effective Date])=selected_year)), SUM(Tracking[Amount] * (Tracking[Type]=type) * (Tracking[Category]=item) * (YEAR(Tracking[Effective Date])=selected_year) * (MONTH(Tracking[Effective Date])=selected_period))) ) )} -> 5200 | L30: {=IF(OR(is_empty,is_header), "", INDEX('Budget Planning'!$E:$AS, row_id, MATCH(IF(selected_period="Total Year", selected_year, DATE(selected_year, selected_period, 1)),'Budget Planning'!$E$9:$AS$9,0) ))} -> 14400 | M30: {=IF(is_cat, IF(header_row_id=income_header_row, MATCH(income_min_row,$C:$C,0), IF(header_row_id=expenses_header_row, MATCH(expenses_min_row,$C:$C,0), IF(header_row_id=savings_header_row, MATCH(savings_min_row,$C:$C,0), ""))), "")} -> 30 | N30: {=IF(is_cat, IF(header_row_id=income_header_row, MATCH(income_max_row,$C:$C,0), IF(header_row_id=expenses_header_row, MATCH(expenses_max_row,$C:$C,0), IF(header_row_id=savings_header_row, MATCH(savings_max_row,$C:$C,0), ""))), "")} -> 33 | O30: =IF(is_cat, ADDRESS(sort_min_row, COLUMN(tracked)) & ":" & ADDRESS(sort_max_row,COLUMN(tracked)), "") -> $K$30:$K$33 | P30: =IF(is_cat, RANK(tracked, INDIRECT(tracked_range), 0),"") -> 3 | Q30: =IF(is_cat, ADDRESS(sort_min_row, COLUMN(budget)) & ":" & ADDRESS(sort_max_row,COLUMN(budget)), "") -> $L$30:$L$33 | R30: =IF(is_cat, RANK(budget, INDIRECT(budget_range), 0),"") -> 2 | S30: =IF(is_cat, _xlfn.NUMBERVALUE(tracked_rank & budget_rank), "") -> 32 | T30: =IF(is_cat, ADDRESS(sort_min_row, COLUMN(comb_rank)) & ":" & ADDRESS(sort_max_row,COLUMN(comb_rank)), "") -> $S$30:$S$33 | U30: =IF(is_cat, RANK(comb_rank, INDIRECT(comb_rank_range),1), "") -> 3 | V30: =IF(is_cat, ADDRESS(sort_min_row, COLUMN(comb_rank_norm)) & ":" & ADDRESS(ROW(),COLUMN(comb_rank_norm)), "") -> $U$30:$U$30 | W30: =IF(is_cat,comb_rank_norm + COUNTIF(INDIRECT(comb_rank_norm_run_range),comb_rank_norm)-1, "") -> 3 | X30: =IF(is_cat, header_row_id + comb_rank_unique, row_id) -> 35 | Y30: =IF(is_empty, "", INDEX($J:$J,MATCH(row_id, $X:$X, 0))) -> Stock Portfolio | Z30: =IF(is_empty, "", IF(is_header, "Tracked", INDEX($K:$K, MATCH(row_id, $X:$X,0)))) -> 6100 | AA30: =IF(is_empty, "", IF(is_header, "Budget", INDEX($L:$L, MATCH(row_id, $X:$X,0)))) -> 12100 | AB30: =IF(is_empty, "", IF(is_header, "% Compl.", IFERROR(out_tracked / out_budget, "-"))) -> 0.50413223 | AC30: =IF(is_empty, "", IF(is_header, "Remaining", IF(out_budget - out_tracked > 0, out_budget - out_tracked, 0))) -> 6000 | AD30: =IF(is_empty, "", IF(is_header, "Excess", IF(out_budget - out_tracked < 0, out_tracked - out_budget, 0))) -> 0 | AI30: =Calculations!I36 -> Groceries | AJ30: =Calculations!J36 -> 7300 | AP30: =Calculations!M36 -> Retirement Account | AQ30: =Calculations!N36 -> 5849.91
C31: {=IF(C30=-1,-1, IF(C30<income_max_row,C30+1, IF(C30=income_max_row,income_total_row, IF(C30=income_total_row,"/1", IF(C30="/1",expenses_header_row, IF(C30<expenses_max_row,C30+1, IF(C30=expenses_max_row,expenses_total_row, IF(C30=expenses_total_row,"/2", IF(C30="/2",savings_header_row, IF(C30<savings_max_row,C30+1, IF(C30=savings_max_row,savings_total_row,-1)))))))))))} -> 34 | D31: =IF(is_header,row_id, IF(NOT(is_empty),D30,-1)) -> 32 | E31: {=1*OR(row_id=income_header_row,row_id=expenses_header_row,row_id=savings_header_row)} -> 0 | F31: =1*NOT(OR(is_header,is_total,is_empty)) -> 1 | G31: {=1*OR(row_id=expenses_total_row,row_id=savings_total_row,row_id=income_total_row)} -> 0 | H31: =1*OR(row_id="/1", row_id="/2", row_id=-1) -> 0 | I31: {=IFERROR(INDEX('Budget Planning'!$C:$C, header_row_id), "")} -> Savings | J31: {=IFERROR(INDEX('Budget Planning'!$C:$C, row_id), "")} -> Retirement Account | K31: {=IF(OR(is_header, is_empty), "", IF(is_total, IF(selected_period="Total Year", SUM(Tracking[Amount] * (Tracking[Type]=type) * (YEAR(Tracking[Effective Date])=selected_year)), SUM(Tracking[Amount] * (Tracking[Type]=type) * (YEAR(Tracking[Effective Date])=selected_year) * (MONTH(Tracking[Effective Date])=selected_period))), IF(selected_period="Total Year", SUM(Tracking[Amount] * (Tracking[Type]=type) * (Tracking[Category]=item) * (YEAR(Tracking[Effective Date])=selected_year)), SUM(Tracking[Amount] * (Tracking[Type]=type) * (Tracking[Category]=item) * (YEAR(Tracking[Effective Date])=selected_year) * (MONTH(Tracking[Effective Date])=selected_period))) ) )} -> 5849.91 | L31: {=IF(OR(is_empty,is_header), "", INDEX('Budget Planning'!$E:$AS, row_id, MATCH(IF(selected_period="Total Year", selected_year, DATE(selected_year, selected_period, 1)),'Budget Planning'!$E$9:$AS$9,0) ))} -> 16800 | M31: {=IF(is_cat, IF(header_row_id=income_header_row, MATCH(income_min_row,$C:$C,0), IF(header_row_id=expenses_header_row, MATCH(expenses_min_row,$C:$C,0), IF(header_row_id=savings_header_row, MATCH(savings_min_row,$C:$C,0), ""))), "")} -> 30 | N31: {=IF(is_cat, IF(header_row_id=income_header_row, MATCH(income_max_row,$C:$C,0), IF(header_row_id=expenses_header_row, MATCH(expenses_max_row,$C:$C,0), IF(header_row_id=savings_header_row, MATCH(savings_max_row,$C:$C,0), ""))), "")} -> 33 | O31: =IF(is_cat, ADDRESS(sort_min_row, COLUMN(tracked)) & ":" & ADDRESS(sort_max_row,COLUMN(tracked)), "") -> $K$30:$K$33 | P31: =IF(is_cat, RANK(tracked, INDIRECT(tracked_range), 0),"") -> 2 | Q31: =IF(is_cat, ADDRESS(sort_min_row, COLUMN(budget)) & ":" & ADDRESS(sort_max_row,COLUMN(budget)), "") -> $L$30:$L$33 | R31: =IF(is_cat, RANK(budget, INDIRECT(budget_range), 0),"") -> 1 | S31: =IF(is_cat, _xlfn.NUMBERVALUE(tracked_rank & budget_rank), "") -> 21 | T31: =IF(is_cat, ADDRESS(sort_min_row, COLUMN(comb_rank)) & ":" & ADDRESS(sort_max_row,COLUMN(comb_rank)), "") -> $S$30:$S$33 | U31: =IF(is_cat, RANK(comb_rank, INDIRECT(comb_rank_range),1), "") -> 2 | V31: =IF(is_cat, ADDRESS(sort_min_row, COLUMN(comb_rank_norm)) & ":" & ADDRESS(ROW(),COLUMN(comb_rank_norm)), "") -> $U$30:$U$31 | W31: =IF(is_cat,comb_rank_norm + COUNTIF(INDIRECT(comb_rank_norm_run_range),comb_rank_norm)-1, "") -> 2 | X31: =IF(is_cat, header_row_id + comb_rank_unique, row_id) -> 34 | Y31: =IF(is_empty, "", INDEX($J:$J,MATCH(row_id, $X:$X, 0))) -> Retirement Account | Z31: =IF(is_empty, "", IF(is_header, "Tracked", INDEX($K:$K, MATCH(row_id, $X:$X,0)))) -> 5849.91 | AA31: =IF(is_empty, "", IF(is_header, "Budget", INDEX($L:$L, MATCH(row_id, $X:$X,0)))) -> 16800 | AB31: =IF(is_empty, "", IF(is_header, "% Compl.", IFERROR(out_tracked / out_budget, "-"))) -> 0.34820893 | AC31: =IF(is_empty, "", IF(is_header, "Remaining", IF(out_budget - out_tracked > 0, out_budget - out_tracked, 0))) -> 10950.09 | AD31: =IF(is_empty, "", IF(is_header, "Excess", IF(out_budget - out_tracked < 0, out_tracked - out_budget, 0))) -> 0 | AI31: =Calculations!I37 -> Technologies | AJ31: =Calculations!J37 -> 2800 | AP31: =Calculations!M37 -> Emergency Fund | AQ31: =Calculations!N37 -> 5200
C32: {=IF(C31=-1,-1, IF(C31<income_max_row,C31+1, IF(C31=income_max_row,income_total_row, IF(C31=income_total_row,"/1", IF(C31="/1",expenses_header_row, IF(C31<expenses_max_row,C31+1, IF(C31=expenses_max_row,expenses_total_row, IF(C31=expenses_total_row,"/2", IF(C31="/2",savings_header_row, IF(C31<savings_max_row,C31+1, IF(C31=savings_max_row,savings_total_row,-1)))))))))))} -> 35 | D32: =IF(is_header,row_id, IF(NOT(is_empty),D31,-1)) -> 32 | E32: {=1*OR(row_id=income_header_row,row_id=expenses_header_row,row_id=savings_header_row)} -> 0 | F32: =1*NOT(OR(is_header,is_total,is_empty)) -> 1 | G32: {=1*OR(row_id=expenses_total_row,row_id=savings_total_row,row_id=income_total_row)} -> 0 | H32: =1*OR(row_id="/1", row_id="/2", row_id=-1) -> 0 | I32: {=IFERROR(INDEX('Budget Planning'!$C:$C, header_row_id), "")} -> Savings | J32: {=IFERROR(INDEX('Budget Planning'!$C:$C, row_id), "")} -> Stock Portfolio | K32: {=IF(OR(is_header, is_empty), "", IF(is_total, IF(selected_period="Total Year", SUM(Tracking[Amount] * (Tracking[Type]=type) * (YEAR(Tracking[Effective Date])=selected_year)), SUM(Tracking[Amount] * (Tracking[Type]=type) * (YEAR(Tracking[Effective Date])=selected_year) * (MONTH(Tracking[Effective Date])=selected_period))), IF(selected_period="Total Year", SUM(Tracking[Amount] * (Tracking[Type]=type) * (Tracking[Category]=item) * (YEAR(Tracking[Effective Date])=selected_year)), SUM(Tracking[Amount] * (Tracking[Type]=type) * (Tracking[Category]=item) * (YEAR(Tracking[Effective Date])=selected_year) * (MONTH(Tracking[Effective Date])=selected_period))) ) )} -> 6100 | L32: {=IF(OR(is_empty,is_header), "", INDEX('Budget Planning'!$E:$AS, row_id, MATCH(IF(selected_period="Total Year", selected_year, DATE(selected_year, selected_period, 1)),'Budget Planning'!$E$9:$AS$9,0) ))} -> 12100 | M32: {=IF(is_cat, IF(header_row_id=income_header_row, MATCH(income_min_row,$C:$C,0), IF(header_row_id=expenses_header_row, MATCH(expenses_min_row,$C:$C,0), IF(header_row_id=savings_header_row, MATCH(savings_min_row,$C:$C,0), ""))), "")} -> 30 | N32: {=IF(is_cat, IF(header_row_id=income_header_row, MATCH(income_max_row,$C:$C,0), IF(header_row_id=expenses_header_row, MATCH(expenses_max_row,$C:$C,0), IF(header_row_id=savings_header_row, MATCH(savings_max_row,$C:$C,0), ""))), "")} -> 33 | O32: =IF(is_cat, ADDRESS(sort_min_row, COLUMN(tracked)) & ":" & ADDRESS(sort_max_row,COLUMN(tracked)), "") -> $K$30:$K$33 | P32: =IF(is_cat, RANK(tracked, INDIRECT(tracked_range), 0),"") -> 1 | Q32: =IF(is_cat, ADDRESS(sort_min_row, COLUMN(budget)) & ":" & ADDRESS(sort_max_row,COLUMN(budget)), "") -> $L$30:$L$33 | R32: =IF(is_cat, RANK(budget, INDIRECT(budget_range), 0),"") -> 3 | S32: =IF(is_cat, _xlfn.NUMBERVALUE(tracked_rank & budget_rank), "") -> 13 | T32: =IF(is_cat, ADDRESS(sort_min_row, COLUMN(comb_rank)) & ":" & ADDRESS(sort_max_row,COLUMN(comb_rank)), "") -> $S$30:$S$33 | U32: =IF(is_cat, RANK(comb_rank, INDIRECT(comb_rank_range),1), "") -> 1 | V32: =IF(is_cat, ADDRESS(sort_min_row, COLUMN(comb_rank_norm)) & ":" & ADDRESS(ROW(),COLUMN(comb_rank_norm)), "") -> $U$30:$U$32 | W32: =IF(is_cat,comb_rank_norm + COUNTIF(INDIRECT(comb_rank_norm_run_range),comb_rank_norm)-1, "") -> 1 | X32: =IF(is_cat, header_row_id + comb_rank_unique, row_id) -> 33 | Y32: =IF(is_empty, "", INDEX($J:$J,MATCH(row_id, $X:$X, 0))) -> Emergency Fund | Z32: =IF(is_empty, "", IF(is_header, "Tracked", INDEX($K:$K, MATCH(row_id, $X:$X,0)))) -> 5200 | AA32: =IF(is_empty, "", IF(is_header, "Budget", INDEX($L:$L, MATCH(row_id, $X:$X,0)))) -> 14400 | AB32: =IF(is_empty, "", IF(is_header, "% Compl.", IFERROR(out_tracked / out_budget, "-"))) -> 0.36111111 | AC32: =IF(is_empty, "", IF(is_header, "Remaining", IF(out_budget - out_tracked > 0, out_budget - out_tracked, 0))) -> 9200 | AD32: =IF(is_empty, "", IF(is_header, "Excess", IF(out_budget - out_tracked < 0, out_tracked - out_budget, 0))) -> 0 | AI32: =Calculations!I38 -> Transport | AJ32: =Calculations!J38 -> 2800 | AP32: =Calculations!M38 -> Other | AQ32: =Calculations!N38 -> 850
C33: {=IF(C32=-1,-1, IF(C32<income_max_row,C32+1, IF(C32=income_max_row,income_total_row, IF(C32=income_total_row,"/1", IF(C32="/1",expenses_header_row, IF(C32<expenses_max_row,C32+1, IF(C32=expenses_max_row,expenses_total_row, IF(C32=expenses_total_row,"/2", IF(C32="/2",savings_header_row, IF(C32<savings_max_row,C32+1, IF(C32=savings_max_row,savings_total_row,-1)))))))))))} -> 36 | D33: =IF(is_header,row_id, IF(NOT(is_empty),D32,-1)) -> 32 | E33: {=1*OR(row_id=income_header_row,row_id=expenses_header_row,row_id=savings_header_row)} -> 0 | F33: =1*NOT(OR(is_header,is_total,is_empty)) -> 1 | G33: {=1*OR(row_id=expenses_total_row,row_id=savings_total_row,row_id=income_total_row)} -> 0 | H33: =1*OR(row_id="/1", row_id="/2", row_id=-1) -> 0 | I33: {=IFERROR(INDEX('Budget Planning'!$C:$C, header_row_id), "")} -> Savings | J33: {=IFERROR(INDEX('Budget Planning'!$C:$C, row_id), "")} -> Other | K33: {=IF(OR(is_header, is_empty), "", IF(is_total, IF(selected_period="Total Year", SUM(Tracking[Amount] * (Tracking[Type]=type) * (YEAR(Tracking[Effective Date])=selected_year)), SUM(Tracking[Amount] * (Tracking[Type]=type) * (YEAR(Tracking[Effective Date])=selected_year) * (MONTH(Tracking[Effective Date])=selected_period))), IF(selected_period="Total Year", SUM(Tracking[Amount] * (Tracking[Type]=type) * (Tracking[Category]=item) * (YEAR(Tracking[Effective Date])=selected_year)), SUM(Tracking[Amount] * (Tracking[Type]=type) * (Tracking[Category]=item) * (YEAR(Tracking[Effective Date])=selected_year) * (MONTH(Tracking[Effective Date])=selected_period))) ) )} -> 850 | L33: {=IF(OR(is_empty,is_header), "", INDEX('Budget Planning'!$E:$AS, row_id, MATCH(IF(selected_period="Total Year", selected_year, DATE(selected_year, selected_period, 1)),'Budget Planning'!$E$9:$AS$9,0) ))} -> 2300 | M33: {=IF(is_cat, IF(header_row_id=income_header_row, MATCH(income_min_row,$C:$C,0), IF(header_row_id=expenses_header_row, MATCH(expenses_min_row,$C:$C,0), IF(header_row_id=savings_header_row, MATCH(savings_min_row,$C:$C,0), ""))), "")} -> 30 | N33: {=IF(is_cat, IF(header_row_id=income_header_row, MATCH(income_max_row,$C:$C,0), IF(header_row_id=expenses_header_row, MATCH(expenses_max_row,$C:$C,0), IF(header_row_id=savings_header_row, MATCH(savings_max_row,$C:$C,0), ""))), "")} -> 33 | O33: =IF(is_cat, ADDRESS(sort_min_row, COLUMN(tracked)) & ":" & ADDRESS(sort_max_row,COLUMN(tracked)), "") -> $K$30:$K$33 | P33: =IF(is_cat, RANK(tracked, INDIRECT(tracked_range), 0),"") -> 4 | Q33: =IF(is_cat, ADDRESS(sort_min_row, COLUMN(budget)) & ":" & ADDRESS(sort_max_row,COLUMN(budget)), "") -> $L$30:$L$33 | R33: =IF(is_cat, RANK(budget, INDIRECT(budget_range), 0),"") -> 4 | S33: =IF(is_cat, _xlfn.NUMBERVALUE(tracked_rank & budget_rank), "") -> 44 | T33: =IF(is_cat, ADDRESS(sort_min_row, COLUMN(comb_rank)) & ":" & ADDRESS(sort_max_row,COLUMN(comb_rank)), "") -> $S$30:$S$33 | U33: =IF(is_cat, RANK(comb_rank, INDIRECT(comb_rank_range),1), "") -> 4 | V33: =IF(is_cat, ADDRESS(sort_min_row, COLUMN(comb_rank_norm)) & ":" & ADDRESS(ROW(),COLUMN(comb_rank_norm)), "") -> $U$30:$U$33 | W33: =IF(is_cat,comb_rank_norm + COUNTIF(INDIRECT(comb_rank_norm_run_range),comb_rank_norm)-1, "") -> 4 | X33: =IF(is_cat, header_row_id + comb_rank_unique, row_id) -> 36 | Y33: =IF(is_empty, "", INDEX($J:$J,MATCH(row_id, $X:$X, 0))) -> Other | Z33: =IF(is_empty, "", IF(is_header, "Tracked", INDEX($K:$K, MATCH(row_id, $X:$X,0)))) -> 850 | AA33: =IF(is_empty, "", IF(is_header, "Budget", INDEX($L:$L, MATCH(row_id, $X:$X,0)))) -> 2300 | AB33: =IF(is_empty, "", IF(is_header, "% Compl.", IFERROR(out_tracked / out_budget, "-"))) -> 0.36956522 | AC33: =IF(is_empty, "", IF(is_header, "Remaining", IF(out_budget - out_tracked > 0, out_budget - out_tracked, 0))) -> 1450 | AD33: =IF(is_empty, "", IF(is_header, "Excess", IF(out_budget - out_tracked < 0, out_tracked - out_budget, 0))) -> 0 | AI33: =Calculations!I39 -> Other | AJ33: =Calculations!J39 -> 1100 | AP33: =Calculations!M39 | AQ33: =Calculations!N39
C34: {=IF(C33=-1,-1, IF(C33<income_max_row,C33+1, IF(C33=income_max_row,income_total_row, IF(C33=income_total_row,"/1", IF(C33="/1",expenses_header_row, IF(C33<expenses_max_row,C33+1, IF(C33=expenses_max_row,expenses_total_row, IF(C33=expenses_total_row,"/2", IF(C33="/2",savings_header_row, IF(C33<savings_max_row,C33+1, IF(C33=savings_max_row,savings_total_row,-1)))))))))))} -> 43 | D34: =IF(is_header,row_id, IF(NOT(is_empty),D33,-1)) -> 32 | E34: {=1*OR(row_id=income_header_row,row_id=expenses_header_row,row_id=savings_header_row)} -> 0 | F34: =1*NOT(OR(is_header,is_total,is_empty)) -> 0 | G34: {=1*OR(row_id=expenses_total_row,row_id=savings_total_row,row_id=income_total_row)} -> 1 | H34: =1*OR(row_id="/1", row_id="/2", row_id=-1) -> 0 | I34: {=IFERROR(INDEX('Budget Planning'!$C:$C, header_row_id), "")} -> Savings | J34: {=IFERROR(INDEX('Budget Planning'!$C:$C, row_id), "")} -> Total | K34: {=IF(OR(is_header, is_empty), "", IF(is_total, IF(selected_period="Total Year", SUM(Tracking[Amount] * (Tracking[Type]=type) * (YEAR(Tracking[Effective Date])=selected_year)), SUM(Tracking[Amount] * (Tracking[Type]=type) * (YEAR(Tracking[Effective Date])=selected_year) * (MONTH(Tracking[Effective Date])=selected_period))), IF(selected_period="Total Year", SUM(Tracking[Amount] * (Tracking[Type]=type) * (Tracking[Category]=item) * (YEAR(Tracking[Effective Date])=selected_year)), SUM(Tracking[Amount] * (Tracking[Type]=type) * (Tracking[Category]=item) * (YEAR(Tracking[Effective Date])=selected_year) * (MONTH(Tracking[Effective Date])=selected_period))) ) )} -> 17999.91 | L34: {=IF(OR(is_empty,is_header), "", INDEX('Budget Planning'!$E:$AS, row_id, MATCH(IF(selected_period="Total Year", selected_year, DATE(selected_year, selected_period, 1)),'Budget Planning'!$E$9:$AS$9,0) ))} -> 45600 | M34: {=IF(is_cat, IF(header_row_id=income_header_row, MATCH(income_min_row,$C:$C,0), IF(header_row_id=expenses_header_row, MATCH(expenses_min_row,$C:$C,0), IF(header_row_id=savings_header_row, MATCH(savings_min_row,$C:$C,0), ""))), "")} | N34: {=IF(is_cat, IF(header_row_id=income_header_row, MATCH(income_max_row,$C:$C,0), IF(header_row_id=expenses_header_row, MATCH(expenses_max_row,$C:$C,0), IF(header_row_id=savings_header_row, MATCH(savings_max_row,$C:$C,0), ""))), "")} | O34: =IF(is_cat, ADDRESS(sort_min_row, COLUMN(tracked)) & ":" & ADDRESS(sort_max_row,COLUMN(tracked)), "") | P34: =IF(is_cat, RANK(tracked, INDIRECT(tracked_range), 0),"") | Q34: =IF(is_cat, ADDRESS(sort_min_row, COLUMN(budget)) & ":" & ADDRESS(sort_max_row,COLUMN(budget)), "") | R34: =IF(is_cat, RANK(budget, INDIRECT(budget_range), 0),"") | S34: =IF(is_cat, _xlfn.NUMBERVALUE(tracked_rank & budget_rank), "") | T34: =IF(is_cat, ADDRESS(sort_min_row, COLUMN(comb_rank)) & ":" & ADDRESS(sort_max_row,COLUMN(comb_rank)), "") | U34: =IF(is_cat, RANK(comb_rank, INDIRECT(comb_rank_range),1), "") | V34: =IF(is_cat, ADDRESS(sort_min_row, COLUMN(comb_rank_norm)) & ":" & ADDRESS(ROW(),COLUMN(comb_rank_norm)), "") | W34: =IF(is_cat,comb_rank_norm + COUNTIF(INDIRECT(comb_rank_norm_run_range),comb_rank_norm)-1, "") | X34: =IF(is_cat, header_row_id + comb_rank_unique, row_id) -> 43 | Y34: =IF(is_empty, "", INDEX($J:$J,MATCH(row_id, $X:$X, 0))) -> Total | Z34: =IF(is_empty, "", IF(is_header, "Tracked", INDEX($K:$K, MATCH(row_id, $X:$X,0)))) -> 17999.91 | AA34: =IF(is_empty, "", IF(is_header, "Budget", INDEX($L:$L, MATCH(row_id, $X:$X,0)))) -> 45600 | AB34: =IF(is_empty, "", IF(is_header, "% Compl.", IFERROR(out_tracked / out_budget, "-"))) -> 0.39473487 | AC34: =IF(is_empty, "", IF(is_header, "Remaining", IF(out_budget - out_tracked > 0, out_budget - out_tracked, 0))) -> 27600.09 | AD34: =IF(is_empty, "", IF(is_header, "Excess", IF(out_budget - out_tracked < 0, out_tracked - out_budget, 0))) -> 0 | AI34: =Calculations!I40 -> Other | AJ34: =Calculations!J40 -> 950 | AP34: =Calculations!M40 | AQ34: =Calculations!N40
C35: {=IF(C34=-1,-1, IF(C34<income_max_row,C34+1, IF(C34=income_max_row,income_total_row, IF(C34=income_total_row,"/1", IF(C34="/1",expenses_header_row, IF(C34<expenses_max_row,C34+1, IF(C34=expenses_max_row,expenses_total_row, IF(C34=expenses_total_row,"/2", IF(C34="/2",savings_header_row, IF(C34<savings_max_row,C34+1, IF(C34=savings_max_row,savings_total_row,-1)))))))))))} -> -1 | D35: =IF(is_header,row_id, IF(NOT(is_empty),D34,-1)) -> -1 | E35: {=1*OR(row_id=income_header_row,row_id=expenses_header_row,row_id=savings_header_row)} -> 0 | F35: =1*NOT(OR(is_header,is_total,is_empty)) -> 0 | G35: {=1*OR(row_id=expenses_total_row,row_id=savings_total_row,row_id=income_total_row)} -> 0 | H35: =1*OR(row_id="/1", row_id="/2", row_id=-1) -> 1 | I35: {=IFERROR(INDEX('Budget Planning'!$C:$C, header_row_id), "")} | J35: {=IFERROR(INDEX('Budget Planning'!$C:$C, row_id), "")} | K35: {=IF(OR(is_header, is_empty), "", IF(is_total, IF(selected_period="Total Year", SUM(Tracking[Amount] * (Tracking[Type]=type) * (YEAR(Tracking[Effective Date])=selected_year)), SUM(Tracking[Amount] * (Tracking[Type]=type) * (YEAR(Tracking[Effective Date])=selected_year) * (MONTH(Tracking[Effective Date])=selected_period))), IF(selected_period="Total Year", SUM(Tracking[Amount] * (Tracking[Type]=type) * (Tracking[Category]=item) * (YEAR(Tracking[Effective Date])=selected_year)), SUM(Tracking[Amount] * (Tracking[Type]=type) * (Tracking[Category]=item) * (YEAR(Tracking[Effective Date])=selected_year) * (MONTH(Tracking[Effective Date])=selected_period))) ) )} | L35: {=IF(OR(is_empty,is_header), "", INDEX('Budget Planning'!$E:$AS, row_id, MATCH(IF(selected_period="Total Year", selected_year, DATE(selected_year, selected_period, 1)),'Budget Planning'!$E$9:$AS$9,0) ))} | M35: {=IF(is_cat, IF(header_row_id=income_header_row, MATCH(income_min_row,$C:$C,0), IF(header_row_id=expenses_header_row, MATCH(expenses_min_row,$C:$C,0), IF(header_row_id=savings_header_row, MATCH(savings_min_row,$C:$C,0), ""))), "")} | N35: {=IF(is_cat, IF(header_row_id=income_header_row, MATCH(income_max_row,$C:$C,0), IF(header_row_id=expenses_header_row, MATCH(expenses_max_row,$C:$C,0), IF(header_row_id=savings_header_row, MATCH(savings_max_row,$C:$C,0), ""))), "")} | O35: =IF(is_cat, ADDRESS(sort_min_row, COLUMN(tracked)) & ":" & ADDRESS(sort_max_row,COLUMN(tracked)), "") | P35: =IF(is_cat, RANK(tracked, INDIRECT(tracked_range), 0),"") | Q35: =IF(is_cat, ADDRESS(sort_min_row, COLUMN(budget)) & ":" & ADDRESS(sort_max_row,COLUMN(budget)), "") | R35: =IF(is_cat, RANK(budget, INDIRECT(budget_range), 0),"") | S35: =IF(is_cat, _xlfn.NUMBERVALUE(tracked_rank & budget_rank), "") | T35: =IF(is_cat, ADDRESS(sort_min_row, COLUMN(comb_rank)) & ":" & ADDRESS(sort_max_row,COLUMN(comb_rank)), "") | U35: =IF(is_cat, RANK(comb_rank, INDIRECT(comb_rank_range),1), "") | V35: =IF(is_cat, ADDRESS(sort_min_row, COLUMN(comb_rank_norm)) & ":" & ADDRESS(ROW(),COLUMN(comb_rank_norm)), "") | W35: =IF(is_cat,comb_rank_norm + COUNTIF(INDIRECT(comb_rank_norm_run_range),comb_rank_norm)-1, "") | X35: =IF(is_cat, header_row_id + comb_rank_unique, row_id) -> -1 | Y35: =IF(is_empty, "", INDEX($J:$J,MATCH(row_id, $X:$X, 0))) | Z35: =IF(is_empty, "", IF(is_header, "Tracked", INDEX($K:$K, MATCH(row_id, $X:$X,0)))) | AA35: =IF(is_empty, "", IF(is_header, "Budget", INDEX($L:$L, MATCH(row_id, $X:$X,0)))) | AB35: =IF(is_empty, "", IF(is_header, "% Compl.", IFERROR(out_tracked / out_budget, "-"))) | AC35: =IF(is_empty, "", IF(is_header, "Remaining", IF(out_budget - out_tracked > 0, out_budget - out_tracked, 0))) | AD35: =IF(is_empty, "", IF(is_header, "Savings", IF(out_budget - out_tracked < 0, out_tracked - out_budget, 0))) | AI35: =Calculations!I41 -> Total | AJ35: =Calculations!J41 -> 32350 | AP35: =Calculations!M41 -> Total | AQ35: =Calculations!N41 -> 17999.91
C36: {=IF(C35=-1,-1, IF(C35<income_max_row,C35+1, IF(C35=income_max_row,income_total_row, IF(C35=income_total_row,"/1", IF(C35="/1",expenses_header_row, IF(C35<expenses_max_row,C35+1, IF(C35=expenses_max_row,expenses_total_row, IF(C35=expenses_total_row,"/2", IF(C35="/2",savings_header_row, IF(C35<savings_max_row,C35+1, IF(C35=savings_max_row,savings_total_row,-1)))))))))))} -> -1 | D36: =IF(is_header,row_id, IF(NOT(is_empty),D35,-1)) -> -1 | E36: {=1*OR(row_id=income_header_row,row_id=expenses_header_row,row_id=savings_header_row)} -> 0 | F36: =1*NOT(OR(is_header,is_total,is_empty)) -> 0 | G36: {=1*OR(row_id=expenses_total_row,row_id=savings_total_row,row_id=income_total_row)} -> 0 | H36: =1*OR(row_id="/1", row_id="/2", row_id=-1) -> 1 | I36: {=IFERROR(INDEX('Budget Planning'!$C:$C, header_row_id), "")} | J36: {=IFERROR(INDEX('Budget Planning'!$C:$C, row_id), "")} | K36: {=IF(OR(is_header, is_empty), "", IF(is_total, IF(selected_period="Total Year", SUM(Tracking[Amount] * (Tracking[Type]=type) * (YEAR(Tracking[Effective Date])=selected_year)), SUM(Tracking[Amount] * (Tracking[Type]=type) * (YEAR(Tracking[Effective Date])=selected_year) * (MONTH(Tracking[Effective Date])=selected_period))), IF(selected_period="Total Year", SUM(Tracking[Amount] * (Tracking[Type]=type) * (Tracking[Category]=item) * (YEAR(Tracking[Effective Date])=selected_year)), SUM(Tracking[Amount] * (Tracking[Type]=type) * (Tracking[Category]=item) * (YEAR(Tracking[Effective Date])=selected_year) * (MONTH(Tracking[Effective Date])=selected_period))) ) )} | L36: {=IF(OR(is_empty,is_header), "", INDEX('Budget Planning'!$E:$AS, row_id, MATCH(IF(selected_period="Total Year", selected_year, DATE(selected_year, selected_period, 1)),'Budget Planning'!$E$9:$AS$9,0) ))} | M36: {=IF(is_cat, IF(header_row_id=income_header_row, MATCH(income_min_row,$C:$C,0), IF(header_row_id=expenses_header_row, MATCH(expenses_min_row,$C:$C,0), IF(header_row_id=savings_header_row, MATCH(savings_min_row,$C:$C,0), ""))), "")} | N36: {=IF(is_cat, IF(header_row_id=income_header_row, MATCH(income_max_row,$C:$C,0), IF(header_row_id=expenses_header_row, MATCH(expenses_max_row,$C:$C,0), IF(header_row_id=savings_header_row, MATCH(savings_max_row,$C:$C,0), ""))), "")} | O36: =IF(is_cat, ADDRESS(sort_min_row, COLUMN(tracked)) & ":" & ADDRESS(sort_max_row,COLUMN(tracked)), "") | P36: =IF(is_cat, RANK(tracked, INDIRECT(tracked_range), 0),"") | Q36: =IF(is_cat, ADDRESS(sort_min_row, COLUMN(budget)) & ":" & ADDRESS(sort_max_row,COLUMN(budget)), "") | R36: =IF(is_cat, RANK(budget, INDIRECT(budget_range), 0),"") | S36: =IF(is_cat, _xlfn.NUMBERVALUE(tracked_rank & budget_rank), "") | T36: =IF(is_cat, ADDRESS(sort_min_row, COLUMN(comb_rank)) & ":" & ADDRESS(sort_max_row,COLUMN(comb_rank)), "") | U36: =IF(is_cat, RANK(comb_rank, INDIRECT(comb_rank_range),1), "") | V36: =IF(is_cat, ADDRESS(sort_min_row, COLUMN(comb_rank_norm)) & ":" & ADDRESS(ROW(),COLUMN(comb_rank_norm)), "") | W36: =IF(is_cat,comb_rank_norm + COUNTIF(INDIRECT(comb_rank_norm_run_range),comb_rank_norm)-1, "") | X36: =IF(is_cat, header_row_id + comb_rank_unique, row_id) -> -1 | Y36: =IF(is_empty, "", INDEX($J:$J,MATCH(row_id, $X:$X, 0))) | Z36: =IF(is_empty, "", IF(is_header, "Tracked", INDEX($K:$K, MATCH(row_id, $X:$X,0)))) | AA36: =IF(is_empty, "", IF(is_header, "Budget", INDEX($L:$L, MATCH(row_id, $X:$X,0)))) | AB36: =IF(is_empty, "", IF(is_header, "% Compl.", IFERROR(out_tracked / out_budget, "-"))) | AC36: =IF(is_empty, "", IF(is_header, "Remaining", IF(out_budget - out_tracked > 0, out_budget - out_tracked, 0))) | AD36: =IF(is_empty, "", IF(is_header, "Savings", IF(out_budget - out_tracked < 0, out_tracked - out_budget, 0)))
C37: {=IF(C36=-1,-1, IF(C36<income_max_row,C36+1, IF(C36=income_max_row,income_total_row, IF(C36=income_total_row,"/1", IF(C36="/1",expenses_header_row, IF(C36<expenses_max_row,C36+1, IF(C36=expenses_max_row,expenses_total_row, IF(C36=expenses_total_row,"/2", IF(C36="/2",savings_header_row, IF(C36<savings_max_row,C36+1, IF(C36=savings_max_row,savings_total_row,-1)))))))))))} -> -1 | D37: =IF(is_header,row_id, IF(NOT(is_empty),D36,-1)) -> -1 | E37: {=1*OR(row_id=income_header_row,row_id=expenses_header_row,row_id=savings_header_row)} -> 0 | F37: =1*NOT(OR(is_header,is_total,is_empty)) -> 0 | G37: {=1*OR(row_id=expenses_total_row,row_id=savings_total_row,row_id=income_total_row)} -> 0 | H37: =1*OR(row_id="/1", row_id="/2", row_id=-1) -> 1 | I37: {=IFERROR(INDEX('Budget Planning'!$C:$C, header_row_id), "")} | J37: {=IFERROR(INDEX('Budget Planning'!$C:$C, row_id), "")} | K37: {=IF(OR(is_header, is_empty), "", IF(is_total, IF(selected_period="Total Year", SUM(Tracking[Amount] * (Tracking[Type]=type) * (YEAR(Tracking[Effective Date])=selected_year)), SUM(Tracking[Amount] * (Tracking[Type]=type) * (YEAR(Tracking[Effective Date])=selected_year) * (MONTH(Tracking[Effective Date])=selected_period))), IF(selected_period="Total Year", SUM(Tracking[Amount] * (Tracking[Type]=type) * (Tracking[Category]=item) * (YEAR(Tracking[Effective Date])=selected_year)), SUM(Tracking[Amount] * (Tracking[Type]=type) * (Tracking[Category]=item) * (YEAR(Tracking[Effective Date])=selected_year) * (MONTH(Tracking[Effective Date])=selected_period))) ) )} | L37: {=IF(OR(is_empty,is_header), "", INDEX('Budget Planning'!$E:$AS, row_id, MATCH(IF(selected_period="Total Year", selected_year, DATE(selected_year, selected_period, 1)),'Budget Planning'!$E$9:$AS$9,0) ))} | M37: {=IF(is_cat, IF(header_row_id=income_header_row, MATCH(income_min_row,$C:$C,0), IF(header_row_id=expenses_header_row, MATCH(expenses_min_row,$C:$C,0), IF(header_row_id=savings_header_row, MATCH(savings_min_row,$C:$C,0), ""))), "")} | N37: {=IF(is_cat, IF(header_row_id=income_header_row, MATCH(income_max_row,$C:$C,0), IF(header_row_id=expenses_header_row, MATCH(expenses_max_row,$C:$C,0), IF(header_row_id=savings_header_row, MATCH(savings_max_row,$C:$C,0), ""))), "")} | O37: =IF(is_cat, ADDRESS(sort_min_row, COLUMN(tracked)) & ":" & ADDRESS(sort_max_row,COLUMN(tracked)), "") | P37: =IF(is_cat, RANK(tracked, INDIRECT(tracked_range), 0),"") | Q37: =IF(is_cat, ADDRESS(sort_min_row, COLUMN(budget)) & ":" & ADDRESS(sort_max_row,COLUMN(budget)), "") | R37: =IF(is_cat, RANK(budget, INDIRECT(budget_range), 0),"") | S37: =IF(is_cat, _xlfn.NUMBERVALUE(tracked_rank & budget_rank), "") | T37: =IF(is_cat, ADDRESS(sort_min_row, COLUMN(comb_rank)) & ":" & ADDRESS(sort_max_row,COLUMN(comb_rank)), "") | U37: =IF(is_cat, RANK(comb_rank, INDIRECT(comb_rank_range),1), "") | V37: =IF(is_cat, ADDRESS(sort_min_row, COLUMN(comb_rank_norm)) & ":" & ADDRESS(ROW(),COLUMN(comb_rank_norm)), "") | W37: =IF(is_cat,comb_rank_norm + COUNTIF(INDIRECT(comb_rank_norm_run_range),comb_rank_norm)-1, "") | X37: =IF(is_cat, header_row_id + comb_rank_unique, row_id) -> -1 | Y37: =IF(is_empty, "", INDEX($J:$J,MATCH(row_id, $X:$X, 0))) | Z37: =IF(is_empty, "", IF(is_header, "Tracked", INDEX($K:$K, MATCH(row_id, $X:$X,0)))) | AA37: =IF(is_empty, "", IF(is_header, "Budget", INDEX($L:$L, MATCH(row_id, $X:$X,0)))) | AB37: =IF(is_empty, "", IF(is_header, "% Compl.", IFERROR(out_tracked / out_budget, "-"))) | AC37: =IF(is_empty, "", IF(is_header, "Remaining", IF(out_budget - out_tracked > 0, out_budget - out_tracked, 0))) | AD37: =IF(is_empty, "", INDEX($J:$J,MATCH(row_id, $X:$X, 0)))
C38: {=IF(C37=-1,-1, IF(C37<income_max_row,C37+1, IF(C37=income_max_row,income_total_row, IF(C37=income_total_row,"/1", IF(C37="/1",expenses_header_row, IF(C37<expenses_max_row,C37+1, IF(C37=expenses_max_row,expenses_total_row, IF(C37=expenses_total_row,"/2", IF(C37="/2",savings_header_row, IF(C37<savings_max_row,C37+1, IF(C37=savings_max_row,savings_total_row,-1)))))))))))} -> -1 | D38: =IF(is_header,row_id, IF(NOT(is_empty),D37,-1)) -> -1 | E38: {=1*OR(row_id=income_header_row,row_id=expenses_header_row,row_id=savings_header_row)} -> 0 | F38: =1*NOT(OR(is_header,is_total,is_empty)) -> 0 | G38: {=1*OR(row_id=expenses_total_row,row_id=savings_total_row,row_id=income_total_row)} -> 0 | H38: =1*OR(row_id="/1", row_id="/2", row_id=-1) -> 1 | I38: {=IFERROR(INDEX('Budget Planning'!$C:$C, header_row_id), "")} | J38: {=IFERROR(INDEX('Budget Planning'!$C:$C, row_id), "")} | K38: {=IF(OR(is_header, is_empty), "", IF(is_total, IF(selected_period="Total Year", SUM(Tracking[Amount] * (Tracking[Type]=type) * (YEAR(Tracking[Effective Date])=selected_year)), SUM(Tracking[Amount] * (Tracking[Type]=type) * (YEAR(Tracking[Effective Date])=selected_year) * (MONTH(Tracking[Effective Date])=selected_period))), IF(selected_period="Total Year", SUM(Tracking[Amount] * (Tracking[Type]=type) * (Tracking[Category]=item) * (YEAR(Tracking[Effective Date])=selected_year)), SUM(Tracking[Amount] * (Tracking[Type]=type) * (Tracking[Category]=item) * (YEAR(Tracking[Effective Date])=selected_year) * (MONTH(Tracking[Effective Date])=selected_period))) ) )} | L38: {=IF(OR(is_empty,is_header), "", INDEX('Budget Planning'!$E:$AS, row_id, MATCH(IF(selected_period="Total Year", selected_year, DATE(selected_year, selected_period, 1)),'Budget Planning'!$E$9:$AS$9,0) ))} | M38: {=IF(is_cat, IF(header_row_id=income_header_row, MATCH(income_min_row,$C:$C,0), IF(header_row_id=expenses_header_row, MATCH(expenses_min_row,$C:$C,0), IF(header_row_id=savings_header_row, MATCH(savings_min_row,$C:$C,0), ""))), "")} | N38: {=IF(is_cat, IF(header_row_id=income_header_row, MATCH(income_max_row,$C:$C,0), IF(header_row_id=expenses_header_row, MATCH(expenses_max_row,$C:$C,0), IF(header_row_id=savings_header_row, MATCH(savings_max_row,$C:$C,0), ""))), "")} | O38: =IF(is_cat, ADDRESS(sort_min_row, COLUMN(tracked)) & ":" & ADDRESS(sort_max_row,COLUMN(tracked)), "") | P38: =IF(is_cat, RANK(tracked, INDIRECT(tracked_range), 0),"") | Q38: =IF(is_cat, ADDRESS(sort_min_row, COLUMN(budget)) & ":" & ADDRESS(sort_max_row,COLUMN(budget)), "") | R38: =IF(is_cat, RANK(budget, INDIRECT(budget_range), 0),"") | S38: =IF(is_cat, _xlfn.NUMBERVALUE(tracked_rank & budget_rank), "") | T38: =IF(is_cat, ADDRESS(sort_min_row, COLUMN(comb_rank)) & ":" & ADDRESS(sort_max_row,COLUMN(comb_rank)), "") | U38: =IF(is_cat, RANK(comb_rank, INDIRECT(comb_rank_range),1), "") | V38: =IF(is_cat, ADDRESS(sort_min_row, COLUMN(comb_rank_norm)) & ":" & ADDRESS(ROW(),COLUMN(comb_rank_norm)), "") | W38: =IF(is_cat,comb_rank_norm + COUNTIF(INDIRECT(comb_rank_norm_run_range),comb_rank_norm)-1, "") | X38: =IF(is_cat, header_row_id + comb_rank_unique, row_id) -> -1 | Y38: =IF(is_empty, "", INDEX($J:$J,MATCH(row_id, $X:$X, 0))) | Z38: =IF(is_empty, "", IF(is_header, "Tracked", INDEX($K:$K, MATCH(row_id, $X:$X,0)))) | AA38: =IF(is_empty, "", IF(is_header, "Budget", INDEX($L:$L, MATCH(row_id, $X:$X,0)))) | AB38: =IF(is_empty, "", IF(is_header, "% Compl.", IFERROR(out_tracked / out_budget, "-"))) | AC38: =IF(is_empty, "", IF(is_header, "Remaining", IF(out_budget - out_tracked > 0, out_budget - out_tracked, 0))) | AD38: =IF(is_empty, "", INDEX($J:$J,MATCH(row_id, $X:$X, 0)))
C39: {=IF(C38=-1,-1, IF(C38<income_max_row,C38+1, IF(C38=income_max_row,income_total_row, IF(C38=income_total_row,"/1", IF(C38="/1",expenses_header_row, IF(C38<expenses_max_row,C38+1, IF(C38=expenses_max_row,expenses_total_row, IF(C38=expenses_total_row,"/2", IF(C38="/2",savings_header_row, IF(C38<savings_max_row,C38+1, IF(C38=savings_max_row,savings_total_row,-1)))))))))))} -> -1 | D39: =IF(is_header,row_id, IF(NOT(is_empty),D38,-1)) -> -1 | E39: {=1*OR(row_id=income_header_row,row_id=expenses_header_row,row_id=savings_header_row)} -> 0 | F39: =1*NOT(OR(is_header,is_total,is_empty)) -> 0 | G39: {=1*OR(row_id=expenses_total_row,row_id=savings_total_row,row_id=income_total_row)} -> 0 | H39: =1*OR(row_id="/1", row_id="/2", row_id=-1) -> 1 | I39: {=IFERROR(INDEX('Budget Planning'!$C:$C, header_row_id), "")} | J39: {=IFERROR(INDEX('Budget Planning'!$C:$C, row_id), "")} | K39: {=IF(OR(is_header, is_empty), "", IF(is_total, IF(selected_period="Total Year", SUM(Tracking[Amount] * (Tracking[Type]=type) * (YEAR(Tracking[Effective Date])=selected_year)), SUM(Tracking[Amount] * (Tracking[Type]=type) * (YEAR(Tracking[Effective Date])=selected_year) * (MONTH(Tracking[Effective Date])=selected_period))), IF(selected_period="Total Year", SUM(Tracking[Amount] * (Tracking[Type]=type) * (Tracking[Category]=item) * (YEAR(Tracking[Effective Date])=selected_year)), SUM(Tracking[Amount] * (Tracking[Type]=type) * (Tracking[Category]=item) * (YEAR(Tracking[Effective Date])=selected_year) * (MONTH(Tracking[Effective Date])=selected_period))) ) )} | L39: {=IF(OR(is_empty,is_header), "", INDEX('Budget Planning'!$E:$AS, row_id, MATCH(IF(selected_period="Total Year", selected_year, DATE(selected_year, selected_period, 1)),'Budget Planning'!$E$9:$AS$9,0) ))} | M39: {=IF(is_cat, IF(header_row_id=income_header_row, MATCH(income_min_row,$C:$C,0), IF(header_row_id=expenses_header_row, MATCH(expenses_min_row,$C:$C,0), IF(header_row_id=savings_header_row, MATCH(savings_min_row,$C:$C,0), ""))), "")} | N39: {=IF(is_cat, IF(header_row_id=income_header_row, MATCH(income_max_row,$C:$C,0), IF(header_row_id=expenses_header_row, MATCH(expenses_max_row,$C:$C,0), IF(header_row_id=savings_header_row, MATCH(savings_max_row,$C:$C,0), ""))), "")} | O39: =IF(is_cat, ADDRESS(sort_min_row, COLUMN(tracked)) & ":" & ADDRESS(sort_max_row,COLUMN(tracked)), "") | P39: =IF(is_cat, RANK(tracked, INDIRECT(tracked_range), 0),"") | Q39: =IF(is_cat, ADDRESS(sort_min_row, COLUMN(budget)) & ":" & ADDRESS(sort_max_row,COLUMN(budget)), "") | R39: =IF(is_cat, RANK(budget, INDIRECT(budget_range), 0),"") | S39: =IF(is_cat, _xlfn.NUMBERVALUE(tracked_rank & budget_rank), "") | T39: =IF(is_cat, ADDRESS(sort_min_row, COLUMN(comb_rank)) & ":" & ADDRESS(sort_max_row,COLUMN(comb_rank)), "") | U39: =IF(is_cat, RANK(comb_rank, INDIRECT(comb_rank_range),1), "") | V39: =IF(is_cat, ADDRESS(sort_min_row, COLUMN(comb_rank_norm)) & ":" & ADDRESS(ROW(),COLUMN(comb_rank_norm)), "") | W39: =IF(is_cat,comb_rank_norm + COUNTIF(INDIRECT(comb_rank_norm_run_range),comb_rank_norm)-1, "") | X39: =IF(is_cat, header_row_id + comb_rank_unique, row_id) -> -1 | Y39: =IF(is_empty, "", INDEX($J:$J,MATCH(row_id, $X:$X, 0))) | Z39: =IF(is_empty, "", IF(is_header, "Tracked", INDEX($K:$K, MATCH(row_id, $X:$X,0)))) | AA39: =IF(is_empty, "", IF(is_header, "Budget", INDEX($L:$L, MATCH(row_id, $X:$X,0)))) | AB39: =IF(is_empty, "", IF(is_header, "% Compl.", IFERROR(out_tracked / out_budget, "-"))) | AC39: =IF(is_empty, "", IF(is_header, "Remaining", IF(out_budget - out_tracked > 0, out_budget - out_tracked, 0))) | AD39: =IF(is_empty, "", INDEX($J:$J,MATCH(row_id, $X:$X, 0)))
C40: {=IF(C39=-1,-1, IF(C39<income_max_row,C39+1, IF(C39=income_max_row,income_total_row, IF(C39=income_total_row,"/1", IF(C39="/1",expenses_header_row, IF(C39<expenses_max_row,C39+1, IF(C39=expenses_max_row,expenses_total_row, IF(C39=expenses_total_row,"/2", IF(C39="/2",savings_header_row, IF(C39<savings_max_row,C39+1, IF(C39=savings_max_row,savings_total_row,-1)))))))))))} -> -1 | D40: =IF(is_header,row_id, IF(NOT(is_empty),D39,-1)) -> -1 | E40: {=1*OR(row_id=income_header_row,row_id=expenses_header_row,row_id=savings_header_row)} -> 0 | F40: =1*NOT(OR(is_header,is_total,is_empty)) -> 0 | G40: {=1*OR(row_id=expenses_total_row,row_id=savings_total_row,row_id=income_total_row)} -> 0 | H40: =1*OR(row_id="/1", row_id="/2", row_id=-1) -> 1 | I40: {=IFERROR(INDEX('Budget Planning'!$C:$C, header_row_id), "")} | J40: {=IFERROR(INDEX('Budget Planning'!$C:$C, row_id), "")} | K40: {=IF(OR(is_header, is_empty), "", IF(is_total, IF(selected_period="Total Year", SUM(Tracking[Amount] * (Tracking[Type]=type) * (YEAR(Tracking[Effective Date])=selected_year)), SUM(Tracking[Amount] * (Tracking[Type]=type) * (YEAR(Tracking[Effective Date])=selected_year) * (MONTH(Tracking[Effective Date])=selected_period))), IF(selected_period="Total Year", SUM(Tracking[Amount] * (Tracking[Type]=type) * (Tracking[Category]=item) * (YEAR(Tracking[Effective Date])=selected_year)), SUM(Tracking[Amount] * (Tracking[Type]=type) * (Tracking[Category]=item) * (YEAR(Tracking[Effective Date])=selected_year) * (MONTH(Tracking[Effective Date])=selected_period))) ) )} | L40: {=IF(OR(is_empty,is_header), "", INDEX('Budget Planning'!$E:$AS, row_id, MATCH(IF(selected_period="Total Year", selected_year, DATE(selected_year, selected_period, 1)),'Budget Planning'!$E$9:$AS$9,0) ))} | M40: {=IF(is_cat, IF(header_row_id=income_header_row, MATCH(income_min_row,$C:$C,0), IF(header_row_id=expenses_header_row, MATCH(expenses_min_row,$C:$C,0), IF(header_row_id=savings_header_row, MATCH(savings_min_row,$C:$C,0), ""))), "")} | N40: {=IF(is_cat, IF(header_row_id=income_header_row, MATCH(income_max_row,$C:$C,0), IF(header_row_id=expenses_header_row, MATCH(expenses_max_row,$C:$C,0), IF(header_row_id=savings_header_row, MATCH(savings_max_row,$C:$C,0), ""))), "")} | O40: =IF(is_cat, ADDRESS(sort_min_row, COLUMN(tracked)) & ":" & ADDRESS(sort_max_row,COLUMN(tracked)), "") | P40: =IF(is_cat, RANK(tracked, INDIRECT(tracked_range), 0),"") | Q40: =IF(is_cat, ADDRESS(sort_min_row, COLUMN(budget)) & ":" & ADDRESS(sort_max_row,COLUMN(budget)), "") | R40: =IF(is_cat, RANK(budget, INDIRECT(budget_range), 0),"") | S40: =IF(is_cat, _xlfn.NUMBERVALUE(tracked_rank & budget_rank), "") | T40: =IF(is_cat, ADDRESS(sort_min_row, COLUMN(comb_rank)) & ":" & ADDRESS(sort_max_row,COLUMN(comb_rank)), "") | U40: =IF(is_cat, RANK(comb_rank, INDIRECT(comb_rank_range),1), "") | V40: =IF(is_cat, ADDRESS(sort_min_row, COLUMN(comb_rank_norm)) & ":" & ADDRESS(ROW(),COLUMN(comb_rank_norm)), "") | W40: =IF(is_cat,comb_rank_norm + COUNTIF(INDIRECT(comb_rank_norm_run_range),comb_rank_norm)-1, "") | X40: =IF(is_cat, header_row_id + comb_rank_unique, row_id) -> -1 | Y40: =IF(is_empty, "", INDEX($J:$J,MATCH(row_id, $X:$X, 0))) | Z40: =IF(is_empty, "", IF(is_header, "Tracked", INDEX($K:$K, MATCH(row_id, $X:$X,0)))) | AA40: =IF(is_empty, "", IF(is_header, "Budget", INDEX($L:$L, MATCH(row_id, $X:$X,0)))) | AB40: =IF(is_empty, "", IF(is_header, "% Compl.", IFERROR(out_tracked / out_budget, "-"))) | AC40: =IF(is_empty, "", IF(is_header, "Remaining", IF(out_budget - out_tracked > 0, out_budget - out_tracked, 0))) | AD40: =IF(is_empty, "", INDEX($J:$J,MATCH(row_id, $X:$X, 0)))
C41: {=IF(C40=-1,-1, IF(C40<income_max_row,C40+1, IF(C40=income_max_row,income_total_row, IF(C40=income_total_row,"/1", IF(C40="/1",expenses_header_row, IF(C40<expenses_max_row,C40+1, IF(C40=expenses_max_row,expenses_total_row, IF(C40=expenses_total_row,"/2", IF(C40="/2",savings_header_row, IF(C40<savings_max_row,C40+1, IF(C40=savings_max_row,savings_total_row,-1)))))))))))} -> -1 | D41: =IF(is_header,row_id, IF(NOT(is_empty),D40,-1)) -> -1 | E41: {=1*OR(row_id=income_header_row,row_id=expenses_header_row,row_id=savings_header_row)} -> 0 | F41: =1*NOT(OR(is_header,is_total,is_empty)) -> 0 | G41: {=1*OR(row_id=expenses_total_row,row_id=savings_total_row,row_id=income_total_row)} -> 0 | H41: =1*OR(row_id="/1", row_id="/2", row_id=-1) -> 1 | I41: {=IFERROR(INDEX('Budget Planning'!$C:$C, header_row_id), "")} | J41: {=IFERROR(INDEX('Budget Planning'!$C:$C, row_id), "")} | K41: {=IF(OR(is_header, is_empty), "", IF(is_total, IF(selected_period="Total Year", SUM(Tracking[Amount] * (Tracking[Type]=type) * (YEAR(Tracking[Effective Date])=selected_year)), SUM(Tracking[Amount] * (Tracking[Type]=type) * (YEAR(Tracking[Effective Date])=selected_year) * (MONTH(Tracking[Effective Date])=selected_period))), IF(selected_period="Total Year", SUM(Tracking[Amount] * (Tracking[Type]=type) * (Tracking[Category]=item) * (YEAR(Tracking[Effective Date])=selected_year)), SUM(Tracking[Amount] * (Tracking[Type]=type) * (Tracking[Category]=item) * (YEAR(Tracking[Effective Date])=selected_year) * (MONTH(Tracking[Effective Date])=selected_period))) ) )} | L41: {=IF(OR(is_empty,is_header), "", INDEX('Budget Planning'!$E:$AS, row_id, MATCH(IF(selected_period="Total Year", selected_year, DATE(selected_year, selected_period, 1)),'Budget Planning'!$E$9:$AS$9,0) ))} | M41: {=IF(is_cat, IF(header_row_id=income_header_row, MATCH(income_min_row,$C:$C,0), IF(header_row_id=expenses_header_row, MATCH(expenses_min_row,$C:$C,0), IF(header_row_id=savings_header_row, MATCH(savings_min_row,$C:$C,0), ""))), "")} | N41: {=IF(is_cat, IF(header_row_id=income_header_row, MATCH(income_max_row,$C:$C,0), IF(header_row_id=expenses_header_row, MATCH(expenses_max_row,$C:$C,0), IF(header_row_id=savings_header_row, MATCH(savings_max_row,$C:$C,0), ""))), "")} | O41: =IF(is_cat, ADDRESS(sort_min_row, COLUMN(tracked)) & ":" & ADDRESS(sort_max_row,COLUMN(tracked)), "") | P41: =IF(is_cat, RANK(tracked, INDIRECT(tracked_range), 0),"") | Q41: =IF(is_cat, ADDRESS(sort_min_row, COLUMN(budget)) & ":" & ADDRESS(sort_max_row,COLUMN(budget)), "") | R41: =IF(is_cat, RANK(budget, INDIRECT(budget_range), 0),"") | S41: =IF(is_cat, _xlfn.NUMBERVALUE(tracked_rank & budget_rank), "") | T41: =IF(is_cat, ADDRESS(sort_min_row, COLUMN(comb_rank)) & ":" & ADDRESS(sort_max_row,COLUMN(comb_rank)), "") | U41: =IF(is_cat, RANK(comb_rank, INDIRECT(comb_rank_range),1), "") | V41: =IF(is_cat, ADDRESS(sort_min_row, COLUMN(comb_rank_norm)) & ":" & ADDRESS(ROW(),COLUMN(comb_rank_norm)), "") | W41: =IF(is_cat,comb_rank_norm + COUNTIF(INDIRECT(comb_rank_norm_run_range),comb_rank_norm)-1, "") | X41: =IF(is_cat, header_row_id + comb_rank_unique, row_id) -> -1 | Y41: =IF(is_empty, "", INDEX($J:$J,MATCH(row_id, $X:$X, 0))) | Z41: =IF(is_empty, "", IF(is_header, "Tracked", INDEX($K:$K, MATCH(row_id, $X:$X,0)))) | AA41: =IF(is_empty, "", IF(is_header, "Budget", INDEX($L:$L, MATCH(row_id, $X:$X,0)))) | AB41: =IF(is_empty, "", IF(is_header, "% Compl.", IFERROR(out_tracked / out_budget, "-"))) | AC41: =IF(is_empty, "", IF(is_header, "Remaining", IF(out_budget - out_tracked > 0, out_budget - out_tracked, 0))) | AD41: =IF(is_empty, "", INDEX($J:$J,MATCH(row_id, $X:$X, 0)))
C42: {=IF(C41=-1,-1, IF(C41<income_max_row,C41+1, IF(C41=income_max_row,income_total_row, IF(C41=income_total_row,"/1", IF(C41="/1",expenses_header_row, IF(C41<expenses_max_row,C41+1, IF(C41=expenses_max_row,expenses_total_row, IF(C41=expenses_total_row,"/2", IF(C41="/2",savings_header_row, IF(C41<savings_max_row,C41+1, IF(C41=savings_max_row,savings_total_row,-1)))))))))))} -> -1 | D42: =IF(is_header,row_id, IF(NOT(is_empty),D41,-1)) -> -1 | E42: {=1*OR(row_id=income_header_row,row_id=expenses_header_row,row_id=savings_header_row)} -> 0 | F42: =1*NOT(OR(is_header,is_total,is_empty)) -> 0 | G42: {=1*OR(row_id=expenses_total_row,row_id=savings_total_row,row_id=income_total_row)} -> 0 | H42: =1*OR(row_id="/1", row_id="/2", row_id=-1) -> 1 | I42: {=IFERROR(INDEX('Budget Planning'!$C:$C, header_row_id), "")} | J42: {=IFERROR(INDEX('Budget Planning'!$C:$C, row_id), "")} | K42: {=IF(OR(is_header, is_empty), "", IF(is_total, IF(selected_period="Total Year", SUM(Tracking[Amount] * (Tracking[Type]=type) * (YEAR(Tracking[Effective Date])=selected_year)), SUM(Tracking[Amount] * (Tracking[Type]=type) * (YEAR(Tracking[Effective Date])=selected_year) * (MONTH(Tracking[Effective Date])=selected_period))), IF(selected_period="Total Year", SUM(Tracking[Amount] * (Tracking[Type]=type) * (Tracking[Category]=item) * (YEAR(Tracking[Effective Date])=selected_year)), SUM(Tracking[Amount] * (Tracking[Type]=type) * (Tracking[Category]=item) * (YEAR(Tracking[Effective Date])=selected_year) * (MONTH(Tracking[Effective Date])=selected_period))) ) )} | L42: {=IF(OR(is_empty,is_header), "", INDEX('Budget Planning'!$E:$AS, row_id, MATCH(IF(selected_period="Total Year", selected_year, DATE(selected_year, selected_period, 1)),'Budget Planning'!$E$9:$AS$9,0) ))} | M42: {=IF(is_cat, IF(header_row_id=income_header_row, MATCH(income_min_row,$C:$C,0), IF(header_row_id=expenses_header_row, MATCH(expenses_min_row,$C:$C,0), IF(header_row_id=savings_header_row, MATCH(savings_min_row,$C:$C,0), ""))), "")} | N42: {=IF(is_cat, IF(header_row_id=income_header_row, MATCH(income_max_row,$C:$C,0), IF(header_row_id=expenses_header_row, MATCH(expenses_max_row,$C:$C,0), IF(header_row_id=savings_header_row, MATCH(savings_max_row,$C:$C,0), ""))), "")} | O42: =IF(is_cat, ADDRESS(sort_min_row, COLUMN(tracked)) & ":" & ADDRESS(sort_max_row,COLUMN(tracked)), "") | P42: =IF(is_cat, RANK(tracked, INDIRECT(tracked_range), 0),"") | Q42: =IF(is_cat, ADDRESS(sort_min_row, COLUMN(budget)) & ":" & ADDRESS(sort_max_row,COLUMN(budget)), "") | R42: =IF(is_cat, RANK(budget, INDIRECT(budget_range), 0),"") | S42: =IF(is_cat, _xlfn.NUMBERVALUE(tracked_rank & budget_rank), "") | T42: =IF(is_cat, ADDRESS(sort_min_row, COLUMN(comb_rank)) & ":" & ADDRESS(sort_max_row,COLUMN(comb_rank)), "") | U42: =IF(is_cat, RANK(comb_rank, INDIRECT(comb_rank_range),1), "") | V42: =IF(is_cat, ADDRESS(sort_min_row, COLUMN(comb_rank_norm)) & ":" & ADDRESS(ROW(),COLUMN(comb_rank_norm)), "") | W42: =IF(is_cat,comb_rank_norm + COUNTIF(INDIRECT(comb_rank_norm_run_range),comb_rank_norm)-1, "") | X42: =IF(is_cat, header_row_id + comb_rank_unique, row_id) -> -1 | Y42: =IF(is_empty, "", INDEX($J:$J,MATCH(row_id, $X:$X, 0))) | Z42: =IF(is_empty, "", IF(is_header, "Tracked", INDEX($K:$K, MATCH(row_id, $X:$X,0)))) | AA42: =IF(is_empty, "", IF(is_header, "Budget", INDEX($L:$L, MATCH(row_id, $X:$X,0)))) | AB42: =IF(is_empty, "", IF(is_header, "% Compl.", IFERROR(out_tracked / out_budget, "-"))) | AC42: =IF(is_empty, "", IF(is_header, "Remaining", IF(out_budget - out_tracked > 0, out_budget - out_tracked, 0))) | AD42: =IF(is_empty, "", INDEX($J:$J,MATCH(row_id, $X:$X, 0)))
C43: {=IF(C42=-1,-1, IF(C42<income_max_row,C42+1, IF(C42=income_max_row,income_total_row, IF(C42=income_total_row,"/1", IF(C42="/1",expenses_header_row, IF(C42<expenses_max_row,C42+1, IF(C42=expenses_max_row,expenses_total_row, IF(C42=expenses_total_row,"/2", IF(C42="/2",savings_header_row, IF(C42<savings_max_row,C42+1, IF(C42=savings_max_row,savings_total_row,-1)))))))))))} -> -1 | D43: =IF(is_header,row_id, IF(NOT(is_empty),D42,-1)) -> -1 | E43: {=1*OR(row_id=income_header_row,row_id=expenses_header_row,row_id=savings_header_row)} -> 0 | F43: =1*NOT(OR(is_header,is_total,is_empty)) -> 0 | G43: {=1*OR(row_id=expenses_total_row,row_id=savings_total_row,row_id=income_total_row)} -> 0 | H43: =1*OR(row_id="/1", row_id="/2", row_id=-1) -> 1 | I43: {=IFERROR(INDEX('Budget Planning'!$C:$C, header_row_id), "")} | J43: {=IFERROR(INDEX('Budget Planning'!$C:$C, row_id), "")} | K43: {=IF(OR(is_header, is_empty), "", IF(is_total, IF(selected_period="Total Year", SUM(Tracking[Amount] * (Tracking[Type]=type) * (YEAR(Tracking[Effective Date])=selected_year)), SUM(Tracking[Amount] * (Tracking[Type]=type) * (YEAR(Tracking[Effective Date])=selected_year) * (MONTH(Tracking[Effective Date])=selected_period))), IF(selected_period="Total Year", SUM(Tracking[Amount] * (Tracking[Type]=type) * (Tracking[Category]=item) * (YEAR(Tracking[Effective Date])=selected_year)), SUM(Tracking[Amount] * (Tracking[Type]=type) * (Tracking[Category]=item) * (YEAR(Tracking[Effective Date])=selected_year) * (MONTH(Tracking[Effective Date])=selected_period))) ) )} | L43: {=IF(OR(is_empty,is_header), "", INDEX('Budget Planning'!$E:$AS, row_id, MATCH(IF(selected_period="Total Year", selected_year, DATE(selected_year, selected_period, 1)),'Budget Planning'!$E$9:$AS$9,0) ))} | M43: {=IF(is_cat, IF(header_row_id=income_header_row, MATCH(income_min_row,$C:$C,0), IF(header_row_id=expenses_header_row, MATCH(expenses_min_row,$C:$C,0), IF(header_row_id=savings_header_row, MATCH(savings_min_row,$C:$C,0), ""))), "")} | N43: {=IF(is_cat, IF(header_row_id=income_header_row, MATCH(income_max_row,$C:$C,0), IF(header_row_id=expenses_header_row, MATCH(expenses_max_row,$C:$C,0), IF(header_row_id=savings_header_row, MATCH(savings_max_row,$C:$C,0), ""))), "")} | O43: =IF(is_cat, ADDRESS(sort_min_row, COLUMN(tracked)) & ":" & ADDRESS(sort_max_row,COLUMN(tracked)), "") | P43: =IF(is_cat, RANK(tracked, INDIRECT(tracked_range), 0),"") | Q43: =IF(is_cat, ADDRESS(sort_min_row, COLUMN(budget)) & ":" & ADDRESS(sort_max_row,COLUMN(budget)), "") | R43: =IF(is_cat, RANK(budget, INDIRECT(budget_range), 0),"") | S43: =IF(is_cat, _xlfn.NUMBERVALUE(tracked_rank & budget_rank), "") | T43: =IF(is_cat, ADDRESS(sort_min_row, COLUMN(comb_rank)) & ":" & ADDRESS(sort_max_row,COLUMN(comb_rank)), "") | U43: =IF(is_cat, RANK(comb_rank, INDIRECT(comb_rank_range),1), "") | V43: =IF(is_cat, ADDRESS(sort_min_row, COLUMN(comb_rank_norm)) & ":" & ADDRESS(ROW(),COLUMN(comb_rank_norm)), "") | W43: =IF(is_cat,comb_rank_norm + COUNTIF(INDIRECT(comb_rank_norm_run_range),comb_rank_norm)-1, "") | X43: =IF(is_cat, header_row_id + comb_rank_unique, row_id) -> -1 | Y43: =IF(is_empty, "", INDEX($J:$J,MATCH(row_id, $X:$X, 0))) | Z43: =IF(is_empty, "", IF(is_header, "Tracked", INDEX($K:$K, MATCH(row_id, $X:$X,0)))) | AA43: =IF(is_empty, "", IF(is_header, "Budget", INDEX($L:$L, MATCH(row_id, $X:$X,0)))) | AB43: =IF(is_empty, "", IF(is_header, "% Compl.", IFERROR(out_tracked / out_budget, "-"))) | AC43: =IF(is_empty, "", IF(is_header, "Remaining", IF(out_budget - out_tracked > 0, out_budget - out_tracked, 0))) | AD43: =IF(is_empty, "", INDEX($J:$J,MATCH(row_id, $X:$X, 0)))
C44: {=IF(C43=-1,-1, IF(C43<income_max_row,C43+1, IF(C43=income_max_row,income_total_row, IF(C43=income_total_row,"/1", IF(C43="/1",expenses_header_row, IF(C43<expenses_max_row,C43+1, IF(C43=expenses_max_row,expenses_total_row, IF(C43=expenses_total_row,"/2", IF(C43="/2",savings_header_row, IF(C43<savings_max_row,C43+1, IF(C43=savings_max_row,savings_total_row,-1)))))))))))} -> -1 | D44: =IF(is_header,row_id, IF(NOT(is_empty),D43,-1)) -> -1 | E44: {=1*OR(row_id=income_header_row,row_id=expenses_header_row,row_id=savings_header_row)} -> 0 | F44: =1*NOT(OR(is_header,is_total,is_empty)) -> 0 | G44: {=1*OR(row_id=expenses_total_row,row_id=savings_total_row,row_id=income_total_row)} -> 0 | H44: =1*OR(row_id="/1", row_id="/2", row_id=-1) -> 1 | I44: {=IFERROR(INDEX('Budget Planning'!$C:$C, header_row_id), "")} | J44: {=IFERROR(INDEX('Budget Planning'!$C:$C, row_id), "")} | K44: {=IF(OR(is_header, is_empty), "", IF(is_total, IF(selected_period="Total Year", SUM(Tracking[Amount] * (Tracking[Type]=type) * (YEAR(Tracking[Effective Date])=selected_year)), SUM(Tracking[Amount] * (Tracking[Type]=type) * (YEAR(Tracking[Effective Date])=selected_year) * (MONTH(Tracking[Effective Date])=selected_period))), IF(selected_period="Total Year", SUM(Tracking[Amount] * (Tracking[Type]=type) * (Tracking[Category]=item) * (YEAR(Tracking[Effective Date])=selected_year)), SUM(Tracking[Amount] * (Tracking[Type]=type) * (Tracking[Category]=item) * (YEAR(Tracking[Effective Date])=selected_year) * (MONTH(Tracking[Effective Date])=selected_period))) ) )} | L44: {=IF(OR(is_empty,is_header), "", INDEX('Budget Planning'!$E:$AS, row_id, MATCH(IF(selected_period="Total Year", selected_year, DATE(selected_year, selected_period, 1)),'Budget Planning'!$E$9:$AS$9,0) ))} | M44: {=IF(is_cat, IF(header_row_id=income_header_row, MATCH(income_min_row,$C:$C,0), IF(header_row_id=expenses_header_row, MATCH(expenses_min_row,$C:$C,0), IF(header_row_id=savings_header_row, MATCH(savings_min_row,$C:$C,0), ""))), "")} | N44: {=IF(is_cat, IF(header_row_id=income_header_row, MATCH(income_max_row,$C:$C,0), IF(header_row_id=expenses_header_row, MATCH(expenses_max_row,$C:$C,0), IF(header_row_id=savings_header_row, MATCH(savings_max_row,$C:$C,0), ""))), "")} | O44: =IF(is_cat, ADDRESS(sort_min_row, COLUMN(tracked)) & ":" & ADDRESS(sort_max_row,COLUMN(tracked)), "") | P44: =IF(is_cat, RANK(tracked, INDIRECT(tracked_range), 0),"") | Q44: =IF(is_cat, ADDRESS(sort_min_row, COLUMN(budget)) & ":" & ADDRESS(sort_max_row,COLUMN(budget)), "") | R44: =IF(is_cat, RANK(budget, INDIRECT(budget_range), 0),"") | S44: =IF(is_cat, _xlfn.NUMBERVALUE(tracked_rank & budget_rank), "") | T44: =IF(is_cat, ADDRESS(sort_min_row, COLUMN(comb_rank)) & ":" & ADDRESS(sort_max_row,COLUMN(comb_rank)), "") | U44: =IF(is_cat, RANK(comb_rank, INDIRECT(comb_rank_range),1), "") | V44: =IF(is_cat, ADDRESS(sort_min_row, COLUMN(comb_rank_norm)) & ":" & ADDRESS(ROW(),COLUMN(comb_rank_norm)), "") | W44: =IF(is_cat,comb_rank_norm + COUNTIF(INDIRECT(comb_rank_norm_run_range),comb_rank_norm)-1, "") | X44: =IF(is_cat, header_row_id + comb_rank_unique, row_id) -> -1 | Y44: =IF(is_empty, "", INDEX($J:$J,MATCH(row_id, $X:$X, 0))) | Z44: =IF(is_empty, "", IF(is_header, "Tracked", INDEX($K:$K, MATCH(row_id, $X:$X,0)))) | AA44: =IF(is_empty, "", IF(is_header, "Budget", INDEX($L:$L, MATCH(row_id, $X:$X,0)))) | AB44: =IF(is_empty, "", IF(is_header, "% Compl.", IFERROR(out_tracked / out_budget, "-"))) | AC44: =IF(is_empty, "", IF(is_header, "Remaining", IF(out_budget - out_tracked > 0, out_budget - out_tracked, 0))) | AD44: =IF(is_empty, "", INDEX($J:$J,MATCH(row_id, $X:$X, 0)))
C45: {=IF(C44=-1,-1, IF(C44<income_max_row,C44+1, IF(C44=income_max_row,income_total_row, IF(C44=income_total_row,"/1", IF(C44="/1",expenses_header_row, IF(C44<expenses_max_row,C44+1, IF(C44=expenses_max_row,expenses_total_row, IF(C44=expenses_total_row,"/2", IF(C44="/2",savings_header_row, IF(C44<savings_max_row,C44+1, IF(C44=savings_max_row,savings_total_row,-1)))))))))))} -> -1 | D45: =IF(is_header,row_id, IF(NOT(is_empty),D44,-1)) -> -1 | E45: {=1*OR(row_id=income_header_row,row_id=expenses_header_row,row_id=savings_header_row)} -> 0 | F45: =1*NOT(OR(is_header,is_total,is_empty)) -> 0 | G45: {=1*OR(row_id=expenses_total_row,row_id=savings_total_row,row_id=income_total_row)} -> 0 | H45: =1*OR(row_id="/1", row_id="/2", row_id=-1) -> 1 | I45: {=IFERROR(INDEX('Budget Planning'!$C:$C, header_row_id), "")} | J45: {=IFERROR(INDEX('Budget Planning'!$C:$C, row_id), "")} | K45: {=IF(OR(is_header, is_empty), "", IF(is_total, IF(selected_period="Total Year", SUM(Tracking[Amount] * (Tracking[Type]=type) * (YEAR(Tracking[Effective Date])=selected_year)), SUM(Tracking[Amount] * (Tracking[Type]=type) * (YEAR(Tracking[Effective Date])=selected_year) * (MONTH(Tracking[Effective Date])=selected_period))), IF(selected_period="Total Year", SUM(Tracking[Amount] * (Tracking[Type]=type) * (Tracking[Category]=item) * (YEAR(Tracking[Effective Date])=selected_year)), SUM(Tracking[Amount] * (Tracking[Type]=type) * (Tracking[Category]=item) * (YEAR(Tracking[Effective Date])=selected_year) * (MONTH(Tracking[Effective Date])=selected_period))) ) )} | L45: {=IF(OR(is_empty,is_header), "", INDEX('Budget Planning'!$E:$AS, row_id, MATCH(IF(selected_period="Total Year", selected_year, DATE(selected_year, selected_period, 1)),'Budget Planning'!$E$9:$AS$9,0) ))} | M45: {=IF(is_cat, IF(header_row_id=income_header_row, MATCH(income_min_row,$C:$C,0), IF(header_row_id=expenses_header_row, MATCH(expenses_min_row,$C:$C,0), IF(header_row_id=savings_header_row, MATCH(savings_min_row,$C:$C,0), ""))), "")} | N45: {=IF(is_cat, IF(header_row_id=income_header_row, MATCH(income_max_row,$C:$C,0), IF(header_row_id=expenses_header_row, MATCH(expenses_max_row,$C:$C,0), IF(header_row_id=savings_header_row, MATCH(savings_max_row,$C:$C,0), ""))), "")} | O45: =IF(is_cat, ADDRESS(sort_min_row, COLUMN(tracked)) & ":" & ADDRESS(sort_max_row,COLUMN(tracked)), "") | P45: =IF(is_cat, RANK(tracked, INDIRECT(tracked_range), 0),"") | Q45: =IF(is_cat, ADDRESS(sort_min_row, COLUMN(budget)) & ":" & ADDRESS(sort_max_row,COLUMN(budget)), "") | R45: =IF(is_cat, RANK(budget, INDIRECT(budget_range), 0),"") | S45: =IF(is_cat, _xlfn.NUMBERVALUE(tracked_rank & budget_rank), "") | T45: =IF(is_cat, ADDRESS(sort_min_row, COLUMN(comb_rank)) & ":" & ADDRESS(sort_max_row,COLUMN(comb_rank)), "") | U45: =IF(is_cat, RANK(comb_rank, INDIRECT(comb_rank_range),1), "") | V45: =IF(is_cat, ADDRESS(sort_min_row, COLUMN(comb_rank_norm)) & ":" & ADDRESS(ROW(),COLUMN(comb_rank_norm)), "") | W45: =IF(is_cat,comb_rank_norm + COUNTIF(INDIRECT(comb_rank_norm_run_range),comb_rank_norm)-1, "") | X45: =IF(is_cat, header_row_id + comb_rank_unique, row_id) -> -1 | Y45: =IF(is_empty, "", INDEX($J:$J,MATCH(row_id, $X:$X, 0))) | Z45: =IF(is_empty, "", IF(is_header, "Tracked", INDEX($K:$K, MATCH(row_id, $X:$X,0)))) | AA45: =IF(is_empty, "", IF(is_header, "Budget", INDEX($L:$L, MATCH(row_id, $X:$X,0)))) | AB45: =IF(is_empty, "", IF(is_header, "% Compl.", IFERROR(out_tracked / out_budget, "-"))) | AC45: =IF(is_empty, "", IF(is_header, "Remaining", IF(out_budget - out_tracked > 0, out_budget - out_tracked, 0))) | AD45: =IF(is_empty, "", INDEX($J:$J,MATCH(row_id, $X:$X, 0)))
C46: {=IF(C45=-1,-1, IF(C45<income_max_row,C45+1, IF(C45=income_max_row,income_total_row, IF(C45=income_total_row,"/1", IF(C45="/1",expenses_header_row, IF(C45<expenses_max_row,C45+1, IF(C45=expenses_max_row,expenses_total_row, IF(C45=expenses_total_row,"/2", IF(C45="/2",savings_header_row, IF(C45<savings_max_row,C45+1, IF(C45=savings_max_row,savings_total_row,-1)))))))))))} -> -1 | D46: =IF(is_header,row_id, IF(NOT(is_empty),D45,-1)) -> -1 | E46: {=1*OR(row_id=income_header_row,row_id=expenses_header_row,row_id=savings_header_row)} -> 0 | F46: =1*NOT(OR(is_header,is_total,is_empty)) -> 0 | G46: {=1*OR(row_id=expenses_total_row,row_id=savings_total_row,row_id=income_total_row)} -> 0 | H46: =1*OR(row_id="/1", row_id="/2", row_id=-1) -> 1 | I46: {=IFERROR(INDEX('Budget Planning'!$C:$C, header_row_id), "")} | J46: {=IFERROR(INDEX('Budget Planning'!$C:$C, row_id), "")} | K46: {=IF(OR(is_header, is_empty), "", IF(is_total, IF(selected_period="Total Year", SUM(Tracking[Amount] * (Tracking[Type]=type) * (YEAR(Tracking[Effective Date])=selected_year)), SUM(Tracking[Amount] * (Tracking[Type]=type) * (YEAR(Tracking[Effective Date])=selected_year) * (MONTH(Tracking[Effective Date])=selected_period))), IF(selected_period="Total Year", SUM(Tracking[Amount] * (Tracking[Type]=type) * (Tracking[Category]=item) * (YEAR(Tracking[Effective Date])=selected_year)), SUM(Tracking[Amount] * (Tracking[Type]=type) * (Tracking[Category]=item) * (YEAR(Tracking[Effective Date])=selected_year) * (MONTH(Tracking[Effective Date])=selected_period))) ) )} | L46: {=IF(OR(is_empty,is_header), "", INDEX('Budget Planning'!$E:$AS, row_id, MATCH(IF(selected_period="Total Year", selected_year, DATE(selected_year, selected_period, 1)),'Budget Planning'!$E$9:$AS$9,0) ))} | M46: {=IF(is_cat, IF(header_row_id=income_header_row, MATCH(income_min_row,$C:$C,0), IF(header_row_id=expenses_header_row, MATCH(expenses_min_row,$C:$C,0), IF(header_row_id=savings_header_row, MATCH(savings_min_row,$C:$C,0), ""))), "")} | N46: {=IF(is_cat, IF(header_row_id=income_header_row, MATCH(income_max_row,$C:$C,0), IF(header_row_id=expenses_header_row, MATCH(expenses_max_row,$C:$C,0), IF(header_row_id=savings_header_row, MATCH(savings_max_row,$C:$C,0), ""))), "")} | O46: =IF(is_cat, ADDRESS(sort_min_row, COLUMN(tracked)) & ":" & ADDRESS(sort_max_row,COLUMN(tracked)), "") | P46: =IF(is_cat, RANK(tracked, INDIRECT(tracked_range), 0),"") | Q46: =IF(is_cat, ADDRESS(sort_min_row, COLUMN(budget)) & ":" & ADDRESS(sort_max_row,COLUMN(budget)), "") | R46: =IF(is_cat, RANK(budget, INDIRECT(budget_range), 0),"") | S46: =IF(is_cat, _xlfn.NUMBERVALUE(tracked_rank & budget_rank), "") | T46: =IF(is_cat, ADDRESS(sort_min_row, COLUMN(comb_rank)) & ":" & ADDRESS(sort_max_row,COLUMN(comb_rank)), "") | U46: =IF(is_cat, RANK(comb_rank, INDIRECT(comb_rank_range),1), "") | V46: =IF(is_cat, ADDRESS(sort_min_row, COLUMN(comb_rank_norm)) & ":" & ADDRESS(ROW(),COLUMN(comb_rank_norm)), "") | W46: =IF(is_cat,comb_rank_norm + COUNTIF(INDIRECT(comb_rank_norm_run_range),comb_rank_norm)-1, "") | X46: =IF(is_cat, header_row_id + comb_rank_unique, row_id) -> -1 | Y46: =IF(is_empty, "", INDEX($J:$J,MATCH(row_id, $X:$X, 0))) | Z46: =IF(is_empty, "", IF(is_header, "Tracked", INDEX($K:$K, MATCH(row_id, $X:$X,0)))) | AA46: =IF(is_empty, "", IF(is_header, "Budget", INDEX($L:$L, MATCH(row_id, $X:$X,0)))) | AB46: =IF(is_empty, "", IF(is_header, "% Compl.", IFERROR(out_tracked / out_budget, "-"))) | AC46: =IF(is_empty, "", IF(is_header, "Remaining", IF(out_budget - out_tracked > 0, out_budget - out_tracked, 0))) | AD46: =IF(is_empty, "", INDEX($J:$J,MATCH(row_id, $X:$X, 0)))
C47: {=IF(C46=-1,-1, IF(C46<income_max_row,C46+1, IF(C46=income_max_row,income_total_row, IF(C46=income_total_row,"/1", IF(C46="/1",expenses_header_row, IF(C46<expenses_max_row,C46+1, IF(C46=expenses_max_row,expenses_total_row, IF(C46=expenses_total_row,"/2", IF(C46="/2",savings_header_row, IF(C46<savings_max_row,C46+1, IF(C46=savings_max_row,savings_total_row,-1)))))))))))} -> -1 | D47: =IF(is_header,row_id, IF(NOT(is_empty),D46,-1)) -> -1 | E47: {=1*OR(row_id=income_header_row,row_id=expenses_header_row,row_id=savings_header_row)} -> 0 | F47: =1*NOT(OR(is_header,is_total,is_empty)) -> 0 | G47: {=1*OR(row_id=expenses_total_row,row_id=savings_total_row,row_id=income_total_row)} -> 0 | H47: =1*OR(row_id="/1", row_id="/2", row_id=-1) -> 1 | I47: {=IFERROR(INDEX('Budget Planning'!$C:$C, header_row_id), "")} | J47: {=IFERROR(INDEX('Budget Planning'!$C:$C, row_id), "")} | K47: {=IF(OR(is_header, is_empty), "", IF(is_total, IF(selected_period="Total Year", SUM(Tracking[Amount] * (Tracking[Type]=type) * (YEAR(Tracking[Effective Date])=selected_year)), SUM(Tracking[Amount] * (Tracking[Type]=type) * (YEAR(Tracking[Effective Date])=selected_year) * (MONTH(Tracking[Effective Date])=selected_period))), IF(selected_period="Total Year", SUM(Tracking[Amount] * (Tracking[Type]=type) * (Tracking[Category]=item) * (YEAR(Tracking[Effective Date])=selected_year)), SUM(Tracking[Amount] * (Tracking[Type]=type) * (Tracking[Category]=item) * (YEAR(Tracking[Effective Date])=selected_year) * (MONTH(Tracking[Effective Date])=selected_period))) ) )} | L47: {=IF(OR(is_empty,is_header), "", INDEX('Budget Planning'!$E:$AS, row_id, MATCH(IF(selected_period="Total Year", selected_year, DATE(selected_year, selected_period, 1)),'Budget Planning'!$E$9:$AS$9,0) ))} | M47: {=IF(is_cat, IF(header_row_id=income_header_row, MATCH(income_min_row,$C:$C,0), IF(header_row_id=expenses_header_row, MATCH(expenses_min_row,$C:$C,0), IF(header_row_id=savings_header_row, MATCH(savings_min_row,$C:$C,0), ""))), "")} | N47: {=IF(is_cat, IF(header_row_id=income_header_row, MATCH(income_max_row,$C:$C,0), IF(header_row_id=expenses_header_row, MATCH(expenses_max_row,$C:$C,0), IF(header_row_id=savings_header_row, MATCH(savings_max_row,$C:$C,0), ""))), "")} | O47: =IF(is_cat, ADDRESS(sort_min_row, COLUMN(tracked)) & ":" & ADDRESS(sort_max_row,COLUMN(tracked)), "") | P47: =IF(is_cat, RANK(tracked, INDIRECT(tracked_range), 0),"") | Q47: =IF(is_cat, ADDRESS(sort_min_row, COLUMN(budget)) & ":" & ADDRESS(sort_max_row,COLUMN(budget)), "") | R47: =IF(is_cat, RANK(budget, INDIRECT(budget_range), 0),"") | S47: =IF(is_cat, _xlfn.NUMBERVALUE(tracked_rank & budget_rank), "") | T47: =IF(is_cat, ADDRESS(sort_min_row, COLUMN(comb_rank)) & ":" & ADDRESS(sort_max_row,COLUMN(comb_rank)), "") | U47: =IF(is_cat, RANK(comb_rank, INDIRECT(comb_rank_range),1), "") | V47: =IF(is_cat, ADDRESS(sort_min_row, COLUMN(comb_rank_norm)) & ":" & ADDRESS(ROW(),COLUMN(comb_rank_norm)), "") | W47: =IF(is_cat,comb_rank_norm + COUNTIF(INDIRECT(comb_rank_norm_run_range),comb_rank_norm)-1, "") | X47: =IF(is_cat, header_row_id + comb_rank_unique, row_id) -> -1 | Y47: =IF(is_empty, "", INDEX($J:$J,MATCH(row_id, $X:$X, 0))) | Z47: =IF(is_empty, "", IF(is_header, "Tracked", INDEX($K:$K, MATCH(row_id, $X:$X,0)))) | AA47: =IF(is_empty, "", IF(is_header, "Budget", INDEX($L:$L, MATCH(row_id, $X:$X,0)))) | AB47: =IF(is_empty, "", IF(is_header, "% Compl.", IFERROR(out_tracked / out_budget, "-"))) | AC47: =IF(is_empty, "", IF(is_header, "Remaining", IF(out_budget - out_tracked > 0, out_budget - out_tracked, 0))) | AD47: =IF(is_empty, "", INDEX($J:$J,MATCH(row_id, $X:$X, 0)))
C48: {=IF(C47=-1,-1, IF(C47<income_max_row,C47+1, IF(C47=income_max_row,income_total_row, IF(C47=income_total_row,"/1", IF(C47="/1",expenses_header_row, IF(C47<expenses_max_row,C47+1, IF(C47=expenses_max_row,expenses_total_row, IF(C47=expenses_total_row,"/2", IF(C47="/2",savings_header_row, IF(C47<savings_max_row,C47+1, IF(C47=savings_max_row,savings_total_row,-1)))))))))))} -> -1 | D48: =IF(is_header,row_id, IF(NOT(is_empty),D47,-1)) -> -1 | E48: {=1*OR(row_id=income_header_row,row_id=expenses_header_row,row_id=savings_header_row)} -> 0 | F48: =1*NOT(OR(is_header,is_total,is_empty)) -> 0 | G48: {=1*OR(row_id=expenses_total_row,row_id=savings_total_row,row_id=income_total_row)} -> 0 | H48: =1*OR(row_id="/1", row_id="/2", row_id=-1) -> 1 | I48: {=IFERROR(INDEX('Budget Planning'!$C:$C, header_row_id), "")} | J48: {=IFERROR(INDEX('Budget Planning'!$C:$C, row_id), "")} | K48: {=IF(OR(is_header, is_empty), "", IF(is_total, IF(selected_period="Total Year", SUM(Tracking[Amount] * (Tracking[Type]=type) * (YEAR(Tracking[Effective Date])=selected_year)), SUM(Tracking[Amount] * (Tracking[Type]=type) * (YEAR(Tracking[Effective Date])=selected_year) * (MONTH(Tracking[Effective Date])=selected_period))), IF(selected_period="Total Year", SUM(Tracking[Amount] * (Tracking[Type]=type) * (Tracking[Category]=item) * (YEAR(Tracking[Effective Date])=selected_year)), SUM(Tracking[Amount] * (Tracking[Type]=type) * (Tracking[Category]=item) * (YEAR(Tracking[Effective Date])=selected_year) * (MONTH(Tracking[Effective Date])=selected_period))) ) )} | L48: {=IF(OR(is_empty,is_header), "", INDEX('Budget Planning'!$E:$AS, row_id, MATCH(IF(selected_period="Total Year", selected_year, DATE(selected_year, selected_period, 1)),'Budget Planning'!$E$9:$AS$9,0) ))} | M48: {=IF(is_cat, IF(header_row_id=income_header_row, MATCH(income_min_row,$C:$C,0), IF(header_row_id=expenses_header_row, MATCH(expenses_min_row,$C:$C,0), IF(header_row_id=savings_header_row, MATCH(savings_min_row,$C:$C,0), ""))), "")} | N48: {=IF(is_cat, IF(header_row_id=income_header_row, MATCH(income_max_row,$C:$C,0), IF(header_row_id=expenses_header_row, MATCH(expenses_max_row,$C:$C,0), IF(header_row_id=savings_header_row, MATCH(savings_max_row,$C:$C,0), ""))), "")} | O48: =IF(is_cat, ADDRESS(sort_min_row, COLUMN(tracked)) & ":" & ADDRESS(sort_max_row,COLUMN(tracked)), "") | P48: =IF(is_cat, RANK(tracked, INDIRECT(tracked_range), 0),"") | Q48: =IF(is_cat, ADDRESS(sort_min_row, COLUMN(budget)) & ":" & ADDRESS(sort_max_row,COLUMN(budget)), "") | R48: =IF(is_cat, RANK(budget, INDIRECT(budget_range), 0),"") | S48: =IF(is_cat, _xlfn.NUMBERVALUE(tracked_rank & budget_rank), "") | T48: =IF(is_cat, ADDRESS(sort_min_row, COLUMN(comb_rank)) & ":" & ADDRESS(sort_max_row,COLUMN(comb_rank)), "") | U48: =IF(is_cat, RANK(comb_rank, INDIRECT(comb_rank_range),1), "") | V48: =IF(is_cat, ADDRESS(sort_min_row, COLUMN(comb_rank_norm)) & ":" & ADDRESS(ROW(),COLUMN(comb_rank_norm)), "") | W48: =IF(is_cat,comb_rank_norm + COUNTIF(INDIRECT(comb_rank_norm_run_range),comb_rank_norm)-1, "") | X48: =IF(is_cat, header_row_id + comb_rank_unique, row_id) -> -1 | Y48: =IF(is_empty, "", INDEX($J:$J,MATCH(row_id, $X:$X, 0))) | Z48: =IF(is_empty, "", IF(is_header, "Tracked", INDEX($K:$K, MATCH(row_id, $X:$X,0)))) | AA48: =IF(is_empty, "", IF(is_header, "Budget", INDEX($L:$L, MATCH(row_id, $X:$X,0)))) | AB48: =IF(is_empty, "", IF(is_header, "% Compl.", IFERROR(out_tracked / out_budget, "-"))) | AC48: =IF(is_empty, "", IF(is_header, "Remaining", IF(out_budget - out_tracked > 0, out_budget - out_tracked, 0))) | AD48: =IF(is_empty, "", INDEX($J:$J,MATCH(row_id, $X:$X, 0)))
C49: {=IF(C48=-1,-1, IF(C48<income_max_row,C48+1, IF(C48=income_max_row,income_total_row, IF(C48=income_total_row,"/1", IF(C48="/1",expenses_header_row, IF(C48<expenses_max_row,C48+1, IF(C48=expenses_max_row,expenses_total_row, IF(C48=expenses_total_row,"/2", IF(C48="/2",savings_header_row, IF(C48<savings_max_row,C48+1, IF(C48=savings_max_row,savings_total_row,-1)))))))))))} -> -1 | D49: =IF(is_header,row_id, IF(NOT(is_empty),D48,-1)) -> -1 | E49: FALSE | F49: =1*NOT(OR(is_header,is_total,is_empty)) -> 0 | G49: {=1*OR(row_id=expenses_total_row,row_id=savings_total_row,row_id=income_total_row)} -> 0 | H49: =1*OR(row_id="/1", row_id="/2", row_id=-1) -> 1 | I49: {=IFERROR(INDEX('Budget Planning'!$C:$C, header_row_id), "")} | J49: {=IFERROR(INDEX('Budget Planning'!$C:$C, row_id), "")} | K49: {=IF(OR(is_header, is_empty), "", IF(is_total, IF(selected_period="Total Year", SUM(Tracking[Amount] * (Tracking[Type]=type) * (YEAR(Tracking[Effective Date])=selected_year)), SUM(Tracking[Amount] * (Tracking[Type]=type) * (YEAR(Tracking[Effective Date])=selected_year) * (MONTH(Tracking[Effective Date])=selected_period))), IF(selected_period="Total Year", SUM(Tracking[Amount] * (Tracking[Type]=type) * (Tracking[Category]=item) * (YEAR(Tracking[Effective Date])=selected_year)), SUM(Tracking[Amount] * (Tracking[Type]=type) * (Tracking[Category]=item) * (YEAR(Tracking[Effective Date])=selected_year) * (MONTH(Tracking[Effective Date])=selected_period))) ) )} | L49: {=IF(OR(is_empty,is_header), "", INDEX('Budget Planning'!$E:$AS, row_id, MATCH(IF(selected_period="Total Year", selected_year, DATE(selected_year, selected_period, 1)),'Budget Planning'!$E$9:$AS$9,0) ))} | M49: {=IF(is_cat, IF(header_row_id=income_header_row, MATCH(income_min_row,$C:$C,0), IF(header_row_id=expenses_header_row, MATCH(expenses_min_row,$C:$C,0), IF(header_row_id=savings_header_row, MATCH(savings_min_row,$C:$C,0), ""))), "")} | N49: {=IF(is_cat, IF(header_row_id=income_header_row, MATCH(income_max_row,$C:$C,0), IF(header_row_id=expenses_header_row, MATCH(expenses_max_row,$C:$C,0), IF(header_row_id=savings_header_row, MATCH(savings_max_row,$C:$C,0), ""))), "")} | O49: =IF(is_cat, ADDRESS(sort_min_row, COLUMN(tracked)) & ":" & ADDRESS(sort_max_row,COLUMN(tracked)), "") | P49: =IF(is_cat, RANK(tracked, INDIRECT(tracked_range), 0),"") | Q49: =IF(is_cat, ADDRESS(sort_min_row, COLUMN(budget)) & ":" & ADDRESS(sort_max_row,COLUMN(budget)), "") | R49: =IF(is_cat, RANK(budget, INDIRECT(budget_range), 0),"") | S49: =IF(is_cat, _xlfn.NUMBERVALUE(tracked_rank & budget_rank), "") | T49: =IF(is_cat, ADDRESS(sort_min_row, COLUMN(comb_rank)) & ":" & ADDRESS(sort_max_row,COLUMN(comb_rank)), "") | U49: =IF(is_cat, RANK(comb_rank, INDIRECT(comb_rank_range),1), "") | V49: =IF(is_cat, ADDRESS(sort_min_row, COLUMN(comb_rank_norm)) & ":" & ADDRESS(ROW(),COLUMN(comb_rank_norm)), "") | W49: =IF(is_cat,comb_rank_norm + COUNTIF(INDIRECT(comb_rank_norm_run_range),comb_rank_norm)-1, "") | X49: =IF(is_cat, header_row_id + comb_rank_unique, row_id) -> -1 | Y49: =IF(is_empty, "", INDEX($J:$J,MATCH(row_id, $X:$X, 0))) | Z49: =IF(is_empty, "", IF(is_header, "Tracked", INDEX($K:$K, MATCH(row_id, $X:$X,0)))) | AA49: =IF(is_empty, "", IF(is_header, "Budget", INDEX($L:$L, MATCH(row_id, $X:$X,0)))) | AB49: =IF(is_empty, "", IF(is_header, "% Compl.", IFERROR(out_tracked / out_budget, "-"))) | AC49: =IF(is_empty, "", IF(is_header, "Remaining", IF(out_budget - out_tracked > 0, out_budget - out_tracked, 0))) | AD49: =IF(is_empty, "", INDEX($J:$J,MATCH(row_id, $X:$X, 0)))
C50: {=IF(C49=-1,-1, IF(C49<income_max_row,C49+1, IF(C49=income_max_row,income_total_row, IF(C49=income_total_row,"/1", IF(C49="/1",expenses_header_row, IF(C49<expenses_max_row,C49+1, IF(C49=expenses_max_row,expenses_total_row, IF(C49=expenses_total_row,"/2", IF(C49="/2",savings_header_row, IF(C49<savings_max_row,C49+1, IF(C49=savings_max_row,savings_total_row,-1)))))))))))} -> -1 | D50: =IF(is_header,row_id, IF(NOT(is_empty),D49,-1)) -> -1 | E50: TRUE | F50: =1*NOT(OR(is_header,is_total,is_empty)) -> 0 | G50: {=1*OR(row_id=expenses_total_row,row_id=savings_total_row,row_id=income_total_row)} -> 0 | H50: =1*OR(row_id="/1", row_id="/2", row_id=-1) -> 1 | I50: {=IFERROR(INDEX('Budget Planning'!$C:$C, header_row_id), "")} | J50: {=IFERROR(INDEX('Budget Planning'!$C:$C, row_id), "")} | K50: {=IF(OR(is_header, is_empty), "", IF(is_total, IF(selected_period="Total Year", SUM(Tracking[Amount] * (Tracking[Type]=type) * (YEAR(Tracking[Effective Date])=selected_year)), SUM(Tracking[Amount] * (Tracking[Type]=type) * (YEAR(Tracking[Effective Date])=selected_year) * (MONTH(Tracking[Effective Date])=selected_period))), IF(selected_period="Total Year", SUM(Tracking[Amount] * (Tracking[Type]=type) * (Tracking[Category]=item) * (YEAR(Tracking[Effective Date])=selected_year)), SUM(Tracking[Amount] * (Tracking[Type]=type) * (Tracking[Category]=item) * (YEAR(Tracking[Effective Date])=selected_year) * (MONTH(Tracking[Effective Date])=selected_period))) ) )} | L50: {=IF(OR(is_empty,is_header), "", INDEX('Budget Planning'!$E:$AS, row_id, MATCH(IF(selected_period="Total Year", selected_year, DATE(selected_year, selected_period, 1)),'Budget Planning'!$E$9:$AS$9,0) ))} | M50: {=IF(is_cat, IF(header_row_id=income_header_row, MATCH(income_min_row,$C:$C,0), IF(header_row_id=expenses_header_row, MATCH(expenses_min_row,$C:$C,0), IF(header_row_id=savings_header_row, MATCH(savings_min_row,$C:$C,0), ""))), "")} | N50: {=IF(is_cat, IF(header_row_id=income_header_row, MATCH(income_max_row,$C:$C,0), IF(header_row_id=expenses_header_row, MATCH(expenses_max_row,$C:$C,0), IF(header_row_id=savings_header_row, MATCH(savings_max_row,$C:$C,0), ""))), "")} | O50: =IF(is_cat, ADDRESS(sort_min_row, COLUMN(tracked)) & ":" & ADDRESS(sort_max_row,COLUMN(tracked)), "") | P50: =IF(is_cat, RANK(tracked, INDIRECT(tracked_range), 0),"") | Q50: =IF(is_cat, ADDRESS(sort_min_row, COLUMN(budget)) & ":" & ADDRESS(sort_max_row,COLUMN(budget)), "") | R50: =IF(is_cat, RANK(budget, INDIRECT(budget_range), 0),"") | S50: =IF(is_cat, _xlfn.NUMBERVALUE(tracked_rank & budget_rank), "") | T50: =IF(is_cat, ADDRESS(sort_min_row, COLUMN(comb_rank)) & ":" & ADDRESS(sort_max_row,COLUMN(comb_rank)), "") | U50: =IF(is_cat, RANK(comb_rank, INDIRECT(comb_rank_range),1), "") | V50: =IF(is_cat, ADDRESS(sort_min_row, COLUMN(comb_rank_norm)) & ":" & ADDRESS(ROW(),COLUMN(comb_rank_norm)), "") | W50: =IF(is_cat,comb_rank_norm + COUNTIF(INDIRECT(comb_rank_norm_run_range),comb_rank_norm)-1, "") | X50: =IF(is_cat, header_row_id + comb_rank_unique, row_id) -> -1 | Y50: =IF(is_empty, "", INDEX($J:$J,MATCH(row_id, $X:$X, 0))) | Z50: =IF(is_empty, "", IF(is_header, "Tracked", INDEX($K:$K, MATCH(row_id, $X:$X,0)))) | AA50: =IF(is_empty, "", IF(is_header, "Budget", INDEX($L:$L, MATCH(row_id, $X:$X,0)))) | AB50: =IF(is_empty, "", IF(is_header, "% Compl.", IFERROR(out_tracked / out_budget, "-"))) | AC50: =IF(is_empty, "", IF(is_header, "Remaining", IF(out_budget - out_tracked > 0, out_budget - out_tracked, 0))) | AD50: =IF(is_empty, "", INDEX($J:$J,MATCH(row_id, $X:$X, 0)))
E51: TRUE
E52: TRUE

Sheet Calculations
B1: Calculations
B6: Worksheet: Budget Tracking
D8: Today: | E8: {=current_date} -> 46153 | H8: Today: | I8: {=current_date} -> 46153 | L8: Today: | M8: {=current_date} -> 46153
D9: Last Record: | E9: =MAX(Tracking[Date]) -> 46170 | H9: Last Record: | I9: =MAX(Tracking[Date]) -> 46170 | L9: Last Record: | M9: =MAX(Tracking[Date]) -> 46170
D10: Delta Last Record: | E10: =IF(E9=0,"","("&_xlfn.DAYS(E8,E9)&" days ago)") -> (-17 days ago) | H10: Delta Last Record: | I10: =IF(I9=0,"","("&_xlfn.DAYS(I8,I9)&" days ago)") -> (-17 days ago) | L10: Delta Last Record: | M10: =IF(M9=0,"","("&_xlfn.DAYS(M8,M9)&" days ago)") -> (-17 days ago)
D11: # Records: | E11: =COUNT(Tracking[Date]) -> 346 | H11: # Records: | I11: =COUNT(Tracking[Date]) -> 346 | L11: # Records: | M11: =COUNT(Tracking[Date]) -> 346
D12: # Records this year: | E12: {="(" & SUMPRODUCT(--(YEAR(Tracking[Date])=YEAR(current_date))) & " this year)"} -> (95 this year) | H12: # Records this year: | I12: {="(" & SUMPRODUCT(--(YEAR(Tracking[Date])=YEAR(current_date))) & " this year)"} -> (95 this year) | L12: # Records this year: | M12: {="(" & SUMPRODUCT(--(YEAR(Tracking[Date])=YEAR(current_date))) & " this year)"} -> (95 this year)
D13: Tracking Balance: | E13: =_xlfn.IFNA(INDEX(Tracking[Balance],MATCH(Calculations!E9,Tracking[Date],0)), "-") -> 22766.97 | H13: Tracking Balance: | I13: =_xlfn.IFNA(INDEX(Tracking[Balance],MATCH(Calculations!I9,Tracking[Date],0)), "-") -> 22766.97 | L13: Tracking Balance: | M13: =_xlfn.IFNA(INDEX(Tracking[Balance],MATCH(Calculations!M9,Tracking[Date],0)), "-") -> 22766.97
D14: Balance Analysiis Text: | E14: =IF(E13>=0,"of tracked income left to be allocated", "allocated not covered by income") -> of tracked income left to be allocated | H14: Balance Analysiis Text: | I14: =IF(I13>=0,"of tracked income left to be allocated", "allocated not covered by income") -> of tracked income left to be allocated | L14: Balance Analysiis Text: | M14: =IF(M13>=0,"of tracked income left to be allocated", "allocated not covered by income") -> of tracked income left to be allocated
B17: Worksheet: Budget Tracking
D19: Selected Year: | E19: {=IF('Budget dashboard'!$AQ$6="Current Year", YEAR(current_date), 'Budget dashboard'!$AQ$6)} -> 2026 | H19: Selected Year: | I19: {=IF('Budget dashboard'!$AQ$6="Current Year", YEAR(current_date), 'Budget dashboard'!$AQ$6)} -> 2026 | L19: Selected Year: | M19: {=IF('Budget dashboard'!$AQ$6="Current Year", YEAR(current_date), 'Budget dashboard'!$AQ$6)} -> 2026
D20: Selected Period: | E20: {=IF('Budget dashboard'!$AQ$9="Total Year", "Total Year", IF('Budget dashboard'!$AQ$9="Current Month",MONTH(current_date),MONTH('Budget dashboard'!$AQ$9)))} -> Total Year | H20: Selected Period: | I20: {=IF('Budget dashboard'!$AQ$9="Total Year", "Total Year", IF('Budget dashboard'!$AQ$9="Current Month",MONTH(current_date),MONTH('Budget dashboard'!$AQ$9)))} -> Total Year | L20: Selected Period: | M20: {=IF('Budget dashboard'!$AQ$9="Total Year", "Total Year", IF('Budget dashboard'!$AQ$9="Current Month",MONTH(current_date),MONTH('Budget dashboard'!$AQ$9)))} -> Total Year
D21: Selected Period(Display): | E21: =IF(selected_period="Total Year","Total Year",TEXT(DATE(selected_year,selected_period,1),"mmmm")) -> Total Year | H21: Selected Period(Display): | I21: =IF(selected_period="Total Year","Total Year",TEXT(DATE(selected_year,selected_period,1),"mmmm")) -> Total Year | L21: Selected Period(Display): | M21: =IF(selected_period="Total Year","Total Year",TEXT(DATE(selected_year,selected_period,1),"mmmm")) -> Total Year
D22: Days in Period: | E22: =IF(selected_period="Total Year", DATE(selected_year,12,31) - DATE(selected_year-1,12,31), DAY(EOMONTH(DATE(selected_year,selected_period,1),0))) -> 365
D23: Days passed in Period: | E23: {=IF(selected_year=YEAR(current_date), IF(selected_period="Total Year", current_date-DATE(selected_year-1,12,31), IF(selected_period=MONTH(current_date), DAY(current_date), IF(selected_period<MONTH(current_date), E22,0))), IF(selected_year<YEAR(current_date), E22, 0))} -> 131
D24: Days passed in Period %: | E24: =E23/E22 -> 0.35890411
D25: Period Tracking Balance: | E25: =F41-(J41+N41) -> 10731.24
D26: Balance Analysiis Text: | E26: =IF(E25>=0,"of tracked income left to be allocated", "allocated not covered by income") -> of tracked income left to be allocated
D27: Period Savings Rate: | E27: =IFERROR(IF(savings_rate_calculation_type="% allocated to Savings", N41/F41, (F41-(J41+Q41))/(F41)), "-") -> 0.4703767
D32: Chart Calculations: Category Distribution Charts
D34: Income | E34: Category | F34: Amount | H34: Expenses | I34: Category | J34: Amount | L34: Savings | M34: Category | N34: Amount
D35: 1 | E35: {=IF(F35="", "", INDEX('Budget dashboard'!$J:$J, MATCH(income_header_row + Calculations!D35, 'Budget dashboard'!$X:$X,0)))} -> Empoyment(Net) | F35: {=IF(D35>COUNTA(Income[]),"", IF(INDEX('Budget dashboard'!$K:$K, MATCH(income_header_row + Calculations!D35, 'Budget dashboard'!$X:$X,0))=0, "", INDEX('Budget dashboard'!$K:$K, MATCH(income_header_row + Calculations!D35, 'Budget dashboard'!$X:$X,0))))} -> 47100 | H35: 1 | I35: {=IF(J35="", "", INDEX('Budget dashboard'!$J:$J, MATCH(expenses_header_row + Calculations!H35, 'Budget dashboard'!$X:$X,0)))} -> Housing | J35: {=IF(H35>COUNTA(Expenses[]),"", IF(INDEX('Budget dashboard'!$K:$K, MATCH(expenses_header_row + Calculations!H35, 'Budget dashboard'!$X:$X,0))=0, "", INDEX('Budget dashboard'!$K:$K, MATCH(expenses_header_row + Calculations!H35, 'Budget dashboard'!$X:$X,0))))} -> 17400 | L35: 1 | M35: {=IF(N35="", "", INDEX('Budget dashboard'!$J:$J, MATCH(savings_header_row + Calculations!L35, 'Budget dashboard'!$X:$X,0)))} -> Stock Portfolio | N35: {=IF(L35>COUNTA(Savings[]),"", IF(INDEX('Budget dashboard'!$K:$K, MATCH(savings_header_row + Calculations!L35, 'Budget dashboard'!$X:$X,0))=0, "", INDEX('Budget dashboard'!$K:$K, MATCH(savings_header_row + Calculations!L35, 'Budget dashboard'!$X:$X,0))))} -> 6100
D36: 2 | E36: {=IF(F36="", "", INDEX('Budget dashboard'!$J:$J, MATCH(income_header_row + Calculations!D36, 'Budget dashboard'!$X:$X,0)))} -> Side Hustle(Net) | F36: {=IF(D36>COUNTA(Income[]),"", IF(INDEX('Budget dashboard'!$K:$K, MATCH(income_header_row + Calculations!D36, 'Budget dashboard'!$X:$X,0))=0, "", INDEX('Budget dashboard'!$K:$K, MATCH(income_header_row + Calculations!D36, 'Budget dashboard'!$X:$X,0))))} -> 10931.15 | H36: 2 | I36: {=IF(J36="", "", INDEX('Budget dashboard'!$J:$J, MATCH(expenses_header_row + Calculations!H36, 'Budget dashboard'!$X:$X,0)))} -> Groceries | J36: {=IF(H36>COUNTA(Expenses[]),"", IF(INDEX('Budget dashboard'!$K:$K, MATCH(expenses_header_row + Calculations!H36, 'Budget dashboard'!$X:$X,0))=0, "", INDEX('Budget dashboard'!$K:$K, MATCH(expenses_header_row + Calculations!H36, 'Budget dashboard'!$X:$X,0))))} -> 7300 | L36: 2 | M36: {=IF(N36="", "", INDEX('Budget dashboard'!$J:$J, MATCH(savings_header_row + Calculations!L36, 'Budget dashboard'!$X:$X,0)))} -> Retirement Account | N36: {=IF(L36>COUNTA(Savings[]),"", IF(INDEX('Budget dashboard'!$K:$K, MATCH(savings_header_row + Calculations!L36, 'Budget dashboard'!$X:$X,0))=0, "", INDEX('Budget dashboard'!$K:$K, MATCH(savings_header_row + Calculations!L36, 'Budget dashboard'!$X:$X,0))))} -> 5849.91
D37: 3 | E37: {=IF(F37="", "", INDEX('Budget dashboard'!$J:$J, MATCH(income_header_row + Calculations!D37, 'Budget dashboard'!$X:$X,0)))} -> Dividents | F37: {=IF(D37>COUNTA(Income[]),"", IF(INDEX('Budget dashboard'!$K:$K, MATCH(income_header_row + Calculations!D37, 'Budget dashboard'!$X:$X,0))=0, "", INDEX('Budget dashboard'!$K:$K, MATCH(income_header_row + Calculations!D37, 'Budget dashboard'!$X:$X,0))))} -> 2050 | H37: 3 | I37: {=IF(J37="", "", INDEX('Budget dashboard'!$J:$J, MATCH(expenses_header_row + Calculations!H37, 'Budget dashboard'!$X:$X,0)))} -> Technologies | J37: {=IF(H37>COUNTA(Expenses[]),"", IF(INDEX('Budget dashboard'!$K:$K, MATCH(expenses_header_row + Calculations!H37, 'Budget dashboard'!$X:$X,0))=0, "", INDEX('Budget dashboard'!$K:$K, MATCH(expenses_header_row + Calculations!H37, 'Budget dashboard'!$X:$X,0))))} -> 2800 | L37: 3 | M37: {=IF(N37="", "", INDEX('Budget dashboard'!$J:$J, MATCH(savings_header_row + Calculations!L37, 'Budget dashboard'!$X:$X,0)))} -> Emergency Fund | N37: {=IF(L37>COUNTA(Savings[]),"", IF(INDEX('Budget dashboard'!$K:$K, MATCH(savings_header_row + Calculations!L37, 'Budget dashboard'!$X:$X,0))=0, "", INDEX('Budget dashboard'!$K:$K, MATCH(savings_header_row + Calculations!L37, 'Budget dashboard'!$X:$X,0))))} -> 5200
D38: 4 | E38: {=IF(F38="", "", INDEX('Budget dashboard'!$J:$J, MATCH(income_header_row + Calculations!D38, 'Budget dashboard'!$X:$X,0)))} -> Other | F38: {=IF(D38>COUNTA(Income[]),"", IF(INDEX('Budget dashboard'!$K:$K, MATCH(income_header_row + Calculations!D38, 'Budget dashboard'!$X:$X,0))=0, "", INDEX('Budget dashboard'!$K:$K, MATCH(income_header_row + Calculations!D38, 'Budget dashboard'!$X:$X,0))))} -> 1000 | H38: 4 | I38: {=IF(J38="", "", INDEX('Budget dashboard'!$J:$J, MATCH(expenses_header_row + Calculations!H38, 'Budget dashboard'!$X:$X,0)))} -> Transport | J38: {=IF(H38>COUNTA(Expenses[]),"", IF(INDEX('Budget dashboard'!$K:$K, MATCH(expenses_header_row + Calculations!H38, 'Budget dashboard'!$X:$X,0))=0, "", INDEX('Budget dashboard'!$K:$K, MATCH(expenses_header_row + Calculations!H38, 'Budget dashboard'!$X:$X,0))))} -> 2800 | L38: 4 | M38: {=IF(N38="", "", INDEX('Budget dashboard'!$J:$J, MATCH(savings_header_row + Calculations!L38, 'Budget dashboard'!$X:$X,0)))} -> Other | N38: {=IF(L38>COUNTA(Savings[]),"", IF(INDEX('Budget dashboard'!$K:$K, MATCH(savings_header_row + Calculations!L38, 'Budget dashboard'!$X:$X,0))=0, "", INDEX('Budget dashboard'!$K:$K, MATCH(savings_header_row + Calculations!L38, 'Budget dashboard'!$X:$X,0))))} -> 850
D39: 5 | E39: {=IF(F39="", "", INDEX('Budget dashboard'!$J:$J, MATCH(income_header_row + Calculations!D39, 'Budget dashboard'!$X:$X,0)))} | F39: {=IF(D39>COUNTA(Income[]),"", IF(INDEX('Budget dashboard'!$K:$K, MATCH(income_header_row + Calculations!D39, 'Budget dashboard'!$X:$X,0))=0, "", INDEX('Budget dashboard'!$K:$K, MATCH(income_header_row + Calculations!D39, 'Budget dashboard'!$X:$X,0))))} | H39: 5 | I39: {=IF(J39="", "", INDEX('Budget dashboard'!$J:$J, MATCH(expenses_header_row + Calculations!H39, 'Budget dashboard'!$X:$X,0)))} -> Other | J39: {=IF(H39>COUNTA(Expenses[]),"", IF(INDEX('Budget dashboard'!$K:$K, MATCH(expenses_header_row + Calculations!H39, 'Budget dashboard'!$X:$X,0))=0, "", INDEX('Budget dashboard'!$K:$K, MATCH(expenses_header_row + Calculations!H39, 'Budget dashboard'!$X:$X,0))))} -> 1100 | L39: 5 | M39: {=IF(N39="", "", INDEX('Budget dashboard'!$J:$J, MATCH(savings_header_row + Calculations!L39, 'Budget dashboard'!$X:$X,0)))} | N39: {=IF(L39>COUNTA(Savings[]),"", IF(INDEX('Budget dashboard'!$K:$K, MATCH(savings_header_row + Calculations!L39, 'Budget dashboard'!$X:$X,0))=0, "", INDEX('Budget dashboard'!$K:$K, MATCH(savings_header_row + Calculations!L39, 'Budget dashboard'!$X:$X,0))))}
D40: 6 | E40: =IF(F40="", "", "Other") -> Other | F40: =IF(F41-SUM(F35:F39)=0, "",F41-SUM(F35:F39)) -> -7.2759576e-12 | H40: 6 | I40: =IF(J40="", "", "Other") -> Other | J40: =IF(J41-SUM(J35:J39)=0, "",J41-SUM(J35:J39)) -> 950 | L40: 6 | M40: =IF(N40="", "", "Other") | N40: =IF(N41-SUM(N35:N39)=0, "",N41-SUM(N35:N39))
E41: Total | F41: {=INDEX('Budget dashboard'!$K:$K, MATCH(income_total_row, 'Budget dashboard'!$X:$X,0))} -> 61081.15 | I41: Total | J41: {=INDEX('Budget dashboard'!$K:$K, MATCH(expenses_total_row, 'Budget dashboard'!$X:$X,0))} -> 32350 | M41: Total | N41: {=INDEX('Budget dashboard'!$K:$K, MATCH(savings_total_row, 'Budget dashboard'!$X:$X,0))} -> 17999.91
D47: Chart Calculations: Tracked(vs. Budget) Chart
D49: Show Income: | E49: TRUE
D50: Show Expenses: | E50: TRUE
D51: Show Savings: | E51: TRUE
D52: Show Remaining Budget: | E52: TRUE
M53: Period in Focus | P53: Period not in Focus
D54: Month | E54: Type | F54: Month Num. | G54: In Focus | H54: Show Type | I54: Show Rem. Budget | J54: Tracked | K54: Budget | L54: Delta | M54: In Budget | N54: Remaining | O54: Excess | P54: In Budget | Q54: Remaining | R54: Excess
D55: =DATE(selected_year,1,1) -> 46023 | E55: Income | F55: =MONTH(D55) -> 1 | G55: =IF(selected_period="Total Year", 1, IF(selected_period=cc_month_number,1,0)) -> 1 | H55: =1*$E$49 -> 1 | I55: =1*$E$52 -> 1 | J55: {=SUM(Tracking[Amount] * (Tracking[Type]=cc_type) * (YEAR(Tracking[Effective Date])=selected_year) * (MONTH(Tracking[Effective Date])=cc_month_number))} -> 10531.15 | K55: {=INDEX('Budget Planning'!$E:$AS, income_total_row, MATCH(DATE(selected_year, cc_month_number, 1),'Budget Planning'!$E$9:$AS$9,0) )} -> 9900 | L55: =cc_budget-cc_tracked -> -631.15 | M55: =cc_in_focus*cc_show_type*MIN(cc_tracked, cc_budget) -> 9900 | N55: =cc_in_focus*cc_show_type*cc_show_rem_budget*IF(cc_delta>0,cc_delta,0) -> 0 | O55: =cc_in_focus*cc_show_type*IF(cc_delta<0, ABS(cc_delta),0) -> 631.15 | P55: =NOT(cc_in_focus)*cc_show_type*MIN(cc_tracked, cc_budget) -> 0 | Q55: =NOT(cc_in_focus)*cc_show_type*cc_show_rem_budget*IF(cc_delta>0,cc_delta,0) -> 0 | R55: =NOT(cc_in_focus)*cc_show_type*IF(cc_delta<0, ABS(cc_delta),0) -> 0
E56: Expenses | F56: =MONTH(D55) -> 1 | G56: =IF(selected_period="Total Year", 1, IF(selected_period=cc_month_number,1,0)) -> 1 | H56: =1*$E$50 -> 1 | I56: =1*$E$52 -> 1 | J56: {=SUM(Tracking[Amount] * (Tracking[Type]=cc_type) * (YEAR(Tracking[Effective Date])=selected_year) * (MONTH(Tracking[Effective Date])=cc_month_number))} -> 5200 | K56: {=INDEX('Budget Planning'!$E:$AS, expenses_total_row, MATCH(DATE(selected_year, cc_month_number, 1),'Budget Planning'!$E$9:$AS$9,0) )} -> 6400 | L56: =cc_budget-cc_tracked -> 1200 | M56: =cc_in_focus*cc_show_type*MIN(cc_tracked, cc_budget) -> 5200 | N56: =cc_in_focus*cc_show_type*cc_show_rem_budget*IF(cc_delta>0,cc_delta,0) -> 1200 | O56: =cc_in_focus*cc_show_type*IF(cc_delta<0, ABS(cc_delta),0) -> 0 | P56: =NOT(cc_in_focus)*cc_show_type*MIN(cc_tracked, cc_budget) -> 0 | Q56: =NOT(cc_in_focus)*cc_show_type*cc_show_rem_budget*IF(cc_delta>0,cc_delta,0) -> 0 | R56: =NOT(cc_in_focus)*cc_show_type*IF(cc_delta<0, ABS(cc_delta),0) -> 0
E57: Savings | F57: =MONTH(D55) -> 1 | G57: =IF(selected_period="Total Year", 1, IF(selected_period=cc_month_number,1,0)) -> 1 | H57: =1*$E$51 -> 1 | I57: =1*$E$52 -> 1 | J57: {=SUM(Tracking[Amount] * (Tracking[Type]=cc_type) * (YEAR(Tracking[Effective Date])=selected_year) * (MONTH(Tracking[Effective Date])=cc_month_number))} -> 3950 | K57: {=INDEX('Budget Planning'!$E:$AS, savings_total_row, MATCH(DATE(selected_year, cc_month_number, 1),'Budget Planning'!$E$9:$AS$9,0) )} -> 3500 | L57: =cc_budget-cc_tracked -> -450 | M57: =cc_in_focus*cc_show_type*MIN(cc_tracked, cc_budget) -> 3500 | N57: =cc_in_focus*cc_show_type*cc_show_rem_budget*IF(cc_delta>0,cc_delta,0) -> 0 | O57: =cc_in_focus*cc_show_type*IF(cc_delta<0, ABS(cc_delta),0) -> 450 | P57: =NOT(cc_in_focus)*cc_show_type*MIN(cc_tracked, cc_budget) -> 0 | Q57: =NOT(cc_in_focus)*cc_show_type*cc_show_rem_budget*IF(cc_delta>0,cc_delta,0) -> 0 | R57: =NOT(cc_in_focus)*cc_show_type*IF(cc_delta<0, ABS(cc_delta),0) -> 0
D59: =DATE(selected_year,2,1) -> 46054 | E59: Income | F59: =MONTH(D59) -> 2 | G59: =IF(selected_period="Total Year", 1, IF(selected_period=cc_month_number,1,0)) -> 1 | H59: =1*$E$49 -> 1 | I59: =1*$E$52 -> 1 | J59: {=SUM(Tracking[Amount] * (Tracking[Type]=cc_type) * (YEAR(Tracking[Effective Date])=selected_year) * (MONTH(Tracking[Effective Date])=cc_month_number))} -> 12120.56 | K59: {=INDEX('Budget Planning'!$E:$AS, income_total_row, MATCH(DATE(selected_year, cc_month_number, 1),'Budget Planning'!$E$9:$AS$9,0) )} -> 10600 | L59: =cc_budget-cc_tracked -> -1520.56 | M59: =cc_in_focus*cc_show_type*MIN(cc_tracked, cc_budget) -> 10600 | N59: =cc_in_focus*cc_show_type*cc_show_rem_budget*IF(cc_delta>0,cc_delta,0) -> 0 | O59: =cc_in_focus*cc_show_type*IF(cc_delta<0, ABS(cc_delta),0) -> 1520.56 | P59: =NOT(cc_in_focus)*cc_show_type*MIN(cc_tracked, cc_budget) -> 0 | Q59: =NOT(cc_in_focus)*cc_show_type*cc_show_rem_budget*IF(cc_delta>0,cc_delta,0) -> 0 | R59: =NOT(cc_in_focus)*cc_show_type*IF(cc_delta<0, ABS(cc_delta),0) -> 0
E60: Expenses | F60: =MONTH(D59) -> 2 | G60: =IF(selected_period="Total Year", 1, IF(selected_period=cc_month_number,1,0)) -> 1 | H60: =1*$E$50 -> 1 | I60: =1*$E$52 -> 1 | J60: {=SUM(Tracking[Amount] * (Tracking[Type]=cc_type) * (YEAR(Tracking[Effective Date])=selected_year) * (MONTH(Tracking[Effective Date])=cc_month_number))} -> 3700 | K60: {=INDEX('Budget Planning'!$E:$AS, expenses_total_row, MATCH(DATE(selected_year, cc_month_number, 1),'Budget Planning'!$E$9:$AS$9,0) )} -> 6300 | L60: =cc_budget-cc_tracked -> 2600 | M60: =cc_in_focus*cc_show_type*MIN(cc_tracked, cc_budget) -> 3700 | N60: =cc_in_focus*cc_show_type*cc_show_rem_budget*IF(cc_delta>0,cc_delta,0) -> 2600 | O60: =cc_in_focus*cc_show_type*IF(cc_delta<0, ABS(cc_delta),0) -> 0 | P60: =NOT(cc_in_focus)*cc_show_type*MIN(cc_tracked, cc_budget) -> 0 | Q60: =NOT(cc_in_focus)*cc_show_type*cc_show_rem_budget*IF(cc_delta>0,cc_delta,0) -> 0 | R60: =NOT(cc_in_focus)*cc_show_type*IF(cc_delta<0, ABS(cc_delta),0) -> 0
E61: Savings | F61: =MONTH(D59) -> 2 | G61: =IF(selected_period="Total Year", 1, IF(selected_period=cc_month_number,1,0)) -> 1 | H61: =1*$E$51 -> 1 | I61: =1*$E$52 -> 1 | J61: {=SUM(Tracking[Amount] * (Tracking[Type]=cc_type) * (YEAR(Tracking[Effective Date])=selected_year) * (MONTH(Tracking[Effective Date])=cc_month_number))} -> 4100 | K61: {=INDEX('Budget Planning'!$E:$AS, savings_total_row, MATCH(DATE(selected_year, cc_month_number, 1),'Budget Planning'!$E$9:$AS$9,0) )} -> 3700 | L61: =cc_budget-cc_tracked -> -400 | M61: =cc_in_focus*cc_show_type*MIN(cc_tracked, cc_budget) -> 3700 | N61: =cc_in_focus*cc_show_type*cc_show_rem_budget*IF(cc_delta>0,cc_delta,0) -> 0 | O61: =cc_in_focus*cc_show_type*IF(cc_delta<0, ABS(cc_delta),0) -> 400 | P61: =NOT(cc_in_focus)*cc_show_type*MIN(cc_tracked, cc_budget) -> 0 | Q61: =NOT(cc_in_focus)*cc_show_type*cc_show_rem_budget*IF(cc_delta>0,cc_delta,0) -> 0 | R61: =NOT(cc_in_focus)*cc_show_type*IF(cc_delta<0, ABS(cc_delta),0) -> 0
D63: =DATE(selected_year,3,1) -> 46082 | E63: Income | F63: =MONTH(D63) -> 3 | G63: =IF(selected_period="Total Year", 1, IF(selected_period=cc_month_number,1,0)) -> 1 | H63: =1*$E$49 -> 1 | I63: =1*$E$52 -> 1 | J63: {=SUM(Tracking[Amount] * (Tracking[Type]=cc_type) * (YEAR(Tracking[Effective Date])=selected_year) * (MONTH(Tracking[Effective Date])=cc_month_number))} -> 6297.85 | K63: {=INDEX('Budget Planning'!$E:$AS, income_total_row, MATCH(DATE(selected_year, cc_month_number, 1),'Budget Planning'!$E$9:$AS$9,0) )} -> 12350 | L63: =cc_budget-cc_tracked -> 6052.15 | M63: =cc_in_focus*cc_show_type*MIN(cc_tracked, cc_budget) -> 6297.85 | N63: =cc_in_focus*cc_show_type*cc_show_rem_budget*IF(cc_delta>0,cc_delta,0) -> 6052.15 | O63: =cc_in_focus*cc_show_type*IF(cc_delta<0, ABS(cc_delta),0) -> 0 | P63: =NOT(cc_in_focus)*cc_show_type*MIN(cc_tracked, cc_budget) -> 0 | Q63: =NOT(cc_in_focus)*cc_show_type*cc_show_rem_budget*IF(cc_delta>0,cc_delta,0) -> 0 | R63: =NOT(cc_in_focus)*cc_show_type*IF(cc_delta<0, ABS(cc_delta),0) -> 0
E64: Expenses | F64: =MONTH(D63) -> 3 | G64: =IF(selected_period="Total Year", 1, IF(selected_period=cc_month_number,1,0)) -> 1 | H64: =1*$E$50 -> 1 | I64: =1*$E$52 -> 1 | J64: {=SUM(Tracking[Amount] * (Tracking[Type]=cc_type) * (YEAR(Tracking[Effective Date])=selected_year) * (MONTH(Tracking[Effective Date])=cc_month_number))} -> 7300 | K64: {=INDEX('Budget Planning'!$E:$AS, expenses_total_row, MATCH(DATE(selected_year, cc_month_number, 1),'Budget Planning'!$E$9:$AS$9,0) )} -> 8250 | L64: =cc_budget-cc_tracked -> 950 | M64: =cc_in_focus*cc_show_type*MIN(cc_tracked, cc_budget) -> 7300 | N64: =cc_in_focus*cc_show_type*cc_show_rem_budget*IF(cc_delta>0,cc_delta,0) -> 950 | O64: =cc_in_focus*cc_show_type*IF(cc_delta<0, ABS(cc_delta),0) -> 0 | P64: =NOT(cc_in_focus)*cc_show_type*MIN(cc_tracked, cc_budget) -> 0 | Q64: =NOT(cc_in_focus)*cc_show_type*cc_show_rem_budget*IF(cc_delta>0,cc_delta,0) -> 0 | R64: =NOT(cc_in_focus)*cc_show_type*IF(cc_delta<0, ABS(cc_delta),0) -> 0
E65: Savings | F65: =MONTH(D63) -> 3 | G65: =IF(selected_period="Total Year", 1, IF(selected_period=cc_month_number,1,0)) -> 1 | H65: =1*$E$51 -> 1 | I65: =1*$E$52 -> 1 | J65: {=SUM(Tracking[Amount] * (Tracking[Type]=cc_type) * (YEAR(Tracking[Effective Date])=selected_year) * (MONTH(Tracking[Effective Date])=cc_month_number))} -> 2600 | K65: {=INDEX('Budget Planning'!$E:$AS, savings_total_row, MATCH(DATE(selected_year, cc_month_number, 1),'Budget Planning'!$E$9:$AS$9,0) )} -> 3750 | L65: =cc_budget-cc_tracked -> 1150 | M65: =cc_in_focus*cc_show_type*MIN(cc_tracked, cc_budget) -> 2600 | N65: =cc_in_focus*cc_show_type*cc_show_rem_budget*IF(cc_delta>0,cc_delta,0) -> 1150 | O65: =cc_in_focus*cc_show_type*IF(cc_delta<0, ABS(cc_delta),0) -> 0 | P65: =NOT(cc_in_focus)*cc_show_type*MIN(cc_tracked, cc_budget) -> 0 | Q65: =NOT(cc_in_focus)*cc_show_type*cc_show_rem_budget*IF(cc_delta>0,cc_delta,0) -> 0 | R65: =NOT(cc_in_focus)*cc_show_type*IF(cc_delta<0, ABS(cc_delta),0) -> 0
D67: =DATE(selected_year,4,1) -> 46113 | E67: Income | F67: =MONTH(D67) -> 4 | G67: =IF(selected_period="Total Year", 1, IF(selected_period=cc_month_number,1,0)) -> 1 | H67: =1*$E$49 -> 1 | I67: =1*$E$52 -> 1 | J67: {=SUM(Tracking[Amount] * (Tracking[Type]=cc_type) * (YEAR(Tracking[Effective Date])=selected_year) * (MONTH(Tracking[Effective Date])=cc_month_number))} -> 13585.37 | K67: {=INDEX('Budget Planning'!$E:$AS, income_total_row, MATCH(DATE(selected_year, cc_month_number, 1),'Budget Planning'!$E$9:$AS$9,0) )} -> 10700 | L67: =cc_budget-cc_tracked -> -2885.37 | M67: =cc_in_focus*cc_show_type*MIN(cc_tracked, cc_budget) -> 10700 | N67: =cc_in_focus*cc_show_type*cc_show_rem_budget*IF(cc_delta>0,cc_delta,0) -> 0 | O67: =cc_in_focus*cc_show_type*IF(cc_delta<0, ABS(cc_delta),0) -> 2885.37 | P67: =NOT(cc_in_focus)*cc_show_type*MIN(cc_tracked, cc_budget) -> 0 | Q67: =NOT(cc_in_focus)*cc_show_type*cc_show_rem_budget*IF(cc_delta>0,cc_delta,0) -> 0 | R67: =NOT(cc_in_focus)*cc_show_type*IF(cc_delta<0, ABS(cc_delta),0) -> 0
E68: Expenses | F68: =MONTH(D67) -> 4 | G68: =IF(selected_period="Total Year", 1, IF(selected_period=cc_month_number,1,0)) -> 1 | H68: =1*$E$50 -> 1 | I68: =1*$E$52 -> 1 | J68: {=SUM(Tracking[Amount] * (Tracking[Type]=cc_type) * (YEAR(Tracking[Effective Date])=selected_year) * (MONTH(Tracking[Effective Date])=cc_month_number))} -> 7150 | K68: {=INDEX('Budget Planning'!$E:$AS, expenses_total_row, MATCH(DATE(selected_year, cc_month_number, 1),'Budget Planning'!$E$9:$AS$9,0) )} -> 6500 | L68: =cc_budget-cc_tracked -> -650 | M68: =cc_in_focus*cc_show_type*MIN(cc_tracked, cc_budget) -> 6500 | N68: =cc_in_focus*cc_show_type*cc_show_rem_budget*IF(cc_delta>0,cc_delta,0) -> 0 | O68: =cc_in_focus*cc_show_type*IF(cc_delta<0, ABS(cc_delta),0) -> 650 | P68: =NOT(cc_in_focus)*cc_show_type*MIN(cc_tracked, cc_budget) -> 0 | Q68: =NOT(cc_in_focus)*cc_show_type*cc_show_rem_budget*IF(cc_delta>0,cc_delta,0) -> 0 | R68: =NOT(cc_in_focus)*cc_show_type*IF(cc_delta<0, ABS(cc_delta),0) -> 0
E69: Savings | F69: =MONTH(D67) -> 4 | G69: =IF(selected_period="Total Year", 1, IF(selected_period=cc_month_number,1,0)) -> 1 | H69: =1*$E$51 -> 1 | I69: =1*$E$52 -> 1 | J69: {=SUM(Tracking[Amount] * (Tracking[Type]=cc_type) * (YEAR(Tracking[Effective Date])=selected_year) * (MONTH(Tracking[Effective Date])=cc_month_number))} -> 3628.61 | K69: {=INDEX('Budget Planning'!$E:$AS, savings_total_row, MATCH(DATE(selected_year, cc_month_number, 1),'Budget Planning'!$E$9:$AS$9,0) )} -> 3550 | L69: =cc_budget-cc_tracked -> -78.61 | M69: =cc_in_focus*cc_show_type*MIN(cc_tracked, cc_budget) -> 3550 | N69: =cc_in_focus*cc_show_type*cc_show_rem_budget*IF(cc_delta>0,cc_delta,0) -> 0 | O69: =cc_in_focus*cc_show_type*IF(cc_delta<0, ABS(cc_delta),0) -> 78.61 | P69: =NOT(cc_in_focus)*cc_show_type*MIN(cc_tracked, cc_budget) -> 0 | Q69: =NOT(cc_in_focus)*cc_show_type*cc_show_rem_budget*IF(cc_delta>0,cc_delta,0) -> 0 | R69: =NOT(cc_in_focus)*cc_show_type*IF(cc_delta<0, ABS(cc_delta),0) -> 0
